{
  "list_total_count": 1,
  "RESULT": {
    "RESULT.CODE": "INFO-000",
    "RESULT.MESSAGE": "정상 처리되었습니다."
  },
  "CITYDATA": {
    "AREA_NM": "고척돔",
    "AREA_CD": "POI086",
    "LIVE_PPLTN_STTS": [
      {
        "AREA_NM": "고척돔",
        "AREA_CD": "POI086",
        "AREA_CONGEST_LVL": "여유",
        "AREA_CONGEST_MSG": "사람이 몰려있을 가능성이 낮고 붐빔은 거의 느껴지지 않아요. 도보 이동이 자유로워요.",
        "AREA_PPLTN_MIN": "1000",
        "AREA_PPLTN_MAX": "1500",
        "MALE_PPLTN_RATE": "45.4",
        "FEMALE_PPLTN_RATE": "54.6",
        "PPLTN_RATE_0": "1.7",
        "PPLTN_RATE_10": "43.6",
        "PPLTN_RATE_20": "8.1",
        "PPLTN_RATE_30": "10.0",
        "PPLTN_RATE_40": "9.1",
        "PPLTN_RATE_50": "9.5",
        "PPLTN_RATE_60": "10.2",
        "PPLTN_RATE_70": "7.8",
        "RESNT_PPLTN_RATE": "11.2",
        "NON_RESNT_PPLTN_RATE": "88.8",
        "REPLACE_YN": "N",
        "PPLTN_TIME": "2025-04-21 12:40",
        "FCST_YN": "Y",
        "FCST_PPLTN": [
          {
            "FCST_TIME": "2025-04-21 14:00",
            "FCST_CONGEST_LVL": "여유",
            "FCST_PPLTN_MIN": "1000",
            "FCST_PPLTN_MAX": "1500"
          },
          {
            "FCST_TIME": "2025-04-21 15:00",
            "FCST_CONGEST_LVL": "여유",
            "FCST_PPLTN_MIN": "1000",
            "FCST_PPLTN_MAX": "1500"
          },
          {
            "FCST_TIME": "2025-04-21 16:00",
            "FCST_CONGEST_LVL": "여유",
            "FCST_PPLTN_MIN": "900",
            "FCST_PPLTN_MAX": "1000"
          },
          {
            "FCST_TIME": "2025-04-21 17:00",
            "FCST_CONGEST_LVL": "여유",
            "FCST_PPLTN_MIN": "900",
            "FCST_PPLTN_MAX": "1000"
          },
          {
            "FCST_TIME": "2025-04-21 18:00",
            "FCST_CONGEST_LVL": "여유",
            "FCST_PPLTN_MIN": "800",
            "FCST_PPLTN_MAX": "900"
          },
          {
            "FCST_TIME": "2025-04-21 19:00",
            "FCST_CONGEST_LVL": "여유",
            "FCST_PPLTN_MIN": "800",
            "FCST_PPLTN_MAX": "900"
          },
          {
            "FCST_TIME": "2025-04-21 20:00",
            "FCST_CONGEST_LVL": "여유",
            "FCST_PPLTN_MIN": "800",
            "FCST_PPLTN_MAX": "900"
          },
          {
            "FCST_TIME": "2025-04-21 21:00",
            "FCST_CONGEST_LVL": "여유",
            "FCST_PPLTN_MIN": "800",
            "FCST_PPLTN_MAX": "900"
          },
          {
            "FCST_TIME": "2025-04-21 22:00",
            "FCST_CONGEST_LVL": "여유",
            "FCST_PPLTN_MIN": "800",
            "FCST_PPLTN_MAX": "900"
          },
          {
            "FCST_TIME": "2025-04-21 23:00",
            "FCST_CONGEST_LVL": "여유",
            "FCST_PPLTN_MIN": "700",
            "FCST_PPLTN_MAX": "800"
          },
          {
            "FCST_TIME": "2025-04-22 00:00",
            "FCST_CONGEST_LVL": "여유",
            "FCST_PPLTN_MIN": "700",
            "FCST_PPLTN_MAX": "800"
          },
          {
            "FCST_TIME": "2025-04-22 01:00",
            "FCST_CONGEST_LVL": "여유",
            "FCST_PPLTN_MIN": "500",
            "FCST_PPLTN_MAX": "600"
          }
        ]
      }
    ],
    "ROAD_TRAFFIC_STTS": {
      "AVG_ROAD_DATA": {
        "ROAD_MSG": "해당 장소로 이동·진입하는 도로가 크게 막히지 않아요.",
        "ROAD_TRAFFIC_IDX": "원활",
        "ROAD_TRAFFIC_SPD": 29,
        "ROAD_TRAFFIC_TIME": "2025-04-21 13:00"
      },
      "ROAD_TRAFFIC_STTS": [
        {
          "LINK_ID": "1160001507",
          "ROAD_NM": "경인로",
          "START_ND_CD": "1160025201",
          "START_ND_NM": "구로소방서앞교차로",
          "START_ND_XY": "126.8646648841337594_37.4977851484350779",
          "END_ND_CD": "1160026900",
          "END_ND_NM": "구로소방서앞",
          "END_ND_XY": "126.8650285338268446_37.4980826026535183",
          "DIST": "46.0",
          "SPD": 20.0,
          "IDX": "서행",
          "XYLIST": "126.8649799291234501_37.4981203226791351|126.8646162794395167_37.4978228692140050"
        },
        {
          "LINK_ID": "1160001607",
          "ROAD_NM": "경인로",
          "START_ND_CD": "1160025201",
          "START_ND_NM": "구로소방서앞교차로",
          "START_ND_XY": "126.8646648841337594_37.4977851484350779",
          "END_ND_CD": "1160025200",
          "END_ND_NM": "라미우드빌딩",
          "END_ND_XY": "126.8640829390592870_37.4973091294691798",
          "DIST": "74.0",
          "SPD": 35.0,
          "IDX": "원활",
          "XYLIST": "126.8641315448181786_37.4972714089075723|126.8647134899099598_37.4977474276371012"
        },
        {
          "LINK_ID": "1160001608",
          "ROAD_NM": "경인로",
          "START_ND_CD": "1160026900",
          "START_ND_NM": "구로소방서앞",
          "START_ND_XY": "126.8650285338268446_37.4980826026535183",
          "END_ND_CD": "1160025201",
          "END_ND_NM": "구로소방서앞교차로",
          "END_ND_XY": "126.8646648841337594_37.4977851484350779",
          "DIST": "46.0",
          "SPD": 16.0,
          "IDX": "서행",
          "XYLIST": "126.8647134899099598_37.4977474276371012|126.8650771396138595_37.4980448817078411"
        },
        {
          "LINK_ID": "1160001901",
          "ROAD_NM": "경인로",
          "START_ND_CD": "1160029300",
          "START_ND_NM": "고척교교차로",
          "START_ND_XY": "126.8717925408608664_37.4988847412315067",
          "END_ND_CD": "1160030600",
          "END_ND_NM": "동양미래대학앞교차로",
          "END_ND_XY": "126.8688356362250431_37.4995692282665161",
          "DIST": "278.0",
          "SPD": 19.0,
          "IDX": "서행",
          "XYLIST": "126.8688159124106534_37.4995175021602236|126.8711528967156568_37.4989518486928404|126.8715231913182890_37.4988650895980484|126.8718322311354001_37.4988219851025306"
        },
        {
          "LINK_ID": "1160002001",
          "ROAD_NM": "경인로",
          "START_ND_CD": "1160030600",
          "START_ND_NM": "동양미래대학앞교차로",
          "START_ND_XY": "126.8688356362250431_37.4995692282665161",
          "END_ND_CD": "1160029300",
          "END_ND_NM": "고척교교차로",
          "END_ND_XY": "126.8717925408608664_37.4988847412315067",
          "DIST": "276.0",
          "SPD": 26.0,
          "IDX": "원활",
          "XYLIST": "126.8718556324660938_37.4989284859377676|126.8715541336007533_37.4989705391101751|126.8711911831498753_37.4990555772781562|126.8688553589356900_37.4996209543678560"
        },
        {
          "LINK_ID": "1160002102",
          "ROAD_NM": "경인로",
          "START_ND_CD": "1160026900",
          "START_ND_NM": "구로소방서앞",
          "START_ND_XY": "126.8650285338268446_37.4980826026535183",
          "END_ND_CD": "1160030700",
          "END_ND_NM": "동양공업전문대학",
          "END_ND_XY": "126.8676243754692337_37.4996624998838897",
          "DIST": "298.0",
          "SPD": 20.0,
          "IDX": "서행",
          "XYLIST": "126.8676099764367535_37.4997153286241556|126.8673777511500731_37.4996751499945233|126.8671788695642988_37.4996233133504546|126.8669493159061687_37.4995461947532931|126.8667640607105227_37.4994684400143257|126.8665382770592061_37.4993469206109040|126.8663359449855790_37.4992109715771136|126.8649803288655278_37.4981206474980979"
        },
        {
          "LINK_ID": "1160002103",
          "ROAD_NM": "경인로",
          "START_ND_CD": "1160030700",
          "START_ND_NM": "동양공업전문대학",
          "START_ND_XY": "126.8676243754692337_37.4996624998838897",
          "END_ND_CD": "1160030600",
          "END_ND_NM": "동양미래대학앞교차로",
          "END_ND_XY": "126.8688356362250431_37.4995692282665161",
          "DIST": "110.0",
          "SPD": 14.0,
          "IDX": "정체",
          "XYLIST": "126.8688489015588772_37.4996222455480819|126.8683211920548217_37.4997060593014453|126.8680553720287776_37.4997276688494807|126.8678007834513579_37.4997347598521955|126.8676158646967735_37.4997161335138145"
        },
        {
          "LINK_ID": "1160002201",
          "ROAD_NM": "경인로",
          "START_ND_CD": "1160030700",
          "START_ND_NM": "동양공업전문대학",
          "START_ND_XY": "126.8676243754692337_37.4996624998838897",
          "END_ND_CD": "1160026900",
          "END_ND_NM": "구로소방서앞",
          "END_ND_XY": "126.8650285338268446_37.4980826026535183",
          "DIST": "291.0",
          "SPD": 20.0,
          "IDX": "서행",
          "XYLIST": "126.8650767398717107_37.4980445568892122|126.8664280783672780_37.4991314413069787|126.8666202355497035_37.4992605526787202|126.8668338770472133_37.4993755367621020|126.8670074112473145_37.4994483731235846|126.8672264118405764_37.4995219460046627|126.8674133406793061_37.4995706669926818|126.8676387744812928_37.4996096711413571"
        },
        {
          "LINK_ID": "1160002202",
          "ROAD_NM": "경인로",
          "START_ND_CD": "1160030600",
          "START_ND_NM": "동양미래대학앞교차로",
          "START_ND_XY": "126.8688356362250431_37.4995692282665161",
          "END_ND_CD": "1160030700",
          "END_ND_NM": "동양공업전문대학",
          "END_ND_XY": "126.8676243754692337_37.4996624998838897",
          "DIST": "106.0",
          "SPD": 24.0,
          "IDX": "서행",
          "XYLIST": "126.8676328862293730_37.4996088662528422|126.8678069625456857_37.4996264010276690|126.8680461031747626_37.4996197405567102|126.8683009934756853_37.4995990198500522|126.8688223697773907_37.4995162118827423"
        },
        {
          "LINK_ID": "1160014101",
          "ROAD_NM": "중앙로",
          "START_ND_CD": "1160026900",
          "START_ND_NM": "구로소방서앞",
          "START_ND_XY": "126.8650285338268446_37.4980826026535183",
          "END_ND_CD": "1160031500",
          "END_ND_NM": "윈골프클럽",
          "END_ND_XY": "126.8637827021795204_37.5003394530817289",
          "DIST": "274.0",
          "SPD": 14.0,
          "IDX": "정체",
          "XYLIST": "126.8637206123964347_37.5003176483187346|126.8647512731021010_37.4984547270839172|126.8649663184724119_37.4980610299531065"
        },
        {
          "LINK_ID": "1160014202",
          "ROAD_NM": "중앙로",
          "START_ND_CD": "1160031500",
          "START_ND_NM": "윈골프클럽",
          "START_ND_XY": "126.8637827021795204_37.5003394530817289",
          "END_ND_CD": "1160026900",
          "END_ND_NM": "구로소방서앞",
          "END_ND_XY": "126.8650285338268446_37.4980826026535183",
          "DIST": "274.0",
          "SPD": 13.0,
          "IDX": "정체",
          "XYLIST": "126.8650907503496370_37.4981041744214352|126.8648755784311248_37.4984981040910128|126.8638447919971526_37.5003612587131130"
        },
        {
          "LINK_ID": "1160015701",
          "ROAD_NM": "안양천로537길",
          "START_ND_CD": "1160030600",
          "START_ND_NM": "동양미래대학앞교차로",
          "START_ND_XY": "126.8688356362250431_37.4995692282665161",
          "END_ND_CD": "1160038400",
          "END_ND_NM": "고척지하차도북측",
          "END_ND_XY": "126.8699822605182987_37.5023690923755026",
          "DIST": "327.0",
          "SPD": 30.0,
          "IDX": "원활",
          "XYLIST": "126.8698525249542399_37.5024008234713904|126.8694643346875210_37.5013934109902394|126.8687070400427928_37.4996037687232757"
        },
        {
          "LINK_ID": "1160015801",
          "ROAD_NM": "안양천로537길",
          "START_ND_CD": "1160038400",
          "START_ND_NM": "고척지하차도북측",
          "START_ND_XY": "126.8699822605182987_37.5023690923755026",
          "END_ND_CD": "1160030600",
          "END_ND_NM": "동양미래대학앞교차로",
          "END_ND_XY": "126.8688356362250431_37.4995692282665161",
          "DIST": "327.0",
          "SPD": 37.5,
          "IDX": "원활",
          "XYLIST": "126.8689642311583157_37.4995346876680884|126.8697227149842348_37.5013271263434547|126.8701119971038764_37.5023373611380109"
        },
        {
          "LINK_ID": "1160049000",
          "ROAD_NM": "안양천로",
          "START_ND_CD": "1160026000",
          "START_ND_NM": "고척지하차도남측",
          "START_ND_XY": "126.8681526068122736_37.4980497949056542",
          "END_ND_CD": "2130015800",
          "END_ND_NM": "구로구-광명시",
          "END_ND_XY": "126.8682412616270483_37.4953596196274361",
          "DIST": "307.0",
          "SPD": 60.0,
          "IDX": "원활",
          "XYLIST": "126.8683154861628140_37.4953380557123168|126.8680791301081570_37.4959108832984143|126.8680192247021239_37.4961901165675542|126.8679713339188453_37.4963936246526259|126.8679416938823437_37.4965988803425390|126.8679353024971164_37.4968807087750235|126.8679467286440712_37.4970971053372253|126.8679814883963815_37.4974018031208942|126.8680806147528557_37.4977290078190819|126.8682164931662868_37.4980315829806869"
        },
        {
          "LINK_ID": "1160049100",
          "ROAD_NM": "안양천로",
          "START_ND_CD": "2130015800",
          "START_ND_NM": "구로구-광명시",
          "START_ND_XY": "126.8682412616270483_37.4953596196274361",
          "END_ND_CD": "1160026000",
          "END_ND_NM": "고척지하차도남측",
          "END_ND_XY": "126.8681526068122736_37.4980497949056542",
          "DIST": "311.0",
          "SPD": 54.6,
          "IDX": "원활",
          "XYLIST": "126.8680887215597437_37.4980680058961937|126.8679504014649098_37.4977599920923339|126.8678472427124149_37.4974194749191909|126.8678112852119142_37.4971042754339194|126.8677995486469570_37.4968820057548768|126.8678061330137012_37.4965917080895466|126.8678370716341277_37.4963774627470841|126.8678856475315513_37.4961710443316889|126.8679464131163144_37.4958878080200222|126.8681782355385650_37.4953336183588917"
        },
        {
          "LINK_ID": "1160054400",
          "ROAD_NM": "안양천로",
          "START_ND_CD": "1160030600",
          "START_ND_NM": "동양미래대학앞교차로",
          "START_ND_XY": "126.8688356362250431_37.4995692282665161",
          "END_ND_CD": "1160026000",
          "END_ND_NM": "고척지하차도남측",
          "END_ND_XY": "126.8681526068122736_37.4980497949056542",
          "DIST": "179.0",
          "SPD": 32.0,
          "IDX": "원활",
          "XYLIST": "126.8682803637142484_37.4980133385672829|126.8689633953864444_37.4995327721041605"
        },
        {
          "LINK_ID": "1160054500",
          "ROAD_NM": "안양천로",
          "START_ND_CD": "1160026000",
          "START_ND_NM": "고척지하차도남측",
          "START_ND_XY": "126.8681526068122736_37.4980497949056542",
          "END_ND_CD": "1160030600",
          "END_ND_NM": "동양미래대학앞교차로",
          "END_ND_XY": "126.8688356362250431_37.4995692282665161",
          "DIST": "179.0",
          "SPD": 40.0,
          "IDX": "원활",
          "XYLIST": "126.8687078758073028_37.4996056851899837|126.8680248497880001_37.4980862502043735"
        },
        {
          "LINK_ID": "1160058300",
          "ROAD_NM": "경인로47길",
          "START_ND_CD": "1160030700",
          "START_ND_NM": "동양공업전문대학",
          "START_ND_XY": "126.8676243754692337_37.4996624998838897",
          "END_ND_CD": "1160031100",
          "END_ND_NM": "의성빌딩",
          "END_ND_XY": "126.8670209070231749_37.5001327623784988",
          "DIST": "75.0",
          "SPD": 6.0,
          "IDX": "정체",
          "XYLIST": "126.8669734779148968_37.5000941026965435|126.8673517388977388_37.4997995352371589|126.8675769033132070_37.4996238737300800"
        },
        {
          "LINK_ID": "1160058400",
          "ROAD_NM": "경인로47길",
          "START_ND_CD": "1160031100",
          "START_ND_NM": "의성빌딩",
          "START_ND_XY": "126.8670209070231749_37.5001327623784988",
          "END_ND_CD": "1160030700",
          "END_ND_NM": "동양공업전문대학",
          "END_ND_XY": "126.8676243754692337_37.4996624998838897",
          "DIST": "75.0",
          "SPD": 13.0,
          "IDX": "정체",
          "XYLIST": "126.8676718488050028_37.4997011260197226|126.8674466402152063_37.4998768209931157|126.8670683361787326_37.5001714229422660"
        },
        {
          "LINK_ID": "1160061600",
          "ROAD_NM": "안양천로",
          "START_ND_CD": "1160038400",
          "START_ND_NM": "고척지하차도북측",
          "START_ND_XY": "126.8699822605182987_37.5023690923755026",
          "END_ND_CD": "1160026000",
          "END_ND_NM": "고척지하차도남측",
          "END_ND_XY": "126.8681526068122736_37.4980497949056542",
          "DIST": "506.0",
          "SPD": 53.0,
          "IDX": "원활",
          "XYLIST": "126.8682164864111712_37.4980315658540704|126.8688997309864703_37.4995514775238874|126.8696581199527316_37.5013436975582763|126.8700471288247513_37.5023532267746091"
        },
        {
          "LINK_ID": "1160061700",
          "ROAD_NM": "안양천로",
          "START_ND_CD": "1160026000",
          "START_ND_NM": "고척지하차도남측",
          "START_ND_XY": "126.8681526068122736_37.4980497949056542",
          "END_ND_CD": "1160038400",
          "END_ND_NM": "고척지하차도북측",
          "END_ND_XY": "126.8699822605182987_37.5023690923755026",
          "DIST": "506.0",
          "SPD": 54.4,
          "IDX": "원활",
          "XYLIST": "126.8699173921845045_37.5023849579406843|126.8695289298043605_37.5013768398816794|126.8687715403008980_37.4995869798739818|126.8680887283148309_37.4980680230228387"
        },
        {
          "LINK_ID": "1160270800",
          "ROAD_NM": "경인로46길",
          "START_ND_CD": "1160025201",
          "START_ND_NM": "구로소방서앞교차로",
          "START_ND_XY": "126.8646648841337594_37.4977851484350779",
          "END_ND_CD": "1160117800",
          "END_ND_NM": "경인고등학교",
          "END_ND_XY": "126.8652605625586602_37.4955707025299247",
          "DIST": "259.0",
          "SPD": 22.0,
          "IDX": "서행",
          "XYLIST": "126.8653271725092821_37.4955809886835780|126.8651773693918727_37.4961968050555399|126.8650154908807366_37.4969853923834933|126.8649780725493486_37.4973595364734464|126.8649652366451903_37.4974365415857633|126.8649243678425194_37.4976454128913019|126.8647141565926830_37.4978223154982686"
        },
        {
          "LINK_ID": "1160270900",
          "ROAD_NM": "경인로46길",
          "START_ND_CD": "1160117800",
          "START_ND_NM": "경인고등학교",
          "START_ND_XY": "126.8652605625586602_37.4955707025299247",
          "END_ND_CD": "1160025201",
          "END_ND_NM": "구로소방서앞교차로",
          "END_ND_XY": "126.8646648841337594_37.4977851484350779",
          "DIST": "252.0",
          "SPD": 61.0,
          "IDX": "원활",
          "XYLIST": "126.8646156128545499_37.4977479813524823|126.8647967893811312_37.4975955125061731|126.8648309175753610_37.4974210952033573|126.8648430814129284_37.4973481177339067|126.8648806639174325_37.4969723502616148|126.8650437702182217_37.4961777890482040|126.8651939526264556_37.4955604163387122"
        }
      ]
    },
    "PRK_STTS": [],
    "SUB_STTS": [
      {
        "SUB_STN_NM": "구일",
        "SUB_STN_LINE": "1",
        "SUB_STN_RADDR": "서울 구로구 구일로 133",
        "SUB_STN_JIBUN": "서울 구로구 구로동 636-45",
        "SUB_STN_X": "126.86969110539",
        "SUB_STN_Y": "37.496254517687",
        "SUB_DETAIL": [
          {
            "SUB_NT_STN": "1001000141",
            "SUB_BF_STN": "1001000143",
            "SUB_ROUTE_NM": "양주행 - 구로방면",
            "SUB_LINE": "1호선",
            "SUB_ORD": "01000양주0",
            "SUB_DIR": "상행",
            "SUB_TERMINAL": "양주",
            "SUB_ARVTIME": "0",
            "SUB_ARMG1": "구일 도착",
            "SUB_ARMG2": "구일",
            "SUB_ARVINFO": "도착"
          },
          {
            "SUB_NT_STN": "1001000141",
            "SUB_BF_STN": "1001000143",
            "SUB_ROUTE_NM": "동두천행 - 구로방면 (급행)",
            "SUB_LINE": "1호선",
            "SUB_ORD": "01006동두천1",
            "SUB_DIR": "상행",
            "SUB_TERMINAL": "동두천",
            "SUB_ARVTIME": "0",
            "SUB_ARMG1": "[6]번째 전역 (부천)",
            "SUB_ARMG2": "부천",
            "SUB_ARVINFO": "운행중"
          },
          {
            "SUB_NT_STN": "1001000141",
            "SUB_BF_STN": "1001000143",
            "SUB_ROUTE_NM": "의정부행 - 구로방면",
            "SUB_LINE": "1호선",
            "SUB_ORD": "02013의정부0",
            "SUB_DIR": "상행",
            "SUB_TERMINAL": "의정부",
            "SUB_ARVTIME": "0",
            "SUB_ARMG1": "[13]번째 전역 (간석)",
            "SUB_ARMG2": "간석",
            "SUB_ARVINFO": "운행중"
          },
          {
            "SUB_NT_STN": "1001000141",
            "SUB_BF_STN": "1001000143",
            "SUB_ROUTE_NM": "용산행 - 구로방면 (급행)",
            "SUB_LINE": "1호선",
            "SUB_ORD": "02018용산1",
            "SUB_DIR": "상행",
            "SUB_TERMINAL": "용산",
            "SUB_ARVTIME": "0",
            "SUB_ARMG1": "[18]번째 전역 (동인천)",
            "SUB_ARMG2": "동인천",
            "SUB_ARVINFO": "운행중"
          },
          {
            "SUB_NT_STN": "1001000143",
            "SUB_BF_STN": "1001000141",
            "SUB_ROUTE_NM": "동인천행 - 개봉방면",
            "SUB_LINE": "1호선",
            "SUB_ORD": "11000동인천0",
            "SUB_DIR": "하행",
            "SUB_TERMINAL": "동인천",
            "SUB_ARVTIME": "0",
            "SUB_ARMG1": "구일 도착",
            "SUB_ARMG2": "영등포",
            "SUB_ARVINFO": "도착"
          },
          {
            "SUB_NT_STN": "1001000143",
            "SUB_BF_STN": "1001000141",
            "SUB_ROUTE_NM": "인천행 - 개봉방면",
            "SUB_LINE": "1호선",
            "SUB_ORD": "11000인천0",
            "SUB_DIR": "하행",
            "SUB_TERMINAL": "인천",
            "SUB_ARVTIME": "0",
            "SUB_ARMG1": "구일 도착",
            "SUB_ARMG2": "영등포",
            "SUB_ARVINFO": "도착"
          },
          {
            "SUB_NT_STN": "1001000143",
            "SUB_BF_STN": "1001000141",
            "SUB_ROUTE_NM": "인천행 - 개봉방면",
            "SUB_LINE": "1호선",
            "SUB_ORD": "12004인천0",
            "SUB_DIR": "하행",
            "SUB_TERMINAL": "인천",
            "SUB_ARVTIME": "0",
            "SUB_ARMG1": "[4]번째 전역 (용산)",
            "SUB_ARMG2": "용산",
            "SUB_ARVINFO": "운행중"
          },
          {
            "SUB_NT_STN": "1001000143",
            "SUB_BF_STN": "1001000141",
            "SUB_ROUTE_NM": "인천행 - 개봉방면",
            "SUB_LINE": "1호선",
            "SUB_ORD": "12038인천0",
            "SUB_DIR": "하행",
            "SUB_TERMINAL": "인천",
            "SUB_ARVTIME": "0",
            "SUB_ARMG1": "[38]번째 전역 (동두천)",
            "SUB_ARMG2": "동두천",
            "SUB_ARVINFO": "운행중"
          }
        ],
        "SUB_FACIINFO": []
      }
    ],
    "BUS_STN_STTS": [
      {
        "BUS_RESULT_MSG": "정상 호출되었습니다.",
        "BUS_STN_ID": "116000007",
        "BUS_ARS_ID": "17007",
        "BUS_STN_NM": "동양미래대학.구로성심병원",
        "BUS_STN_X": "126.8679976691",
        "BUS_STN_Y": "37.4996343963",
        "BUS_DETAIL": [
          {
            "RTE_STN_NM": "동양미래대학.구로성심병원",
            "RTE_NM": "160",
            "RTE_ID": "100100033",
            "RTE_SECT": "구일역.중앙유통상가.롯데마트~동양미래대학.구로성심병원",
            "RTE_CONGEST_1": "여유",
            "RTE_ARRV_TM_1": "5분24초후[2번째 전]",
            "RTE_ARRV_STN_1": "신도림동.구로역",
            "RTE_CONGEST_2": "여유",
            "RTE_ARRV_TM_2": "12분12초후[4번째 전]",
            "RTE_ARRV_STN_2": "문래동남성아파트"
          },
          {
            "RTE_STN_NM": "동양미래대학.구로성심병원",
            "RTE_NM": "600",
            "RTE_ID": "100100085",
            "RTE_SECT": "구일역.중앙유통상가.롯데마트~동양미래대학.구로성심병원",
            "RTE_CONGEST_1": "여유",
            "RTE_ARRV_TM_1": "곧 도착",
            "RTE_ARRV_STN_1": "동양미래대학.구로성심병원",
            "RTE_CONGEST_2": "여유",
            "RTE_ARRV_TM_2": "12분12초후[4번째 전]",
            "RTE_ARRV_STN_2": "문래동남성아파트"
          },
          {
            "RTE_STN_NM": "동양미래대학.구로성심병원",
            "RTE_NM": "660",
            "RTE_ID": "116000004",
            "RTE_SECT": "구일역.중앙유통상가.롯데마트~동양미래대학.구로성심병원",
            "RTE_CONGEST_1": "여유",
            "RTE_ARRV_TM_1": "곧 도착",
            "RTE_ARRV_STN_1": "동양미래대학.구로성심병원",
            "RTE_CONGEST_2": "여유",
            "RTE_ARRV_TM_2": "13분11초후[5번째 전]",
            "RTE_ARRV_STN_2": "남부지방법원등기국.구로세무서(에이스하이테크시티)"
          },
          {
            "RTE_STN_NM": "동양미래대학.구로성심병원",
            "RTE_NM": "662",
            "RTE_ID": "100100550",
            "RTE_SECT": "구일역.중앙유통상가.롯데마트~동양미래대학.구로성심병원",
            "RTE_CONGEST_1": "여유",
            "RTE_ARRV_TM_1": "5분3초후[1번째 전]",
            "RTE_ARRV_STN_1": "구일역.중앙유통상가",
            "RTE_CONGEST_2": "여유",
            "RTE_ARRV_TM_2": "15분58초후[6번째 전]",
            "RTE_ARRV_STN_2": "영등포역"
          },
          {
            "RTE_STN_NM": "동양미래대학.구로성심병원",
            "RTE_NM": "N16",
            "RTE_ID": "100100592",
            "RTE_SECT": "구일역.중앙유통상가.롯데마트~동양미래대학.구로성심병원",
            "RTE_CONGEST_1": "정보없음",
            "RTE_ARRV_TM_1": "운행종료",
            "RTE_ARRV_STN_1": null,
            "RTE_CONGEST_2": "정보없음",
            "RTE_ARRV_TM_2": "운행종료",
            "RTE_ARRV_STN_2": null
          },
          {
            "RTE_STN_NM": "동양미래대학.구로성심병원",
            "RTE_NM": "5626",
            "RTE_ID": "100100282",
            "RTE_SECT": "구일역.중앙유통상가.롯데마트~동양미래대학.구로성심병원",
            "RTE_CONGEST_1": "여유",
            "RTE_ARRV_TM_1": "10분26초후[3번째 전]",
            "RTE_ARRV_STN_1": "구로구청",
            "RTE_CONGEST_2": "여유",
            "RTE_ARRV_TM_2": "20분19초후[9번째 전]",
            "RTE_ARRV_STN_2": "디지털단지오거리"
          },
          {
            "RTE_STN_NM": "동양미래대학.구로성심병원",
            "RTE_NM": "5712",
            "RTE_ID": "100100286",
            "RTE_SECT": "구일역.중앙유통상가.롯데마트~동양미래대학.구로성심병원",
            "RTE_CONGEST_1": "여유",
            "RTE_ARRV_TM_1": "3분33초후[1번째 전]",
            "RTE_ARRV_STN_1": "구일역.중앙유통상가",
            "RTE_CONGEST_2": "여유",
            "RTE_ARRV_TM_2": "10분21초후[4번째 전]",
            "RTE_ARRV_STN_2": "구로119안전센터"
          },
          {
            "RTE_STN_NM": "동양미래대학.구로성심병원",
            "RTE_NM": "6511",
            "RTE_ID": "100100291",
            "RTE_SECT": "구일역.중앙유통상가.롯데마트~동양미래대학.구로성심병원",
            "RTE_CONGEST_1": "여유",
            "RTE_ARRV_TM_1": "19분10초후[8번째 전]",
            "RTE_ARRV_STN_1": "한국SGI",
            "RTE_CONGEST_2": "여유",
            "RTE_ARRV_TM_2": "39분43초후[19번째 전]",
            "RTE_ARRV_STN_2": "신대방역"
          },
          {
            "RTE_STN_NM": "동양미래대학.구로성심병원",
            "RTE_NM": "6515",
            "RTE_ID": "100100521",
            "RTE_SECT": "구일역.중앙유통상가.롯데마트~동양미래대학.구로성심병원",
            "RTE_CONGEST_1": "여유",
            "RTE_ARRV_TM_1": "5분24초후[2번째 전]",
            "RTE_ARRV_STN_1": "신도림동.구로역",
            "RTE_CONGEST_2": "여유",
            "RTE_ARRV_TM_2": "15분4초후[6번째 전]",
            "RTE_ARRV_STN_2": "경방타임스퀘어.신세계백화점"
          },
          {
            "RTE_STN_NM": "동양미래대학.구로성심병원",
            "RTE_NM": "6637",
            "RTE_ID": "100100312",
            "RTE_SECT": "구일역.중앙유통상가.롯데마트~동양미래대학.구로성심병원",
            "RTE_CONGEST_1": "여유",
            "RTE_ARRV_TM_1": "2분48초후[1번째 전]",
            "RTE_ARRV_STN_1": "구일역.중앙유통상가",
            "RTE_CONGEST_2": "여유",
            "RTE_ARRV_TM_2": "9분48초후[3번째 전]",
            "RTE_ARRV_STN_2": "신도림역"
          },
          {
            "RTE_STN_NM": "동양미래대학.구로성심병원",
            "RTE_NM": "6640A",
            "RTE_ID": "100100601",
            "RTE_SECT": "구일역.중앙유통상가.롯데마트~동양미래대학.구로성심병원",
            "RTE_CONGEST_1": "여유",
            "RTE_ARRV_TM_1": "10분34초후[4번째 전]",
            "RTE_ARRV_STN_1": "문래동남성아파트",
            "RTE_CONGEST_2": "여유",
            "RTE_ARRV_TM_2": "23분51초후[11번째 전]",
            "RTE_ARRV_STN_2": "관악고등학교"
          },
          {
            "RTE_STN_NM": "동양미래대학.구로성심병원",
            "RTE_NM": "6713",
            "RTE_ID": "100100293",
            "RTE_SECT": "구일역.중앙유통상가.롯데마트~동양미래대학.구로성심병원",
            "RTE_CONGEST_1": "여유",
            "RTE_ARRV_TM_1": "9분45초후[3번째 전]",
            "RTE_ARRV_STN_1": "신도림역",
            "RTE_CONGEST_2": "여유",
            "RTE_ARRV_TM_2": "19분26초후[7번째 전]",
            "RTE_ARRV_STN_2": "신길5동주민센터"
          },
          {
            "RTE_STN_NM": "동양미래대학.구로성심병원",
            "RTE_NM": "10부천",
            "RTE_ID": "212000003",
            "RTE_SECT": "구일역.중앙유통상가.롯데마트~동양미래대학.구로성심병원",
            "RTE_CONGEST_1": "",
            "RTE_ARRV_TM_1": "곧 도착",
            "RTE_ARRV_STN_1": "동양미래대학.구로성심병원",
            "RTE_CONGEST_2": "",
            "RTE_ARRV_TM_2": "17분22초후[7번째 전]",
            "RTE_ARRV_STN_2": "영등포로터리(미정차)"
          },
          {
            "RTE_STN_NM": "동양미래대학.구로성심병원",
            "RTE_NM": "301안산",
            "RTE_ID": "216000021",
            "RTE_SECT": "구일역.중앙유통상가.롯데마트~동양미래대학.구로성심병원",
            "RTE_CONGEST_1": "",
            "RTE_ARRV_TM_1": "21분41초후[11번째 전]",
            "RTE_ARRV_STN_1": "한국거래소",
            "RTE_CONGEST_2": "",
            "RTE_ARRV_TM_2": "55분51초후[23번째 전]",
            "RTE_ARRV_STN_2": "현대아파트.개봉중앙시장"
          },
          {
            "RTE_STN_NM": "동양미래대학.구로성심병원",
            "RTE_NM": "320안산",
            "RTE_ID": "217000013",
            "RTE_SECT": "구일역.중앙유통상가.롯데마트~동양미래대학.구로성심병원",
            "RTE_CONGEST_1": "",
            "RTE_ARRV_TM_1": "18분42초후[9번째 전]",
            "RTE_ARRV_STN_1": "여의도공원1번출입구",
            "RTE_CONGEST_2": "",
            "RTE_ARRV_TM_2": "47분10초후[20번째 전]",
            "RTE_ARRV_STN_2": "구일역.제일제당"
          },
          {
            "RTE_STN_NM": "동양미래대학.구로성심병원",
            "RTE_NM": "5200시흥",
            "RTE_ID": "224000052",
            "RTE_SECT": "구일역.중앙유통상가.롯데마트~동양미래대학.구로성심병원",
            "RTE_CONGEST_1": "",
            "RTE_ARRV_TM_1": "18분47초후[4번째 전]",
            "RTE_ARRV_STN_1": "신도림동.구로역",
            "RTE_CONGEST_2": "",
            "RTE_ARRV_TM_2": "39분42초후[8번째 전]",
            "RTE_ARRV_STN_2": "오류동역"
          },
          {
            "RTE_STN_NM": "동양미래대학.구로성심병원",
            "RTE_NM": "530시흥",
            "RTE_ID": "224000029",
            "RTE_SECT": "구일역.중앙유통상가.롯데마트~동양미래대학.구로성심병원",
            "RTE_CONGEST_1": "",
            "RTE_ARRV_TM_1": "곧 도착",
            "RTE_ARRV_STN_1": "동양미래대학.구로성심병원",
            "RTE_CONGEST_2": "",
            "RTE_ARRV_TM_2": "33분14초후[14번째 전]",
            "RTE_ARRV_STN_2": "한국경제인협회"
          },
          {
            "RTE_STN_NM": "동양미래대학.구로성심병원",
            "RTE_NM": "83부천",
            "RTE_ID": "212000002",
            "RTE_SECT": "구일역.중앙유통상가.롯데마트~동양미래대학.구로성심병원",
            "RTE_CONGEST_1": "",
            "RTE_ARRV_TM_1": "곧 도착",
            "RTE_ARRV_STN_1": "동양미래대학.구로성심병원",
            "RTE_CONGEST_2": "",
            "RTE_ARRV_TM_2": "15분32초후[6번째 전]",
            "RTE_ARRV_STN_2": "영등포역"
          },
          {
            "RTE_STN_NM": "동양미래대학.구로성심병원",
            "RTE_NM": "88부천",
            "RTE_ID": "212000001",
            "RTE_SECT": "구일역.중앙유통상가.롯데마트~동양미래대학.구로성심병원",
            "RTE_CONGEST_1": "",
            "RTE_ARRV_TM_1": "3분21초후[1번째 전]",
            "RTE_ARRV_STN_1": "구일역.중앙유통상가",
            "RTE_CONGEST_2": "",
            "RTE_ARRV_TM_2": "7분27초후[2번째 전]",
            "RTE_ARRV_STN_2": "신도림동.구로역"
          }
        ]
      },
      {
        "BUS_RESULT_MSG": "정상 호출되었습니다.",
        "BUS_STN_ID": "116000008",
        "BUS_ARS_ID": "17008",
        "BUS_STN_NM": "동양미래대학.구로성심병원",
        "BUS_STN_X": "126.8670186731",
        "BUS_STN_Y": "37.4993764843",
        "BUS_DETAIL": [
          {
            "RTE_STN_NM": "동양미래대학.구로성심병원",
            "RTE_NM": "160",
            "RTE_ID": "100100033",
            "RTE_SECT": "개봉역.한마을아파트~동양미래대학.구로성심병원",
            "RTE_CONGEST_1": "여유",
            "RTE_ARRV_TM_1": "7분14초후[2번째 전]",
            "RTE_ARRV_STN_1": "경인중학교.개봉사거리",
            "RTE_CONGEST_2": "여유",
            "RTE_ARRV_TM_2": "13분25초후[8번째 전]",
            "RTE_ARRV_STN_2": "우신고등학교"
          },
          {
            "RTE_STN_NM": "동양미래대학.구로성심병원",
            "RTE_NM": "600",
            "RTE_ID": "100100085",
            "RTE_SECT": "고척중학교~동양미래대학.구로성심병원",
            "RTE_CONGEST_1": "여유",
            "RTE_ARRV_TM_1": "4분58초후[1번째 전]",
            "RTE_ARRV_STN_1": "고척중학교",
            "RTE_CONGEST_2": "여유",
            "RTE_ARRV_TM_2": "12분2초후[5번째 전]",
            "RTE_ARRV_STN_2": "세곡초등학교"
          },
          {
            "RTE_STN_NM": "동양미래대학.구로성심병원",
            "RTE_NM": "660",
            "RTE_ID": "116000004",
            "RTE_SECT": "개봉역.한마을아파트~동양미래대학.구로성심병원",
            "RTE_CONGEST_1": "여유",
            "RTE_ARRV_TM_1": "3분46초후[1번째 전]",
            "RTE_ARRV_STN_1": "개봉역.한마을아파트",
            "RTE_CONGEST_2": "여유",
            "RTE_ARRV_TM_2": "17분47초후[10번째 전]",
            "RTE_ARRV_STN_2": "항동하버라인10단지"
          },
          {
            "RTE_STN_NM": "동양미래대학.구로성심병원",
            "RTE_NM": "662",
            "RTE_ID": "100100550",
            "RTE_SECT": "개봉역.한마을아파트~동양미래대학.구로성심병원",
            "RTE_CONGEST_1": "여유",
            "RTE_ARRV_TM_1": "14분22초후[6번째 전]",
            "RTE_ARRV_STN_1": "강신중학교",
            "RTE_CONGEST_2": "여유",
            "RTE_ARRV_TM_2": "18분27초후[10번째 전]",
            "RTE_ARRV_STN_2": "푸른마을1단지아파트"
          },
          {
            "RTE_STN_NM": "동양미래대학.구로성심병원",
            "RTE_NM": "N16",
            "RTE_ID": "100100592",
            "RTE_SECT": "개봉역.한마을아파트~동양미래대학.구로성심병원",
            "RTE_CONGEST_1": "정보없음",
            "RTE_ARRV_TM_1": "운행종료",
            "RTE_ARRV_STN_1": "온수동종점",
            "RTE_CONGEST_2": "정보없음",
            "RTE_ARRV_TM_2": "운행종료",
            "RTE_ARRV_STN_2": "오류동역"
          },
          {
            "RTE_STN_NM": "동양미래대학.구로성심병원",
            "RTE_NM": "5626",
            "RTE_ID": "100100282",
            "RTE_SECT": "개봉역.한마을아파트~동양미래대학.구로성심병원",
            "RTE_CONGEST_1": "여유",
            "RTE_ARRV_TM_1": "13분26초후[7번째 전]",
            "RTE_ARRV_STN_1": "개봉1동사거리.개봉푸르지오아파트",
            "RTE_CONGEST_2": "여유",
            "RTE_ARRV_TM_2": "17분40초후[9번째 전]",
            "RTE_ARRV_STN_2": "오류동역"
          },
          {
            "RTE_STN_NM": "동양미래대학.구로성심병원",
            "RTE_NM": "5712",
            "RTE_ID": "100100286",
            "RTE_SECT": "고척중학교~동양미래대학.구로성심병원",
            "RTE_CONGEST_1": "여유",
            "RTE_ARRV_TM_1": "4분46초후[1번째 전]",
            "RTE_ARRV_STN_1": "고척중학교",
            "RTE_CONGEST_2": "여유",
            "RTE_ARRV_TM_2": "10분17초후[5번째 전]",
            "RTE_ARRV_STN_2": "신트리사거리"
          },
          {
            "RTE_STN_NM": "동양미래대학.구로성심병원",
            "RTE_NM": "6511",
            "RTE_ID": "100100291",
            "RTE_SECT": "고척중학교~동양미래대학.구로성심병원",
            "RTE_CONGEST_1": "정보없음",
            "RTE_ARRV_TM_1": "출발대기",
            "RTE_ARRV_STN_1": null,
            "RTE_CONGEST_2": "정보없음",
            "RTE_ARRV_TM_2": "출발대기",
            "RTE_ARRV_STN_2": null
          },
          {
            "RTE_STN_NM": "동양미래대학.구로성심병원",
            "RTE_NM": "6515",
            "RTE_ID": "100100521",
            "RTE_SECT": "고척중학교~동양미래대학.구로성심병원",
            "RTE_CONGEST_1": "여유",
            "RTE_ARRV_TM_1": "곧 도착",
            "RTE_ARRV_STN_1": "동양미래대학.구로성심병원",
            "RTE_CONGEST_2": "여유",
            "RTE_ARRV_TM_2": "6분53초후[2번째 전]",
            "RTE_ARRV_STN_2": "고척시장"
          },
          {
            "RTE_STN_NM": "동양미래대학.구로성심병원",
            "RTE_NM": "6637",
            "RTE_ID": "100100312",
            "RTE_SECT": "개봉역.한마을아파트~동양미래대학.구로성심병원",
            "RTE_CONGEST_1": "여유",
            "RTE_ARRV_TM_1": "2분49초후[1번째 전]",
            "RTE_ARRV_STN_1": "개봉역.한마을아파트",
            "RTE_CONGEST_2": "여유",
            "RTE_ARRV_TM_2": "7분20초후[3번째 전]",
            "RTE_ARRV_STN_2": "현대아파트.개봉중앙시장"
          },
          {
            "RTE_STN_NM": "동양미래대학.구로성심병원",
            "RTE_NM": "6640B",
            "RTE_ID": "100100602",
            "RTE_SECT": "개봉역.한마을아파트~동양미래대학.구로성심병원",
            "RTE_CONGEST_1": "여유",
            "RTE_ARRV_TM_1": "곧 도착",
            "RTE_ARRV_STN_1": "동양미래대학.구로성심병원",
            "RTE_CONGEST_2": "여유",
            "RTE_ARRV_TM_2": "8분25초후[3번째 전]",
            "RTE_ARRV_STN_2": "오류1동주민센터.오류문화센터"
          },
          {
            "RTE_STN_NM": "동양미래대학.구로성심병원",
            "RTE_NM": "6713",
            "RTE_ID": "100100293",
            "RTE_SECT": "개봉역.한마을아파트~동양미래대학.구로성심병원",
            "RTE_CONGEST_1": "여유",
            "RTE_ARRV_TM_1": "6분36초후[3번째 전]",
            "RTE_ARRV_STN_1": "현대아파트.개봉중앙시장",
            "RTE_CONGEST_2": "정보없음",
            "RTE_ARRV_TM_2": "출발대기",
            "RTE_ARRV_STN_2": null
          },
          {
            "RTE_STN_NM": "동양미래대학.구로성심병원",
            "RTE_NM": "10부천",
            "RTE_ID": "212000003",
            "RTE_SECT": "개봉역.한마을아파트~동양미래대학.구로성심병원",
            "RTE_CONGEST_1": "",
            "RTE_ARRV_TM_1": "5분35초후[2번째 전]",
            "RTE_ARRV_STN_1": "경인중학교.개봉사거리",
            "RTE_CONGEST_2": "",
            "RTE_ARRV_TM_2": "10분49초후[5번째 전]",
            "RTE_ARRV_STN_2": "씨티월드"
          },
          {
            "RTE_STN_NM": "동양미래대학.구로성심병원",
            "RTE_NM": "301안산",
            "RTE_ID": "216000021",
            "RTE_SECT": "개봉역.한마을아파트~동양미래대학.구로성심병원",
            "RTE_CONGEST_1": "",
            "RTE_ARRV_TM_1": "6분7초후[2번째 전]",
            "RTE_ARRV_STN_1": "현대아파트.개봉중앙시장",
            "RTE_CONGEST_2": "",
            "RTE_ARRV_TM_2": "53분47초후[28번째 전]",
            "RTE_ARRV_STN_2": "식물원건너편"
          },
          {
            "RTE_STN_NM": "동양미래대학.구로성심병원",
            "RTE_NM": "301안산",
            "RTE_ID": "216000021",
            "RTE_SECT": "행복주유소~부곡동하늘공원묘지",
            "RTE_CONGEST_1": "",
            "RTE_ARRV_TM_1": "13분28초후[10번째 전]",
            "RTE_ARRV_STN_1": "식물원건너편",
            "RTE_CONGEST_2": "정보없음",
            "RTE_ARRV_TM_2": "출발대기",
            "RTE_ARRV_STN_2": null
          },
          {
            "RTE_STN_NM": "동양미래대학.구로성심병원",
            "RTE_NM": "320안산",
            "RTE_ID": "217000013",
            "RTE_SECT": "개봉역.한마을아파트~동양미래대학.구로성심병원",
            "RTE_CONGEST_1": "",
            "RTE_ARRV_TM_1": "14분39초후[5번째 전]",
            "RTE_ARRV_STN_1": "새마을시장",
            "RTE_CONGEST_2": "",
            "RTE_ARRV_TM_2": "43분3초후[15번째 전]",
            "RTE_ARRV_STN_2": "동막골앞"
          },
          {
            "RTE_STN_NM": "동양미래대학.구로성심병원",
            "RTE_NM": "5200시흥",
            "RTE_ID": "224000052",
            "RTE_SECT": "개봉역.한마을아파트~동양미래대학.구로성심병원",
            "RTE_CONGEST_1": "",
            "RTE_ARRV_TM_1": "16분19초후[2번째 전]",
            "RTE_ARRV_STN_1": "오류동역",
            "RTE_CONGEST_2": "",
            "RTE_ARRV_TM_2": "35분49초후[12번째 전]",
            "RTE_ARRV_STN_2": "은계우미린더퍼스트.제일풍경채"
          },
          {
            "RTE_STN_NM": "동양미래대학.구로성심병원",
            "RTE_NM": "530시흥",
            "RTE_ID": "224000029",
            "RTE_SECT": "개봉역.한마을아파트~동양미래대학.구로성심병원",
            "RTE_CONGEST_1": "",
            "RTE_ARRV_TM_1": "23분25초후[16번째 전]",
            "RTE_ARRV_STN_1": "밤일로사거리",
            "RTE_CONGEST_2": "",
            "RTE_ARRV_TM_2": "62분39초후[52번째 전]",
            "RTE_ARRV_STN_2": "새터말"
          },
          {
            "RTE_STN_NM": "동양미래대학.구로성심병원",
            "RTE_NM": "83부천",
            "RTE_ID": "212000002",
            "RTE_SECT": "개봉역.한마을아파트~동양미래대학.구로성심병원",
            "RTE_CONGEST_1": "",
            "RTE_ARRV_TM_1": "4분6초후[1번째 전]",
            "RTE_ARRV_STN_1": "개봉역.한마을아파트",
            "RTE_CONGEST_2": "",
            "RTE_ARRV_TM_2": "16분16초후[8번째 전]",
            "RTE_ARRV_STN_2": "유한대학교"
          },
          {
            "RTE_STN_NM": "동양미래대학.구로성심병원",
            "RTE_NM": "88부천",
            "RTE_ID": "212000001",
            "RTE_SECT": "개봉역.한마을아파트~동양미래대학.구로성심병원",
            "RTE_CONGEST_1": "",
            "RTE_ARRV_TM_1": "곧 도착",
            "RTE_ARRV_STN_1": "동양미래대학.구로성심병원",
            "RTE_CONGEST_2": "",
            "RTE_ARRV_TM_2": "8분47초후[4번째 전]",
            "RTE_ARRV_STN_2": "오류동역"
          }
        ]
      }
    ],
    "ACDNT_CNTRL_STTS": [],
    "SBIKE_STTS": [
      {
        "SBIKE_SPOT_NM": "1928. 고척스카이돔구장 광장",
        "SBIKE_SPOT_ID": "ST-675",
        "SBIKE_SHARED": "40",
        "SBIKE_PARKING_CNT": "4",
        "SBIKE_RACK_CNT": "10",
        "SBIKE_X": 126.86840057,
        "SBIKE_Y": 37.49946976
      }
    ],
    "WEATHER_STTS": [
      {
        "WEATHER_TIME": "2025-04-21 12:50",
        "TEMP": "24.6",
        "SENSIBLE_TEMP": "24.6",
        "MAX_TEMP": "26.0",
        "MIN_TEMP": "17.0",
        "HUMIDITY": "45",
        "WIND_DIRCT": "ESE",
        "WIND_SPD": "3.1",
        "PRECIPITATION": "-",
        "PRECPT_TYPE": "없음",
        "PCP_MSG": "비 또는 눈 소식이 없어요.",
        "SUNRISE": "05:49",
        "SUNSET": "19:13",
        "UV_INDEX_LVL": "6",
        "UV_INDEX": "높음",
        "UV_MSG": "햇볕에 노출 시 1-2시간 이내에도 피부 화상을 입을 수 있어 위험해요.한낮에는 실내나 그늘에 머물러주세요.외출시 긴 소매 옷, 모자, 선글라스를 착용해주세요.자외선 차단제를 정기적으로 발라주세요.",
        "PM25_INDEX": "좋음",
        "PM25": "10",
        "PM10_INDEX": "좋음",
        "PM10": "11",
        "AIR_IDX": "보통",
        "AIR_IDX_MVL": "69.0",
        "AIR_IDX_MAIN": "O3",
        "AIR_MSG": "호흡기가 예민하신 분들은 몸상태 유의하며 활동해주세요.",
        "FCST24HOURS": [
          {
            "FCST_DT": "202504211300",
            "TEMP": "25",
            "PRECIPITATION": "-",
            "PRECPT_TYPE": "없음",
            "RAIN_CHANCE": "0",
            "SKY_STTS": "흐림"
          },
          {
            "FCST_DT": "202504211400",
            "TEMP": "25",
            "PRECIPITATION": "-",
            "PRECPT_TYPE": "없음",
            "RAIN_CHANCE": "0",
            "SKY_STTS": "흐림"
          },
          {
            "FCST_DT": "202504211500",
            "TEMP": "25",
            "PRECIPITATION": "-",
            "PRECPT_TYPE": "없음",
            "RAIN_CHANCE": "0",
            "SKY_STTS": "흐림"
          },
          {
            "FCST_DT": "202504211600",
            "TEMP": "24",
            "PRECIPITATION": "-",
            "PRECPT_TYPE": "없음",
            "RAIN_CHANCE": "0",
            "SKY_STTS": "맑음"
          },
          {
            "FCST_DT": "202504211700",
            "TEMP": "24",
            "PRECIPITATION": "-",
            "PRECPT_TYPE": "없음",
            "RAIN_CHANCE": "0",
            "SKY_STTS": "흐림"
          },
          {
            "FCST_DT": "202504211800",
            "TEMP": "22",
            "PRECIPITATION": "-",
            "PRECPT_TYPE": "없음",
            "RAIN_CHANCE": "0",
            "SKY_STTS": "흐림"
          },
          {
            "FCST_DT": "202504211900",
            "TEMP": "21",
            "PRECIPITATION": "-",
            "PRECPT_TYPE": "없음",
            "RAIN_CHANCE": "0",
            "SKY_STTS": "맑음"
          },
          {
            "FCST_DT": "202504212000",
            "TEMP": "20",
            "PRECIPITATION": "-",
            "PRECPT_TYPE": "없음",
            "RAIN_CHANCE": "0",
            "SKY_STTS": "맑음"
          },
          {
            "FCST_DT": "202504212100",
            "TEMP": "19",
            "PRECIPITATION": "-",
            "PRECPT_TYPE": "없음",
            "RAIN_CHANCE": "20",
            "SKY_STTS": "구름많음"
          },
          {
            "FCST_DT": "202504212200",
            "TEMP": "18",
            "PRECIPITATION": "-",
            "PRECPT_TYPE": "없음",
            "RAIN_CHANCE": "20",
            "SKY_STTS": "구름많음"
          },
          {
            "FCST_DT": "202504212300",
            "TEMP": "18",
            "PRECIPITATION": "-",
            "PRECPT_TYPE": "없음",
            "RAIN_CHANCE": "20",
            "SKY_STTS": "구름많음"
          },
          {
            "FCST_DT": "202504220000",
            "TEMP": "18",
            "PRECIPITATION": "-",
            "PRECPT_TYPE": "없음",
            "RAIN_CHANCE": "30",
            "SKY_STTS": "흐림"
          },
          {
            "FCST_DT": "202504220100",
            "TEMP": "18",
            "PRECIPITATION": "-",
            "PRECPT_TYPE": "없음",
            "RAIN_CHANCE": "30",
            "SKY_STTS": "흐림"
          },
          {
            "FCST_DT": "202504220200",
            "TEMP": "17",
            "PRECIPITATION": "-",
            "PRECPT_TYPE": "없음",
            "RAIN_CHANCE": "30",
            "SKY_STTS": "흐림"
          },
          {
            "FCST_DT": "202504220300",
            "TEMP": "17",
            "PRECIPITATION": "-",
            "PRECPT_TYPE": "없음",
            "RAIN_CHANCE": "30",
            "SKY_STTS": "흐림"
          },
          {
            "FCST_DT": "202504220400",
            "TEMP": "17",
            "PRECIPITATION": "-",
            "PRECPT_TYPE": "없음",
            "RAIN_CHANCE": "30",
            "SKY_STTS": "흐림"
          },
          {
            "FCST_DT": "202504220500",
            "TEMP": "17",
            "PRECIPITATION": "1 미만",
            "PRECPT_TYPE": "비",
            "RAIN_CHANCE": "60",
            "SKY_STTS": "흐림"
          },
          {
            "FCST_DT": "202504220600",
            "TEMP": "17",
            "PRECIPITATION": "1 미만",
            "PRECPT_TYPE": "비",
            "RAIN_CHANCE": "60",
            "SKY_STTS": "흐림"
          },
          {
            "FCST_DT": "202504220700",
            "TEMP": "17",
            "PRECIPITATION": "-",
            "PRECPT_TYPE": "없음",
            "RAIN_CHANCE": "30",
            "SKY_STTS": "흐림"
          },
          {
            "FCST_DT": "202504220800",
            "TEMP": "17",
            "PRECIPITATION": "2.0",
            "PRECPT_TYPE": "비",
            "RAIN_CHANCE": "60",
            "SKY_STTS": "흐림"
          },
          {
            "FCST_DT": "202504220900",
            "TEMP": "17",
            "PRECIPITATION": "6.0",
            "PRECPT_TYPE": "비",
            "RAIN_CHANCE": "68",
            "SKY_STTS": "흐림"
          },
          {
            "FCST_DT": "202504221000",
            "TEMP": "17",
            "PRECIPITATION": "5.0",
            "PRECPT_TYPE": "비",
            "RAIN_CHANCE": "64",
            "SKY_STTS": "흐림"
          },
          {
            "FCST_DT": "202504221100",
            "TEMP": "17",
            "PRECIPITATION": "4.0",
            "PRECPT_TYPE": "비",
            "RAIN_CHANCE": "62",
            "SKY_STTS": "흐림"
          },
          {
            "FCST_DT": "202504221200",
            "TEMP": "17",
            "PRECIPITATION": "7.0",
            "PRECPT_TYPE": "비",
            "RAIN_CHANCE": "72",
            "SKY_STTS": "흐림"
          }
        ],
        "NEWS_LIST": []
      }
    ],
    "CHARGER_STTS": [
      {
        "STAT_NM": "고척스카이돔",
        "STAT_ID": "KP003028",
        "STAT_ADDR": "서울특별시 구로구 경인로 430",
        "STAT_X": "126.866274181",
        "STAT_Y": "37.4985266401",
        "STAT_USETIME": "24시간 이용가능",
        "STAT_PARKPAY": "Y",
        "STAT_LIMITYN": "N",
        "STAT_LIMITDETAIL": "",
        "STAT_KINDDETAIL": "경기장",
        "CHARGER_DETAILS": [
          {
            "CHARGER_ID": "01",
            "CHARGER_TYPE": "DC차데모+AC3상+DC콤보",
            "CHARGER_STAT": "사용가능",
            "STATUPDDT": "2025-04-21 11:38",
            "LASTTSDT": "2025-04-21 11:20",
            "LASTTEDT": "2025-04-21 11:37",
            "NOWTSDT": null,
            "OUTPUT": "50",
            "METHOD": ""
          },
          {
            "CHARGER_ID": "02",
            "CHARGER_TYPE": "DC차데모+AC3상+DC콤보",
            "CHARGER_STAT": "사용가능",
            "STATUPDDT": "2025-04-21 03:36",
            "LASTTSDT": "2025-04-16 20:00",
            "LASTTEDT": "2025-04-16 20:01",
            "NOWTSDT": null,
            "OUTPUT": "50",
            "METHOD": ""
          },
          {
            "CHARGER_ID": "03",
            "CHARGER_TYPE": "DC차데모+AC3상+DC콤보",
            "CHARGER_STAT": "사용가능",
            "STATUPDDT": "2025-04-21 12:38",
            "LASTTSDT": "2025-04-21 11:41",
            "LASTTEDT": "2025-04-21 12:37",
            "NOWTSDT": null,
            "OUTPUT": "50",
            "METHOD": ""
          }
        ]
      },
      {
        "STAT_NM": "고척스카이돔",
        "STAT_ID": "SE000060",
        "STAT_ADDR": "서울특별시 구로구 안양천로 545",
        "STAT_X": "126.86734135",
        "STAT_Y": "37.496180722",
        "STAT_USETIME": "24시간 이용가능",
        "STAT_PARKPAY": "Y",
        "STAT_LIMITYN": "N",
        "STAT_LIMITDETAIL": "",
        "STAT_KINDDETAIL": "공공기관",
        "CHARGER_DETAILS": [
          {
            "CHARGER_ID": "01",
            "CHARGER_TYPE": "DC콤보",
            "CHARGER_STAT": "사용가능",
            "STATUPDDT": "2025-04-18 19:55",
            "LASTTSDT": "2025-04-18 19:34",
            "LASTTEDT": "2025-04-18 19:55",
            "NOWTSDT": null,
            "OUTPUT": "90",
            "METHOD": "동시"
          },
          {
            "CHARGER_ID": "02",
            "CHARGER_TYPE": "DC콤보",
            "CHARGER_STAT": "사용가능",
            "STATUPDDT": "2025-04-19 16:52",
            "LASTTSDT": "2025-04-19 16:33",
            "LASTTEDT": "2025-04-19 16:52",
            "NOWTSDT": null,
            "OUTPUT": "90",
            "METHOD": "동시"
          },
          {
            "CHARGER_ID": "03",
            "CHARGER_TYPE": "DC콤보",
            "CHARGER_STAT": "사용가능",
            "STATUPDDT": "2025-04-19 18:37",
            "LASTTSDT": "2025-04-19 18:23",
            "LASTTEDT": "2025-04-19 18:37",
            "NOWTSDT": null,
            "OUTPUT": "90",
            "METHOD": "동시"
          },
          {
            "CHARGER_ID": "04",
            "CHARGER_TYPE": "DC콤보",
            "CHARGER_STAT": "사용가능",
            "STATUPDDT": "2025-04-20 13:37",
            "LASTTSDT": "2025-04-20 13:26",
            "LASTTEDT": "2025-04-20 13:37",
            "NOWTSDT": null,
            "OUTPUT": "90",
            "METHOD": "동시"
          },
          {
            "CHARGER_ID": "05",
            "CHARGER_TYPE": "DC콤보",
            "CHARGER_STAT": "사용가능",
            "STATUPDDT": "2025-04-21 11:15",
            "LASTTSDT": "2025-04-21 11:04",
            "LASTTEDT": "2025-04-21 11:15",
            "NOWTSDT": null,
            "OUTPUT": "90",
            "METHOD": "동시"
          },
          {
            "CHARGER_ID": "06",
            "CHARGER_TYPE": "DC콤보",
            "CHARGER_STAT": "사용가능",
            "STATUPDDT": "2025-04-20 10:27",
            "LASTTSDT": "2025-04-20 09:36",
            "LASTTEDT": "2025-04-20 10:27",
            "NOWTSDT": null,
            "OUTPUT": "90",
            "METHOD": "동시"
          },
          {
            "CHARGER_ID": "07",
            "CHARGER_TYPE": "AC완속",
            "CHARGER_STAT": "사용가능",
            "STATUPDDT": "2025-04-20 13:40",
            "LASTTSDT": "2025-04-20 11:12",
            "LASTTEDT": "2025-04-20 13:39",
            "NOWTSDT": null,
            "OUTPUT": "7",
            "METHOD": "단독"
          }
        ]
      },
      {
        "STAT_NM": "서울시 구로구 구로소방서 ",
        "STAT_ID": "PI000740",
        "STAT_ADDR": "서울특별시 구로구 경인로 408",
        "STAT_X": "126.8652147",
        "STAT_Y": "37.497792",
        "STAT_USETIME": "평일 09:00 ~ 18:00",
        "STAT_PARKPAY": "Y",
        "STAT_LIMITYN": "N",
        "STAT_LIMITDETAIL": "",
        "STAT_KINDDETAIL": "공공기관",
        "CHARGER_DETAILS": [
          {
            "CHARGER_ID": "02",
            "CHARGER_TYPE": "AC완속",
            "CHARGER_STAT": "사용가능",
            "STATUPDDT": "2025-04-19 07:16",
            "LASTTSDT": "2025-04-18 05:26",
            "LASTTEDT": "2025-04-18 05:26",
            "NOWTSDT": null,
            "OUTPUT": "7",
            "METHOD": "단독"
          }
        ]
      }
    ],
    "EVENT_STTS": [
      {
        "EVENT_NM": "[서울아트책보고] 프로젝트 해시태그 2024 참여전시",
        "EVENT_PERIOD": "2025-04-15~2025-04-27",
        "EVENT_PLACE": "서울아트책보고 북카페",
        "EVENT_X": 126.867088741096,
        "EVENT_Y": 37.4982125677913,
        "PAY_YN": null,
        "THUMBNAIL": "https://culture.seoul.go.kr/cmmn/file/getImage.do?atchFileId=92a972a42f204d369796487d9c196d64&thumb=Y",
        "URL": "https://culture.seoul.go.kr/culture/culture/cultureEvent/view.do?cultcode=153205&menuNo=200009",
        "EVENT_ETC_DETAIL": ""
      }
    ],
    "LIVE_CMRCL_STTS": null
  }
}