{
  "list_total_count": 1,
  "RESULT": {
    "RESULT.CODE": "INFO-000",
    "RESULT.MESSAGE": "정상 처리되었습니다."
  },
  "CITYDATA": {
    "AREA_NM": "방배역 먹자골목",
    "AREA_CD": "POI065",
    "LIVE_PPLTN_STTS": [
      {
        "AREA_NM": "방배역 먹자골목",
        "AREA_CD": "POI065",
        "AREA_CONGEST_LVL": "약간 붐빔",
        "AREA_CONGEST_MSG": "사람들이 몰려있을 가능성이 크고 붐빈다고 느낄 수 있어요. 인구밀도가 높은 구간에서는 도보 이동시 부딪힘이 발생할 수 있어요.",
        "AREA_PPLTN_MIN": "2000",
        "AREA_PPLTN_MAX": "2500",
        "MALE_PPLTN_RATE": "45.8",
        "FEMALE_PPLTN_RATE": "54.2",
        "PPLTN_RATE_0": "0.2",
        "PPLTN_RATE_10": "21.9",
        "PPLTN_RATE_20": "22.8",
        "PPLTN_RATE_30": "15.1",
        "PPLTN_RATE_40": "14.3",
        "PPLTN_RATE_50": "12.0",
        "PPLTN_RATE_60": "7.7",
        "PPLTN_RATE_70": "6.0",
        "RESNT_PPLTN_RATE": "11.0",
        "NON_RESNT_PPLTN_RATE": "89.0",
        "REPLACE_YN": "N",
        "PPLTN_TIME": "2025-04-21 12:40",
        "FCST_YN": "Y",
        "FCST_PPLTN": [
          {
            "FCST_TIME": "2025-04-21 14:00",
            "FCST_CONGEST_LVL": "약간 붐빔",
            "FCST_PPLTN_MIN": "1500",
            "FCST_PPLTN_MAX": "2000"
          },
          {
            "FCST_TIME": "2025-04-21 15:00",
            "FCST_CONGEST_LVL": "약간 붐빔",
            "FCST_PPLTN_MIN": "1500",
            "FCST_PPLTN_MAX": "2000"
          },
          {
            "FCST_TIME": "2025-04-21 16:00",
            "FCST_CONGEST_LVL": "약간 붐빔",
            "FCST_PPLTN_MIN": "1500",
            "FCST_PPLTN_MAX": "2000"
          },
          {
            "FCST_TIME": "2025-04-21 17:00",
            "FCST_CONGEST_LVL": "약간 붐빔",
            "FCST_PPLTN_MIN": "1500",
            "FCST_PPLTN_MAX": "2000"
          },
          {
            "FCST_TIME": "2025-04-21 18:00",
            "FCST_CONGEST_LVL": "약간 붐빔",
            "FCST_PPLTN_MIN": "1500",
            "FCST_PPLTN_MAX": "2000"
          },
          {
            "FCST_TIME": "2025-04-21 19:00",
            "FCST_CONGEST_LVL": "약간 붐빔",
            "FCST_PPLTN_MIN": "1500",
            "FCST_PPLTN_MAX": "2000"
          },
          {
            "FCST_TIME": "2025-04-21 20:00",
            "FCST_CONGEST_LVL": "보통",
            "FCST_PPLTN_MIN": "1000",
            "FCST_PPLTN_MAX": "1500"
          },
          {
            "FCST_TIME": "2025-04-21 21:00",
            "FCST_CONGEST_LVL": "보통",
            "FCST_PPLTN_MIN": "1000",
            "FCST_PPLTN_MAX": "1500"
          },
          {
            "FCST_TIME": "2025-04-21 22:00",
            "FCST_CONGEST_LVL": "여유",
            "FCST_PPLTN_MIN": "800",
            "FCST_PPLTN_MAX": "900"
          },
          {
            "FCST_TIME": "2025-04-21 23:00",
            "FCST_CONGEST_LVL": "여유",
            "FCST_PPLTN_MIN": "600",
            "FCST_PPLTN_MAX": "700"
          },
          {
            "FCST_TIME": "2025-04-22 00:00",
            "FCST_CONGEST_LVL": "여유",
            "FCST_PPLTN_MIN": "400",
            "FCST_PPLTN_MAX": "500"
          },
          {
            "FCST_TIME": "2025-04-22 01:00",
            "FCST_CONGEST_LVL": "여유",
            "FCST_PPLTN_MIN": "200",
            "FCST_PPLTN_MAX": "300"
          }
        ]
      }
    ],
    "ROAD_TRAFFIC_STTS": {
      "AVG_ROAD_DATA": {
        "ROAD_MSG": "해당 장소로 이동·진입하는 도로가 크게 막히지 않아요.",
        "ROAD_TRAFFIC_IDX": "원활",
        "ROAD_TRAFFIC_SPD": 26,
        "ROAD_TRAFFIC_TIME": "2025-04-21 13:00"
      },
      "ROAD_TRAFFIC_STTS": [
        {
          "LINK_ID": "1210011800",
          "ROAD_NM": "방배로",
          "START_ND_CD": "1210016900",
          "START_ND_NM": "경남아파트앞교차로",
          "START_ND_XY": "127.0018655974946142_37.4751684159924636",
          "END_ND_CD": "1210020200",
          "END_ND_NM": "방배역사거리",
          "END_ND_XY": "126.9976635036703385_37.4814953256300498",
          "DIST": "796.0",
          "SPD": 22.0,
          "IDX": "서행",
          "XYLIST": "126.9976035026176362_37.4814701033855826|126.9989201967898680_37.4794808315917720|127.0016213874163498_37.4753601743264184|127.0018123343111114_37.4751310222064902"
        },
        {
          "LINK_ID": "1210011900",
          "ROAD_NM": "방배로",
          "START_ND_CD": "1210020200",
          "START_ND_NM": "방배역사거리",
          "START_ND_XY": "126.9976635036703385_37.4814953256300498",
          "END_ND_CD": "1210016900",
          "END_ND_NM": "경남아파트앞교차로",
          "END_ND_XY": "127.0018655974946142_37.4751684159924636",
          "DIST": "795.0",
          "SPD": 25.0,
          "IDX": "원활",
          "XYLIST": "127.0019253450242758_37.4751908375669132|127.0017383358341192_37.4754152649134369|126.9990403210066745_37.4795310873209431|126.9977235047633570_37.4815205487449745"
        },
        {
          "LINK_ID": "1210013000",
          "ROAD_NM": "효령로",
          "START_ND_CD": "1210003700",
          "START_ND_NM": "효령아파트앞교차로",
          "START_ND_XY": "126.9936401397866348_37.4801899794544653",
          "END_ND_CD": "1210020200",
          "END_ND_NM": "방배역사거리",
          "END_ND_XY": "126.9976635036703385_37.4814953256300498",
          "DIST": "384.0",
          "SPD": 22.0,
          "IDX": "서행",
          "XYLIST": "126.9976379264009836_37.4815453968919456|126.9936145602778197_37.4802400489552952"
        },
        {
          "LINK_ID": "1210013100",
          "ROAD_NM": "효령로",
          "START_ND_CD": "1210020200",
          "START_ND_NM": "방배역사거리",
          "START_ND_XY": "126.9976635036703385_37.4814953256300498",
          "END_ND_CD": "1210003700",
          "END_ND_NM": "효령아파트앞교차로",
          "END_ND_XY": "126.9936401397866348_37.4801899794544653",
          "DIST": "384.0",
          "SPD": 29.0,
          "IDX": "원활",
          "XYLIST": "126.9936657203919168_37.4801399099477308|126.9976890820361319_37.4814452552632460"
        },
        {
          "LINK_ID": "1210013802",
          "ROAD_NM": "효령로",
          "START_ND_CD": "1210020200",
          "START_ND_NM": "방배역사거리",
          "START_ND_XY": "126.9976635036703385_37.4814953256300498",
          "END_ND_CD": "1210020201",
          "END_ND_NM": "방배동912-14",
          "END_ND_XY": "126.9987450236171327_37.4816462826896881",
          "DIST": "99.0",
          "SPD": 27.0,
          "IDX": "원활",
          "XYLIST": "126.9987366855253583_37.4816999331774383|126.9979254416350898_37.4816198652729895|126.9976425743291770_37.4815467493991932"
        },
        {
          "LINK_ID": "1210013901",
          "ROAD_NM": "효령로",
          "START_ND_CD": "1210020201",
          "START_ND_NM": "방배동912-14",
          "START_ND_XY": "126.9987450236171327_37.4816462826896881",
          "END_ND_CD": "1210020200",
          "END_ND_NM": "방배역사거리",
          "END_ND_XY": "126.9976635036703385_37.4814953256300498",
          "DIST": "96.0",
          "SPD": 29.0,
          "IDX": "원활",
          "XYLIST": "126.9976844329827941_37.4814439027577677|126.9979549762968531_37.4815138332533166|126.9987533605663259_37.4815926322008437"
        },
        {
          "LINK_ID": "1210015601",
          "ROAD_NM": "방배로",
          "START_ND_CD": "1210020200",
          "START_ND_NM": "방배역사거리",
          "START_ND_XY": "126.9976635036703385_37.4814953256300498",
          "END_ND_CD": "1210022200",
          "END_ND_NM": "방림종합시장입구",
          "END_ND_XY": "126.9964823029518186_37.4832963508228545",
          "DIST": "226.0",
          "SPD": 16.5,
          "IDX": "서행",
          "XYLIST": "126.9964221809990903_37.4832713099863071|126.9976033827664281_37.4814702853869477"
        },
        {
          "LINK_ID": "1210015602",
          "ROAD_NM": "방배로",
          "START_ND_CD": "1210022200",
          "START_ND_NM": "방림종합시장입구",
          "START_ND_XY": "126.9964823029518186_37.4832963508228545",
          "END_ND_CD": "1210027800",
          "END_ND_NM": "내방역앞교차로",
          "END_ND_XY": "126.9936549599425746_37.4877005300783566",
          "DIST": "549.0",
          "SPD": 15.7,
          "IDX": "서행",
          "XYLIST": "126.9935945628673721_37.4876759085775149|126.9964219073631710_37.4832717307490597"
        },
        {
          "LINK_ID": "1210015701",
          "ROAD_NM": "방배로",
          "START_ND_CD": "1210022200",
          "START_ND_NM": "방림종합시장입구",
          "START_ND_XY": "126.9964823029518186_37.4832963508228545",
          "END_ND_CD": "1210020200",
          "END_ND_NM": "방배역사거리",
          "END_ND_XY": "126.9976635036703385_37.4814953256300498",
          "DIST": "226.0",
          "SPD": 24.0,
          "IDX": "서행",
          "XYLIST": "126.9977236246143377_37.4815203667434815|126.9965424249446215_37.4833213925297173"
        },
        {
          "LINK_ID": "1210015702",
          "ROAD_NM": "방배로",
          "START_ND_CD": "1210027800",
          "START_ND_NM": "내방역앞교차로",
          "START_ND_XY": "126.9936549599425746_37.4877005300783566",
          "END_ND_CD": "1210022200",
          "END_ND_NM": "방림종합시장입구",
          "END_ND_XY": "126.9964823029518186_37.4832963508228545",
          "DIST": "549.0",
          "SPD": 15.6,
          "IDX": "서행",
          "XYLIST": "126.9965426974494136_37.4833209717666378|126.9937153581880551_37.4877251524492792"
        },
        {
          "LINK_ID": "1210043100",
          "ROAD_NM": "방배로13길",
          "START_ND_CD": "1210022200",
          "START_ND_NM": "방림종합시장입구",
          "START_ND_XY": "126.9964823029518186_37.4832963508228545",
          "END_ND_CD": "1210020400",
          "END_ND_NM": "이수중교입구",
          "END_ND_XY": "126.9926449775441739_37.4817247536477822",
          "DIST": "382.0",
          "SPD": 81.0,
          "IDX": "원활",
          "XYLIST": "126.9926759861187264_37.4816766714308685|126.9965133108476607_37.4832482685126038"
        },
        {
          "LINK_ID": "1210043200",
          "ROAD_NM": "방배로13길",
          "START_ND_CD": "1210020400",
          "START_ND_NM": "이수중교입구",
          "START_ND_XY": "126.9926449775441739_37.4817247536477822",
          "END_ND_CD": "1210022200",
          "END_ND_NM": "방림종합시장입구",
          "END_ND_XY": "126.9964823029518186_37.4832963508228545",
          "DIST": "382.0",
          "SPD": 18.0,
          "IDX": "서행",
          "XYLIST": "126.9964512950162145_37.4833444340255753|126.9926139677993717_37.4817728349550734"
        },
        {
          "LINK_ID": "1210169300",
          "ROAD_NM": "방배로",
          "START_ND_CD": "1210022200",
          "START_ND_NM": "방림종합시장입구",
          "START_ND_XY": "126.9964823029518186_37.4832963508228545",
          "END_ND_CD": "1210081200",
          "END_ND_NM": "방배동906-20",
          "END_ND_XY": "126.9970612552435085_37.4835229009423401",
          "DIST": "57.0",
          "SPD": 12.0,
          "IDX": "정체",
          "XYLIST": "126.9970313544726679_37.4835714267182354|126.9964524018968746_37.4833448764540904"
        },
        {
          "LINK_ID": "1210169400",
          "ROAD_NM": "방배로",
          "START_ND_CD": "1210081200",
          "START_ND_NM": "방배동906-20",
          "START_ND_XY": "126.9970612552435085_37.4835229009423401",
          "END_ND_CD": "1210022200",
          "END_ND_NM": "방림종합시장입구",
          "END_ND_XY": "126.9964823029518186_37.4832963508228545",
          "DIST": "57.0",
          "SPD": 38.0,
          "IDX": "원활",
          "XYLIST": "126.9965122039680949_37.4832478251836534|126.9970911559756814_37.4834743742574688"
        }
      ]
    },
    "PRK_STTS": [
      {
        "PRK_NM": "방배역 노상 공영주차장(구)",
        "PRK_CD": "1580208",
        "PRK_TYPE": "NS",
        "CPCTY": "9",
        "CUR_PRK_CNT": "",
        "CUR_PRK_TIME": "",
        "CUR_PRK_YN": "N",
        "PAY_YN": "Y",
        "RATES": "500",
        "TIME_RATES": "10",
        "ADD_RATES": "500",
        "ADD_TIME_RATES": "10",
        "ADDRESS": "서초구 방배동 91-16",
        "ROAD_ADDR": "",
        "LNG": "126.99682376888889",
        "LAT": "37.48249786444445"
      },
      {
        "PRK_NM": "방배역 노상 공영주차장(구)",
        "PRK_CD": "1580208",
        "PRK_TYPE": "NS",
        "CPCTY": "1",
        "CUR_PRK_CNT": "",
        "CUR_PRK_TIME": "",
        "CUR_PRK_YN": "N",
        "PAY_YN": "Y",
        "RATES": "500",
        "TIME_RATES": "10",
        "ADD_RATES": "500",
        "ADD_TIME_RATES": "10",
        "ADDRESS": "서초구 방배동 910-9",
        "ROAD_ADDR": "",
        "LNG": "126.99704975",
        "LAT": "37.48214653"
      },
      {
        "PRK_NM": "방배역 공영주차장(구)",
        "PRK_CD": "3094955",
        "PRK_TYPE": "NS",
        "CPCTY": "9",
        "CUR_PRK_CNT": "",
        "CUR_PRK_TIME": "",
        "CUR_PRK_YN": "N",
        "PAY_YN": "Y",
        "RATES": "250",
        "TIME_RATES": "5",
        "ADD_RATES": "250",
        "ADD_TIME_RATES": "5",
        "ADDRESS": "서초구 방배동 910-16",
        "ROAD_ADDR": "",
        "LNG": "126.99679805555554",
        "LAT": "37.482540566666664"
      },
      {
        "PRK_NM": "유경빌딩 주차장",
        "PRK_CD": "3022517",
        "PRK_TYPE": "BS",
        "CPCTY": "30",
        "CUR_PRK_CNT": "",
        "CUR_PRK_TIME": "",
        "CUR_PRK_YN": "N",
        "PAY_YN": "Y",
        "RATES": "2000",
        "TIME_RATES": "30",
        "ADD_RATES": "1000",
        "ADD_TIME_RATES": "10",
        "ADDRESS": "서초구 방배동 909-9",
        "ROAD_ADDR": "",
        "LNG": "126.9971169",
        "LAT": "37.4815462"
      },
      {
        "PRK_NM": "방배아크로타워 주차장",
        "PRK_CD": "3025285",
        "PRK_TYPE": "BS",
        "CPCTY": "191",
        "CUR_PRK_CNT": "",
        "CUR_PRK_TIME": "",
        "CUR_PRK_YN": "N",
        "PAY_YN": "Y",
        "RATES": "1000",
        "TIME_RATES": "10",
        "ADD_RATES": "1000",
        "ADD_TIME_RATES": "10",
        "ADDRESS": "서초구 방배동 923-6",
        "ROAD_ADDR": "",
        "LNG": "126.995322",
        "LAT": "37.483151"
      },
      {
        "PRK_NM": "방배센트럴빌딩 주차장",
        "PRK_CD": "3018744",
        "PRK_TYPE": "BS",
        "CPCTY": "38",
        "CUR_PRK_CNT": "",
        "CUR_PRK_TIME": "",
        "CUR_PRK_YN": "N",
        "PAY_YN": "Y",
        "RATES": "1000",
        "TIME_RATES": "10",
        "ADD_RATES": "1000",
        "ADD_TIME_RATES": "10",
        "ADDRESS": "서초구 방배동 909-6",
        "ROAD_ADDR": "",
        "LNG": "126.997026",
        "LAT": "37.481855"
      }
    ],
    "SUB_STTS": [
      {
        "SUB_STN_NM": "방배",
        "SUB_STN_LINE": "2",
        "SUB_STN_RADDR": "서울 서초구 방배로 지하 80",
        "SUB_STN_JIBUN": "서울 서초구 방배동 912-14",
        "SUB_STN_X": "126.997553345516",
        "SUB_STN_Y": "37.4814561268152",
        "SUB_DETAIL": [
          {
            "SUB_NT_STN": "1002000224",
            "SUB_BF_STN": "1002000226",
            "SUB_ROUTE_NM": "성수행 - 서초방면",
            "SUB_LINE": "2호선",
            "SUB_ORD": "01001성수0",
            "SUB_DIR": "외선",
            "SUB_TERMINAL": "성수",
            "SUB_ARVTIME": "140",
            "SUB_ARMG1": "전역 출발",
            "SUB_ARMG2": "사당",
            "SUB_ARVINFO": "전역출발"
          },
          {
            "SUB_NT_STN": "1002000224",
            "SUB_BF_STN": "1002000226",
            "SUB_ROUTE_NM": "성수행 - 서초방면",
            "SUB_LINE": "2호선",
            "SUB_ORD": "02003성수0",
            "SUB_DIR": "외선",
            "SUB_TERMINAL": "성수",
            "SUB_ARVTIME": "350",
            "SUB_ARMG1": "5분 50초 후",
            "SUB_ARMG2": "서울대입구",
            "SUB_ARVINFO": "운행중"
          },
          {
            "SUB_NT_STN": "1002000226",
            "SUB_BF_STN": "1002000224",
            "SUB_ROUTE_NM": "성수행 - 사당방면",
            "SUB_LINE": "2호선",
            "SUB_ORD": "11001성수0",
            "SUB_DIR": "내선",
            "SUB_TERMINAL": "성수",
            "SUB_ARVTIME": "110",
            "SUB_ARMG1": "전역 출발",
            "SUB_ARMG2": "서초",
            "SUB_ARVINFO": "전역출발"
          },
          {
            "SUB_NT_STN": "1002000226",
            "SUB_BF_STN": "1002000224",
            "SUB_ROUTE_NM": "성수행 - 사당방면",
            "SUB_LINE": "2호선",
            "SUB_ORD": "12004성수0",
            "SUB_DIR": "내선",
            "SUB_TERMINAL": "성수",
            "SUB_ARVTIME": "330",
            "SUB_ARMG1": "5분 30초 후",
            "SUB_ARMG2": "역삼",
            "SUB_ARVINFO": "운행중"
          }
        ],
        "SUB_FACIINFO": [
          {
            "ELVTR_NM": "승강기)에스컬레이터 1",
            "OPR_SEC": "F1-B1",
            "INSTL_PSTN": "4번 출입구",
            "USE_YN": "사용가능",
            "ELVTR_SE": "ES"
          },
          {
            "ELVTR_NM": "승강기)에스컬레이터 2",
            "OPR_SEC": "B1-F1",
            "INSTL_PSTN": "4번 출입구",
            "USE_YN": "사용가능",
            "ELVTR_SE": "ES"
          },
          {
            "ELVTR_NM": "승강기)엘리베이터 내부#1",
            "OPR_SEC": "B2-B1",
            "INSTL_PSTN": "서초 방면8-3",
            "USE_YN": "사용가능",
            "ELVTR_SE": "EV"
          },
          {
            "ELVTR_NM": "승강기)엘리베이터 내부#2",
            "OPR_SEC": "B2-B1",
            "INSTL_PSTN": "사당 방면3-1",
            "USE_YN": "사용가능",
            "ELVTR_SE": "EV"
          },
          {
            "ELVTR_NM": "승강기)엘리베이터 외부#1",
            "OPR_SEC": "B1-1F",
            "INSTL_PSTN": "3번 출입구",
            "USE_YN": "사용가능",
            "ELVTR_SE": "EV"
          }
        ]
      }
    ],
    "BUS_STN_STTS": [
      {
        "BUS_RESULT_MSG": "정상 호출되었습니다.",
        "BUS_STN_ID": "121000153",
        "BUS_ARS_ID": "22229",
        "BUS_STN_NM": "방배역.방배서리풀이편한세상",
        "BUS_STN_X": "126.99647",
        "BUS_STN_Y": "37.483588",
        "BUS_DETAIL": [
          {
            "RTE_STN_NM": "방배역.방배서리풀이편한세상",
            "RTE_NM": "142",
            "RTE_ID": "100100021",
            "RTE_SECT": "방배3동주민센터~방배역(구방림시장)",
            "RTE_CONGEST_1": "여유",
            "RTE_ARRV_TM_1": "1분54초후[1번째 전]",
            "RTE_ARRV_STN_1": "서울지방법무사회",
            "RTE_CONGEST_2": "여유",
            "RTE_ARRV_TM_2": "7분58초후[3번째 전]",
            "RTE_ARRV_STN_2": "방배동래미안아트힐.국립국악원"
          },
          {
            "RTE_STN_NM": "방배역.방배서리풀이편한세상",
            "RTE_NM": "148",
            "RTE_ID": "100100027",
            "RTE_SECT": "방배역.백석예술대학교~방배역(구방림시장)",
            "RTE_CONGEST_1": "여유",
            "RTE_ARRV_TM_1": "2분6초후[1번째 전]",
            "RTE_ARRV_STN_1": "방배역.백석예술대학교",
            "RTE_CONGEST_2": "여유",
            "RTE_ARRV_TM_2": "10분51초후[5번째 전]",
            "RTE_ARRV_STN_2": "서문여고입구"
          },
          {
            "RTE_STN_NM": "방배역.방배서리풀이편한세상",
            "RTE_NM": "406",
            "RTE_ID": "100100064",
            "RTE_SECT": "방배3동주민센터~방배역(구방림시장)",
            "RTE_CONGEST_1": "여유",
            "RTE_ARRV_TM_1": "5분28초후[2번째 전]",
            "RTE_ARRV_STN_1": "경남임광아파트",
            "RTE_CONGEST_2": "여유",
            "RTE_ARRV_TM_2": "17분15초후[8번째 전]",
            "RTE_ARRV_STN_2": "양재역말죽거리.강남베드로병원"
          },
          {
            "RTE_STN_NM": "방배역.방배서리풀이편한세상",
            "RTE_NM": "4319",
            "RTE_ID": "100100427",
            "RTE_SECT": "방배역~방배역(구방림시장)",
            "RTE_CONGEST_1": "여유",
            "RTE_ARRV_TM_1": "2분8초후[1번째 전]",
            "RTE_ARRV_STN_1": "방배역",
            "RTE_CONGEST_2": "여유",
            "RTE_ARRV_TM_2": "13분37초후[8번째 전]",
            "RTE_ARRV_STN_2": "서초그랑자이아파트"
          },
          {
            "RTE_STN_NM": "방배역.방배서리풀이편한세상",
            "RTE_NM": "M4455용인",
            "RTE_ID": "228000412",
            "RTE_SECT": "서초동예술의전당~방배역.방배서리풀이편한세상",
            "RTE_CONGEST_1": "",
            "RTE_ARRV_TM_1": "12분21초후[4번째 전]",
            "RTE_ARRV_STN_1": "양재IC(미정차)",
            "RTE_CONGEST_2": "",
            "RTE_ARRV_TM_2": "43분8초후[15번째 전]",
            "RTE_ARRV_STN_2": "동백이마트"
          }
        ]
      },
      {
        "BUS_RESULT_MSG": "정상 호출되었습니다.",
        "BUS_STN_ID": "121000156",
        "BUS_ARS_ID": "22232",
        "BUS_STN_NM": "방배1동주민센터.방배아크로타워",
        "BUS_STN_X": "126.9961463518",
        "BUS_STN_Y": "37.4834494617",
        "BUS_DETAIL": [
          {
            "RTE_STN_NM": "방배1동주민센터.방배아크로타워",
            "RTE_NM": "142",
            "RTE_ID": "100100021",
            "RTE_SECT": "내방역~방림시장",
            "RTE_CONGEST_1": "보통",
            "RTE_ARRV_TM_1": "곧 도착",
            "RTE_ARRV_STN_1": "방배1동주민센터.방배아크로타워",
            "RTE_CONGEST_2": "여유",
            "RTE_ARRV_TM_2": "11분28초후[6번째 전]",
            "RTE_ARRV_STN_2": "반포종합운동장"
          },
          {
            "RTE_STN_NM": "방배1동주민센터.방배아크로타워",
            "RTE_NM": "406",
            "RTE_ID": "100100064",
            "RTE_SECT": "내방역~방림시장",
            "RTE_CONGEST_1": "여유",
            "RTE_ARRV_TM_1": "곧 도착",
            "RTE_ARRV_STN_1": "방배1동주민센터.방배아크로타워",
            "RTE_CONGEST_2": "여유",
            "RTE_ARRV_TM_2": "24분15초후[11번째 전]",
            "RTE_ARRV_STN_2": "용산한신아파트"
          },
          {
            "RTE_STN_NM": "방배1동주민센터.방배아크로타워",
            "RTE_NM": "4319",
            "RTE_ID": "100100427",
            "RTE_SECT": "내방역~방림시장",
            "RTE_CONGEST_1": "여유",
            "RTE_ARRV_TM_1": "1분39초후[1번째 전]",
            "RTE_ARRV_STN_1": "내방역",
            "RTE_CONGEST_2": "여유",
            "RTE_ARRV_TM_2": "11분40초후[5번째 전]",
            "RTE_ARRV_STN_2": "이수역"
          }
        ]
      },
      {
        "BUS_RESULT_MSG": "정상 호출되었습니다.",
        "BUS_STN_ID": "121000157",
        "BUS_ARS_ID": "22233",
        "BUS_STN_NM": "지하철2호선방배역",
        "BUS_STN_X": "126.996712",
        "BUS_STN_Y": "37.481352",
        "BUS_DETAIL": [
          {
            "RTE_STN_NM": "지하철2호선방배역",
            "RTE_NM": "350",
            "RTE_ID": "100100553",
            "RTE_SECT": "방배동신동아아파트~지하철2호선방배역",
            "RTE_CONGEST_1": "여유",
            "RTE_ARRV_TM_1": "13분12초후[8번째 전]",
            "RTE_ARRV_STN_1": "서초동신동아아파트",
            "RTE_CONGEST_2": "여유",
            "RTE_ARRV_TM_2": "24분14초후[12번째 전]",
            "RTE_ARRV_STN_2": "신한은행데이터센터"
          },
          {
            "RTE_STN_NM": "지하철2호선방배역",
            "RTE_NM": "461",
            "RTE_ID": "100100071",
            "RTE_SECT": "방배동신동아아파트~지하철2호선방배역",
            "RTE_CONGEST_1": "여유",
            "RTE_ARRV_TM_1": "4분후[2번째 전]",
            "RTE_ARRV_STN_1": "서울고등학교",
            "RTE_CONGEST_2": "여유",
            "RTE_ARRV_TM_2": "12분49초후[7번째 전]",
            "RTE_ARRV_STN_2": "서초그랑자이아파트"
          },
          {
            "RTE_STN_NM": "지하철2호선방배역",
            "RTE_NM": "641",
            "RTE_ID": "100100094",
            "RTE_SECT": "방배동신동아아파트~지하철2호선방배역",
            "RTE_CONGEST_1": "여유",
            "RTE_ARRV_TM_1": "곧 도착",
            "RTE_ARRV_STN_1": "지하철2호선방배역",
            "RTE_CONGEST_2": "여유",
            "RTE_ARRV_TM_2": "9분11초후[4번째 전]",
            "RTE_ARRV_STN_2": "남부터미널.한일시멘트"
          }
        ]
      },
      {
        "BUS_RESULT_MSG": "정상 호출되었습니다.",
        "BUS_STN_ID": "121000173",
        "BUS_ARS_ID": "22249",
        "BUS_STN_NM": "방배역.백석예술대학교",
        "BUS_STN_X": "126.996763",
        "BUS_STN_Y": "37.481038",
        "BUS_DETAIL": [
          {
            "RTE_STN_NM": "방배역.백석예술대학교",
            "RTE_NM": "148",
            "RTE_ID": "100100027",
            "RTE_SECT": "이수중학교~방배역.백석예술대학교",
            "RTE_CONGEST_1": "여유",
            "RTE_ARRV_TM_1": "곧 도착",
            "RTE_ARRV_STN_1": "방배역.백석예술대학교",
            "RTE_CONGEST_2": "여유",
            "RTE_ARRV_TM_2": "8분58초후[4번째 전]",
            "RTE_ARRV_STN_2": "서문여고입구"
          },
          {
            "RTE_STN_NM": "방배역.백석예술대학교",
            "RTE_NM": "350",
            "RTE_ID": "100100553",
            "RTE_SECT": "방배동대우효령아파트앞~방배역.백석예술대학교",
            "RTE_CONGEST_1": "여유",
            "RTE_ARRV_TM_1": "6분32초후[5번째 전]",
            "RTE_ARRV_STN_1": "방배동래미안타워.동덕여중고",
            "RTE_CONGEST_2": "여유",
            "RTE_ARRV_TM_2": "15분43초후[8번째 전]",
            "RTE_ARRV_STN_2": "총신대입구역.남성사계시장입구앞"
          },
          {
            "RTE_STN_NM": "방배역.백석예술대학교",
            "RTE_NM": "461",
            "RTE_ID": "100100071",
            "RTE_SECT": "방배동대우효령아파트앞~방배역.백석예술대학교",
            "RTE_CONGEST_1": "여유",
            "RTE_ARRV_TM_1": "2분후[2번째 전]",
            "RTE_ARRV_STN_1": "종로교회앞",
            "RTE_CONGEST_2": "여유",
            "RTE_ARRV_TM_2": "9분8초후[6번째 전]",
            "RTE_ARRV_STN_2": "남서울농협남현동지점"
          },
          {
            "RTE_STN_NM": "방배역.백석예술대학교",
            "RTE_NM": "641",
            "RTE_ID": "100100094",
            "RTE_SECT": "방배동대우효령아파트앞~방배역.백석예술대학교",
            "RTE_CONGEST_1": "여유",
            "RTE_ARRV_TM_1": "1분후[1번째 전]",
            "RTE_ARRV_STN_1": "방배동대우효령아파트앞",
            "RTE_CONGEST_2": "여유",
            "RTE_ARRV_TM_2": "12분9초후[7번째 전]",
            "RTE_ARRV_STN_2": "인헌중고.서울미술고"
          }
        ]
      },
      {
        "BUS_RESULT_MSG": "정상 호출되었습니다.",
        "BUS_STN_ID": "121000313",
        "BUS_ARS_ID": "22395",
        "BUS_STN_NM": "방배역",
        "BUS_STN_X": "126.997238",
        "BUS_STN_Y": "37.482326",
        "BUS_DETAIL": [
          {
            "RTE_STN_NM": "방배역",
            "RTE_NM": "4319",
            "RTE_ID": "100100427",
            "RTE_SECT": "방배동신동아아파트~방배역",
            "RTE_CONGEST_1": "여유",
            "RTE_ARRV_TM_1": "곧 도착",
            "RTE_ARRV_STN_1": "방배역",
            "RTE_CONGEST_2": "여유",
            "RTE_ARRV_TM_2": "12분41초후[7번째 전]",
            "RTE_ARRV_STN_2": "서초그랑자이아파트"
          }
        ]
      },
      {
        "BUS_RESULT_MSG": "정상 호출되었습니다.",
        "BUS_STN_ID": "121900259",
        "BUS_ARS_ID": "22436",
        "BUS_STN_NM": "방배1동주민센터.방배아크로타워",
        "BUS_STN_X": "126.996256",
        "BUS_STN_Y": "37.483491",
        "BUS_DETAIL": [
          {
            "RTE_STN_NM": "방배1동주민센터.방배아크로타워",
            "RTE_NM": "서초07",
            "RTE_ID": "121900011",
            "RTE_SECT": "방일초등학교~대명빌딩",
            "RTE_CONGEST_1": "정보없음",
            "RTE_ARRV_TM_1": "출발대기",
            "RTE_ARRV_STN_1": null,
            "RTE_CONGEST_2": "정보없음",
            "RTE_ARRV_TM_2": "출발대기",
            "RTE_ARRV_STN_2": null
          },
          {
            "RTE_STN_NM": "방배1동주민센터.방배아크로타워",
            "RTE_NM": "서초15",
            "RTE_ID": "121900012",
            "RTE_SECT": "방일초등학교~대명빌딩",
            "RTE_CONGEST_1": "",
            "RTE_ARRV_TM_1": "7분54초후[7번째 전]",
            "RTE_ARRV_STN_1": "카페골목입구",
            "RTE_CONGEST_2": "정보없음",
            "RTE_ARRV_TM_2": "출발대기",
            "RTE_ARRV_STN_2": null
          }
        ]
      },
      {
        "BUS_RESULT_MSG": "정상 호출되었습니다.",
        "BUS_STN_ID": "121900269",
        "BUS_ARS_ID": "22516",
        "BUS_STN_NM": "방배역.백석대",
        "BUS_STN_X": "126.9967265422",
        "BUS_STN_Y": "37.4809786482",
        "BUS_DETAIL": [
          {
            "RTE_STN_NM": "방배역.백석대",
            "RTE_NM": "서초16",
            "RTE_ID": "119900005",
            "RTE_SECT": "대우효령아파트~방배역.백석대",
            "RTE_CONGEST_1": "",
            "RTE_ARRV_TM_1": "8분50초후[8번째 전]",
            "RTE_ARRV_STN_1": "이수역5번출구",
            "RTE_CONGEST_2": "정보없음",
            "RTE_ARRV_TM_2": "출발대기",
            "RTE_ARRV_STN_2": null
          },
          {
            "RTE_STN_NM": "방배역.백석대",
            "RTE_NM": "서초17",
            "RTE_ID": "119900004",
            "RTE_SECT": "대우효령아파트~방배역.백석대",
            "RTE_CONGEST_1": "",
            "RTE_ARRV_TM_1": "3분36초후[4번째 전]",
            "RTE_ARRV_STN_1": "서울교통공사",
            "RTE_CONGEST_2": "정보없음",
            "RTE_ARRV_TM_2": "출발대기",
            "RTE_ARRV_STN_2": null
          }
        ]
      },
      {
        "BUS_RESULT_MSG": "정상 호출되었습니다.",
        "BUS_STN_ID": "121900118",
        "BUS_ARS_ID": "22574",
        "BUS_STN_NM": "방배(백석예술대)역.서초프라자약국",
        "BUS_STN_X": "126.9973009069",
        "BUS_STN_Y": "37.4822348038",
        "BUS_DETAIL": [
          {
            "RTE_STN_NM": "방배(백석예술대)역.서초프라자약국",
            "RTE_NM": "서초07",
            "RTE_ID": "121900011",
            "RTE_SECT": "방배역~방배역.서초프라자약국",
            "RTE_CONGEST_1": "",
            "RTE_ARRV_TM_1": "7분50초후[5번째 전]",
            "RTE_ARRV_STN_1": "방배동래미안아트힐.국립국악원",
            "RTE_CONGEST_2": "정보없음",
            "RTE_ARRV_TM_2": "출발대기",
            "RTE_ARRV_STN_2": null
          },
          {
            "RTE_STN_NM": "방배(백석예술대)역.서초프라자약국",
            "RTE_NM": "서초15",
            "RTE_ID": "121900012",
            "RTE_SECT": "대우효령아파트~방배역.서초프라자약국",
            "RTE_CONGEST_1": "",
            "RTE_ARRV_TM_1": "2분후[2번째 전]",
            "RTE_ARRV_STN_1": "백산빌딩",
            "RTE_CONGEST_2": "",
            "RTE_ARRV_TM_2": "10분27초후[5번째 전]",
            "RTE_ARRV_STN_2": "사당역"
          }
        ]
      },
      {
        "BUS_RESULT_MSG": "정상 호출되었습니다.",
        "BUS_STN_ID": "121000516",
        "BUS_ARS_ID": "22808",
        "BUS_STN_NM": "방배역",
        "BUS_STN_X": "126.9964065362",
        "BUS_STN_Y": "37.4811876954",
        "BUS_DETAIL": [
          {
            "RTE_STN_NM": "방배역",
            "RTE_NM": "6016",
            "RTE_ID": "100100423",
            "RTE_SECT": "서울고교~방배역",
            "RTE_CONGEST_1": "",
            "RTE_ARRV_TM_1": "6분26초후[1번째 전]",
            "RTE_ARRV_STN_1": "서울고교",
            "RTE_CONGEST_2": "",
            "RTE_ARRV_TM_2": "[차고지출발] ",
            "RTE_ARRV_STN_2": "남부터미널"
          }
        ]
      },
      {
        "BUS_RESULT_MSG": "정상 호출되었습니다.",
        "BUS_STN_ID": "121900264",
        "BUS_ARS_ID": "22981",
        "BUS_STN_NM": "방배(백석예술대)역.3번출구",
        "BUS_STN_X": "126.9964879477",
        "BUS_STN_Y": "37.4812111266",
        "BUS_DETAIL": [
          {
            "RTE_STN_NM": "방배(백석예술대)역.3번출구",
            "RTE_NM": "서초16",
            "RTE_ID": "119900005",
            "RTE_SECT": "방배역.백석대~방배역3번출구",
            "RTE_CONGEST_1": "",
            "RTE_ARRV_TM_1": "9분56초후[9번째 전]",
            "RTE_ARRV_STN_1": "이수역5번출구",
            "RTE_CONGEST_2": "정보없음",
            "RTE_ARRV_TM_2": "출발대기",
            "RTE_ARRV_STN_2": null
          },
          {
            "RTE_STN_NM": "방배(백석예술대)역.3번출구",
            "RTE_NM": "서초17",
            "RTE_ID": "119900004",
            "RTE_SECT": "제약회관~방배역3번출구",
            "RTE_CONGEST_1": "",
            "RTE_ARRV_TM_1": "곧 도착",
            "RTE_ARRV_STN_1": "방배(백석예술대)역3번출구",
            "RTE_CONGEST_2": "",
            "RTE_ARRV_TM_2": "13분4초후[10번째 전]",
            "RTE_ARRV_STN_2": "서울시인재개발원입구"
          }
        ]
      }
    ],
    "ACDNT_CNTRL_STTS": [],
    "SBIKE_STTS": [],
    "WEATHER_STTS": [
      {
        "WEATHER_TIME": "2025-04-21 12:50",
        "TEMP": "24.9",
        "SENSIBLE_TEMP": "24.9",
        "MAX_TEMP": "26.0",
        "MIN_TEMP": "17.0",
        "HUMIDITY": "51",
        "WIND_DIRCT": "N",
        "WIND_SPD": "1.2",
        "PRECIPITATION": "-",
        "PRECPT_TYPE": "없음",
        "PCP_MSG": "비 또는 눈 소식이 없어요.",
        "SUNRISE": "05:49",
        "SUNSET": "19:13",
        "UV_INDEX_LVL": "6",
        "UV_INDEX": "높음",
        "UV_MSG": "햇볕에 노출 시 1-2시간 이내에도 피부 화상을 입을 수 있어 위험해요.한낮에는 실내나 그늘에 머물러주세요.외출시 긴 소매 옷, 모자, 선글라스를 착용해주세요.자외선 차단제를 정기적으로 발라주세요.",
        "PM25_INDEX": "좋음",
        "PM25": "14",
        "PM10_INDEX": "보통",
        "PM10": "35",
        "AIR_IDX": "보통",
        "AIR_IDX_MVL": "62.0",
        "AIR_IDX_MAIN": "O3",
        "AIR_MSG": "호흡기가 예민하신 분들은 몸상태 유의하며 활동해주세요.",
        "FCST24HOURS": [
          {
            "FCST_DT": "202504211300",
            "TEMP": "26",
            "PRECIPITATION": "-",
            "PRECPT_TYPE": "없음",
            "RAIN_CHANCE": "0",
            "SKY_STTS": "흐림"
          },
          {
            "FCST_DT": "202504211400",
            "TEMP": "26",
            "PRECIPITATION": "-",
            "PRECPT_TYPE": "없음",
            "RAIN_CHANCE": "0",
            "SKY_STTS": "흐림"
          },
          {
            "FCST_DT": "202504211500",
            "TEMP": "25",
            "PRECIPITATION": "-",
            "PRECPT_TYPE": "없음",
            "RAIN_CHANCE": "0",
            "SKY_STTS": "흐림"
          },
          {
            "FCST_DT": "202504211600",
            "TEMP": "25",
            "PRECIPITATION": "-",
            "PRECPT_TYPE": "없음",
            "RAIN_CHANCE": "0",
            "SKY_STTS": "구름많음"
          },
          {
            "FCST_DT": "202504211700",
            "TEMP": "25",
            "PRECIPITATION": "-",
            "PRECPT_TYPE": "없음",
            "RAIN_CHANCE": "0",
            "SKY_STTS": "구름많음"
          },
          {
            "FCST_DT": "202504211800",
            "TEMP": "23",
            "PRECIPITATION": "-",
            "PRECPT_TYPE": "없음",
            "RAIN_CHANCE": "0",
            "SKY_STTS": "흐림"
          },
          {
            "FCST_DT": "202504211900",
            "TEMP": "20",
            "PRECIPITATION": "-",
            "PRECPT_TYPE": "없음",
            "RAIN_CHANCE": "0",
            "SKY_STTS": "맑음"
          },
          {
            "FCST_DT": "202504212000",
            "TEMP": "20",
            "PRECIPITATION": "-",
            "PRECPT_TYPE": "없음",
            "RAIN_CHANCE": "0",
            "SKY_STTS": "맑음"
          },
          {
            "FCST_DT": "202504212100",
            "TEMP": "19",
            "PRECIPITATION": "-",
            "PRECPT_TYPE": "없음",
            "RAIN_CHANCE": "0",
            "SKY_STTS": "맑음"
          },
          {
            "FCST_DT": "202504212200",
            "TEMP": "19",
            "PRECIPITATION": "-",
            "PRECPT_TYPE": "없음",
            "RAIN_CHANCE": "20",
            "SKY_STTS": "구름많음"
          },
          {
            "FCST_DT": "202504212300",
            "TEMP": "18",
            "PRECIPITATION": "-",
            "PRECPT_TYPE": "없음",
            "RAIN_CHANCE": "20",
            "SKY_STTS": "구름많음"
          },
          {
            "FCST_DT": "202504220000",
            "TEMP": "18",
            "PRECIPITATION": "-",
            "PRECPT_TYPE": "없음",
            "RAIN_CHANCE": "20",
            "SKY_STTS": "구름많음"
          },
          {
            "FCST_DT": "202504220100",
            "TEMP": "18",
            "PRECIPITATION": "-",
            "PRECPT_TYPE": "없음",
            "RAIN_CHANCE": "30",
            "SKY_STTS": "흐림"
          },
          {
            "FCST_DT": "202504220200",
            "TEMP": "18",
            "PRECIPITATION": "-",
            "PRECPT_TYPE": "없음",
            "RAIN_CHANCE": "30",
            "SKY_STTS": "흐림"
          },
          {
            "FCST_DT": "202504220300",
            "TEMP": "18",
            "PRECIPITATION": "-",
            "PRECPT_TYPE": "없음",
            "RAIN_CHANCE": "30",
            "SKY_STTS": "흐림"
          },
          {
            "FCST_DT": "202504220400",
            "TEMP": "17",
            "PRECIPITATION": "-",
            "PRECPT_TYPE": "없음",
            "RAIN_CHANCE": "30",
            "SKY_STTS": "흐림"
          },
          {
            "FCST_DT": "202504220500",
            "TEMP": "17",
            "PRECIPITATION": "1 미만",
            "PRECPT_TYPE": "비",
            "RAIN_CHANCE": "60",
            "SKY_STTS": "흐림"
          },
          {
            "FCST_DT": "202504220600",
            "TEMP": "17",
            "PRECIPITATION": "1 미만",
            "PRECPT_TYPE": "비",
            "RAIN_CHANCE": "60",
            "SKY_STTS": "흐림"
          },
          {
            "FCST_DT": "202504220700",
            "TEMP": "17",
            "PRECIPITATION": "-",
            "PRECPT_TYPE": "없음",
            "RAIN_CHANCE": "30",
            "SKY_STTS": "흐림"
          },
          {
            "FCST_DT": "202504220800",
            "TEMP": "17",
            "PRECIPITATION": "1.0",
            "PRECPT_TYPE": "비",
            "RAIN_CHANCE": "60",
            "SKY_STTS": "흐림"
          },
          {
            "FCST_DT": "202504220900",
            "TEMP": "17",
            "PRECIPITATION": "5.0",
            "PRECPT_TYPE": "비",
            "RAIN_CHANCE": "65",
            "SKY_STTS": "흐림"
          },
          {
            "FCST_DT": "202504221000",
            "TEMP": "17",
            "PRECIPITATION": "5.0",
            "PRECPT_TYPE": "비",
            "RAIN_CHANCE": "66",
            "SKY_STTS": "흐림"
          },
          {
            "FCST_DT": "202504221100",
            "TEMP": "17",
            "PRECIPITATION": "4.0",
            "PRECPT_TYPE": "비",
            "RAIN_CHANCE": "62",
            "SKY_STTS": "흐림"
          },
          {
            "FCST_DT": "202504221200",
            "TEMP": "17",
            "PRECIPITATION": "6.0",
            "PRECPT_TYPE": "비",
            "RAIN_CHANCE": "70",
            "SKY_STTS": "흐림"
          }
        ],
        "NEWS_LIST": []
      }
    ],
    "CHARGER_STTS": [
      {
        "STAT_NM": "서울시 서초구 방배아크로타워",
        "STAT_ID": "PI200889",
        "STAT_ADDR": "서울특별시 서초구 방배로13길 18",
        "STAT_X": "126.99528895",
        "STAT_Y": "37.483136619",
        "STAT_USETIME": "24시간 이용가능",
        "STAT_PARKPAY": "Y",
        "STAT_LIMITYN": "N",
        "STAT_LIMITDETAIL": "",
        "STAT_KINDDETAIL": "아파트",
        "CHARGER_DETAILS": [
          {
            "CHARGER_ID": "01",
            "CHARGER_TYPE": "AC완속",
            "CHARGER_STAT": "충전중",
            "STATUPDDT": "2025-04-21 08:54",
            "LASTTSDT": "2025-04-21 08:53",
            "LASTTEDT": "2025-04-21 08:53",
            "NOWTSDT": "2025-04-21 08:54",
            "OUTPUT": "7",
            "METHOD": "단독"
          },
          {
            "CHARGER_ID": "02",
            "CHARGER_TYPE": "AC완속",
            "CHARGER_STAT": "사용가능",
            "STATUPDDT": "2025-04-21 05:04",
            "LASTTSDT": "2025-04-20 17:02",
            "LASTTEDT": "2025-04-20 17:02",
            "NOWTSDT": null,
            "OUTPUT": "7",
            "METHOD": "단독"
          },
          {
            "CHARGER_ID": "03",
            "CHARGER_TYPE": "AC완속",
            "CHARGER_STAT": "충전중",
            "STATUPDDT": "2025-04-21 08:34",
            "LASTTSDT": "2025-04-21 08:33",
            "LASTTEDT": "2025-04-21 08:33",
            "NOWTSDT": "2025-04-21 08:34",
            "OUTPUT": "7",
            "METHOD": "단독"
          }
        ]
      }
    ],
    "EVENT_STTS": [],
    "LIVE_CMRCL_STTS": {
      "AREA_CMRCL_LVL": "분주한",
      "AREA_SH_PAYMENT_CNT": "63",
      "AREA_SH_PAYMENT_AMT_MIN": 950000,
      "AREA_SH_PAYMENT_AMT_MAX": 1000000,
      "CMRCL_RSB": [
        {
          "RSB_LRG_CTGR": "음식·음료",
          "RSB_MID_CTGR": "한식",
          "RSB_PAYMENT_LVL": "분주한",
          "RSB_SH_PAYMENT_CNT": 21,
          "RSB_SH_PAYMENT_AMT_MIN": 350000,
          "RSB_SH_PAYMENT_AMT_MAX": 400000,
          "RSB_MCT_CNT": 65,
          "RSB_MCT_TIME": "202503"
        },
        {
          "RSB_LRG_CTGR": "음식·음료",
          "RSB_MID_CTGR": "일식/중식/양식",
          "RSB_PAYMENT_LVL": "분주한",
          "RSB_SH_PAYMENT_CNT": 6,
          "RSB_SH_PAYMENT_AMT_MIN": 300000,
          "RSB_SH_PAYMENT_AMT_MAX": 350000,
          "RSB_MCT_CNT": 26,
          "RSB_MCT_TIME": "202503"
        },
        {
          "RSB_LRG_CTGR": "음식·음료",
          "RSB_MID_CTGR": "제과/커피/패스트푸드",
          "RSB_PAYMENT_LVL": "분주한",
          "RSB_SH_PAYMENT_CNT": 15,
          "RSB_SH_PAYMENT_AMT_MIN": 90000,
          "RSB_SH_PAYMENT_AMT_MAX": 100000,
          "RSB_MCT_CNT": 19,
          "RSB_MCT_TIME": "202503"
        },
        {
          "RSB_LRG_CTGR": "음식·음료",
          "RSB_MID_CTGR": "기타요식",
          "RSB_PAYMENT_LVL": "보통",
          "RSB_SH_PAYMENT_CNT": 11,
          "RSB_SH_PAYMENT_AMT_MIN": 90000,
          "RSB_SH_PAYMENT_AMT_MAX": 100000,
          "RSB_MCT_CNT": 49,
          "RSB_MCT_TIME": "202503"
        },
        {
          "RSB_LRG_CTGR": "의료",
          "RSB_MID_CTGR": "병원",
          "RSB_PAYMENT_LVL": "한산한",
          "RSB_SH_PAYMENT_CNT": 4,
          "RSB_SH_PAYMENT_AMT_MIN": 40000,
          "RSB_SH_PAYMENT_AMT_MAX": 50000,
          "RSB_MCT_CNT": 54,
          "RSB_MCT_TIME": "202503"
        },
        {
          "RSB_LRG_CTGR": "의료",
          "RSB_MID_CTGR": "약국",
          "RSB_PAYMENT_LVL": "한산한",
          "RSB_SH_PAYMENT_CNT": 6,
          "RSB_SH_PAYMENT_AMT_MIN": 30000,
          "RSB_SH_PAYMENT_AMT_MAX": 40000,
          "RSB_MCT_CNT": 12,
          "RSB_MCT_TIME": "202503"
        }
      ],
      "CMRCL_MALE_RATE": 45.2,
      "CMRCL_FEMALE_RATE": 54.8,
      "CMRCL_10_RATE": 5.9,
      "CMRCL_20_RATE": 23.6,
      "CMRCL_30_RATE": 23.9,
      "CMRCL_40_RATE": 20.1,
      "CMRCL_50_RATE": 20.6,
      "CMRCL_60_RATE": 5.9,
      "CMRCL_PERSONAL_RATE": 63.7,
      "CMRCL_CORPORATION_RATE": 36.3,
      "CMRCL_TIME": "20250421 1240"
    }
  }
}