{
  "list_total_count": 1,
  "RESULT": {
    "RESULT.CODE": "INFO-000",
    "RESULT.MESSAGE": "정상 처리되었습니다."
  },
  "CITYDATA": {
    "AREA_NM": "청담동 명품거리",
    "AREA_CD": "POI080",
    "LIVE_PPLTN_STTS": [
      {
        "AREA_NM": "청담동 명품거리",
        "AREA_CD": "POI080",
        "AREA_CONGEST_LVL": "보통",
        "AREA_CONGEST_MSG": "사람이 몰려있을 수 있지만 크게 붐비지는 않아요. 도보 이동에 큰 제약이 없어요.",
        "AREA_PPLTN_MIN": "7000",
        "AREA_PPLTN_MAX": "7500",
        "MALE_PPLTN_RATE": "41.5",
        "FEMALE_PPLTN_RATE": "58.5",
        "PPLTN_RATE_0": "0.3",
        "PPLTN_RATE_10": "3.0",
        "PPLTN_RATE_20": "21.2",
        "PPLTN_RATE_30": "29.0",
        "PPLTN_RATE_40": "24.6",
        "PPLTN_RATE_50": "11.7",
        "PPLTN_RATE_60": "6.9",
        "PPLTN_RATE_70": "3.4",
        "RESNT_PPLTN_RATE": "29.7",
        "NON_RESNT_PPLTN_RATE": "70.3",
        "REPLACE_YN": "N",
        "PPLTN_TIME": "2025-04-21 12:40",
        "FCST_YN": "Y",
        "FCST_PPLTN": [
          {
            "FCST_TIME": "2025-04-21 14:00",
            "FCST_CONGEST_LVL": "약간 붐빔",
            "FCST_PPLTN_MIN": "7500",
            "FCST_PPLTN_MAX": "8000"
          },
          {
            "FCST_TIME": "2025-04-21 15:00",
            "FCST_CONGEST_LVL": "약간 붐빔",
            "FCST_PPLTN_MIN": "7500",
            "FCST_PPLTN_MAX": "8000"
          },
          {
            "FCST_TIME": "2025-04-21 16:00",
            "FCST_CONGEST_LVL": "약간 붐빔",
            "FCST_PPLTN_MIN": "7500",
            "FCST_PPLTN_MAX": "8000"
          },
          {
            "FCST_TIME": "2025-04-21 17:00",
            "FCST_CONGEST_LVL": "약간 붐빔",
            "FCST_PPLTN_MIN": "7500",
            "FCST_PPLTN_MAX": "8000"
          },
          {
            "FCST_TIME": "2025-04-21 18:00",
            "FCST_CONGEST_LVL": "약간 붐빔",
            "FCST_PPLTN_MIN": "7000",
            "FCST_PPLTN_MAX": "7500"
          },
          {
            "FCST_TIME": "2025-04-21 19:00",
            "FCST_CONGEST_LVL": "약간 붐빔",
            "FCST_PPLTN_MIN": "6500",
            "FCST_PPLTN_MAX": "7000"
          },
          {
            "FCST_TIME": "2025-04-21 20:00",
            "FCST_CONGEST_LVL": "보통",
            "FCST_PPLTN_MIN": "5500",
            "FCST_PPLTN_MAX": "6000"
          },
          {
            "FCST_TIME": "2025-04-21 21:00",
            "FCST_CONGEST_LVL": "여유",
            "FCST_PPLTN_MIN": "4500",
            "FCST_PPLTN_MAX": "5000"
          },
          {
            "FCST_TIME": "2025-04-21 22:00",
            "FCST_CONGEST_LVL": "여유",
            "FCST_PPLTN_MIN": "3500",
            "FCST_PPLTN_MAX": "4000"
          },
          {
            "FCST_TIME": "2025-04-21 23:00",
            "FCST_CONGEST_LVL": "여유",
            "FCST_PPLTN_MIN": "3000",
            "FCST_PPLTN_MAX": "3500"
          },
          {
            "FCST_TIME": "2025-04-22 00:00",
            "FCST_CONGEST_LVL": "여유",
            "FCST_PPLTN_MIN": "2500",
            "FCST_PPLTN_MAX": "3000"
          },
          {
            "FCST_TIME": "2025-04-22 01:00",
            "FCST_CONGEST_LVL": "여유",
            "FCST_PPLTN_MIN": "2000",
            "FCST_PPLTN_MAX": "2500"
          }
        ]
      }
    ],
    "ROAD_TRAFFIC_STTS": {
      "AVG_ROAD_DATA": {
        "ROAD_MSG": "해당 장소로 이동·진입시 시간이 다소 소요될 수 있어요.",
        "ROAD_TRAFFIC_IDX": "서행",
        "ROAD_TRAFFIC_SPD": 19,
        "ROAD_TRAFFIC_TIME": "2025-04-21 13:00"
      },
      "ROAD_TRAFFIC_STTS": [
        {
          "LINK_ID": "1220033403",
          "ROAD_NM": "선릉로",
          "START_ND_CD": "1220050900",
          "START_ND_NM": "영동고교",
          "START_ND_XY": "127.0396227344423750_37.5216785753609514",
          "END_ND_CD": "1220052200",
          "END_ND_NM": "학동사거리",
          "END_ND_XY": "127.0391508912950087_37.5231966635705092",
          "DIST": "175.0",
          "SPD": 21.0,
          "IDX": "서행",
          "XYLIST": "127.0390832416087932_37.5231922629546233|127.0391133064020863_37.5228990829912732|127.0395574844147575_37.5216636928451095"
        },
        {
          "LINK_ID": "1220033503",
          "ROAD_NM": "선릉로",
          "START_ND_CD": "1220052200",
          "START_ND_NM": "학동사거리",
          "START_ND_XY": "127.0391508912950087_37.5231966635705092",
          "END_ND_CD": "1220050900",
          "END_ND_NM": "영동고교",
          "END_ND_XY": "127.0396227344423750_37.5216785753609514",
          "DIST": "173.0",
          "SPD": 11.0,
          "IDX": "정체",
          "XYLIST": "127.0396879856271255_37.5216934578402785|127.0392475112795978_37.5229185559885323|127.0392185409890971_37.5232010641476563"
        },
        {
          "LINK_ID": "1220034002",
          "ROAD_NM": "삼성로",
          "START_ND_CD": "1220049200",
          "START_ND_NM": "청담천주교회",
          "START_ND_XY": "127.0496435629604690_37.5199617505320830",
          "END_ND_CD": "1220053000",
          "END_ND_NM": "청담사거리",
          "END_ND_XY": "127.0473765747084940_37.5242378014164260",
          "DIST": "515.0",
          "SPD": 32.0,
          "IDX": "원활",
          "XYLIST": "127.0473139778392380_37.5242168998292556|127.0489834009505756_37.5210453154687968|127.0495812322759406_37.5199403562690108"
        },
        {
          "LINK_ID": "1220034102",
          "ROAD_NM": "삼성로",
          "START_ND_CD": "1220053000",
          "START_ND_NM": "청담사거리",
          "START_ND_XY": "127.0473765747084940_37.5242378014164260",
          "END_ND_CD": "1220049200",
          "END_ND_NM": "청담천주교회",
          "END_ND_XY": "127.0496435629604690_37.5199617505320830",
          "DIST": "515.0",
          "SPD": 19.0,
          "IDX": "서행",
          "XYLIST": "127.0497058936811783_37.5199831456631614|127.0491083304976456_37.5210876125254487|127.0474391716132061_37.5242587038713253"
        },
        {
          "LINK_ID": "1220034204",
          "ROAD_NM": "도산대로",
          "START_ND_CD": "1220051800",
          "START_ND_NM": "영동소방",
          "START_ND_XY": "127.0373845961656087_37.5226568037103831",
          "END_ND_CD": "1220052200",
          "END_ND_NM": "학동사거리",
          "END_ND_XY": "127.0391508912950087_37.5231966635705092",
          "DIST": "167.0",
          "SPD": 37.0,
          "IDX": "원활",
          "XYLIST": "127.0391265743657243_37.5232471349778507|127.0373602782215130_37.5227072756602453"
        },
        {
          "LINK_ID": "1220034304",
          "ROAD_NM": "도산대로",
          "START_ND_CD": "1220052200",
          "START_ND_NM": "학동사거리",
          "START_ND_XY": "127.0391508912950087_37.5231966635705092",
          "END_ND_CD": "1220051800",
          "END_ND_NM": "영동소방",
          "END_ND_XY": "127.0373845961656087_37.5226568037103831",
          "DIST": "167.0",
          "SPD": 15.0,
          "IDX": "서행",
          "XYLIST": "127.0374089140773890_37.5226063326561103|127.0391752081915371_37.5231461921577747"
        },
        {
          "LINK_ID": "1220034601",
          "ROAD_NM": "도산대로",
          "START_ND_CD": "1220052200",
          "START_ND_NM": "학동사거리",
          "START_ND_XY": "127.0391508912950087_37.5231966635705092",
          "END_ND_CD": "1220052400",
          "END_ND_NM": "동궁타운앞",
          "END_ND_XY": "127.0413838928056833_37.5234724352375437",
          "DIST": "200.0",
          "SPD": 23.0,
          "IDX": "서행",
          "XYLIST": "127.0413734933095924_37.5235258575155015|127.0391404902441508_37.5232500847542312"
        },
        {
          "LINK_ID": "1220034602",
          "ROAD_NM": "도산대로",
          "START_ND_CD": "1220052400",
          "START_ND_NM": "동궁타운앞",
          "START_ND_XY": "127.0413838928056833_37.5234724352375437",
          "END_ND_CD": "1220052600",
          "END_ND_NM": "CJ미디어",
          "END_ND_XY": "127.0446346541440903_37.5238908194591545",
          "DIST": "291.0",
          "SPD": 37.0,
          "IDX": "원활",
          "XYLIST": "127.0446238281292324_37.5239441872189801|127.0413730634038956_37.5235258027049525"
        },
        {
          "LINK_ID": "1220034603",
          "ROAD_NM": "도산대로",
          "START_ND_CD": "1220052600",
          "START_ND_NM": "CJ미디어",
          "START_ND_XY": "127.0446346541440903_37.5238908194591545",
          "END_ND_CD": "1220053000",
          "END_ND_NM": "청담사거리",
          "END_ND_XY": "127.0473765747084940_37.5242378014164260",
          "DIST": "245.0",
          "SPD": 31.0,
          "IDX": "원활",
          "XYLIST": "127.0473659248258400_37.5242911918783406|127.0446240023562581_37.5239442096781985"
        },
        {
          "LINK_ID": "1220034701",
          "ROAD_NM": "도산대로",
          "START_ND_CD": "1220052400",
          "START_ND_NM": "동궁타운앞",
          "START_ND_XY": "127.0413838928056833_37.5234724352375437",
          "END_ND_CD": "1220052200",
          "END_ND_NM": "학동사거리",
          "END_ND_XY": "127.0391508912950087_37.5231966635705092",
          "DIST": "200.0",
          "SPD": 20.0,
          "IDX": "서행",
          "XYLIST": "127.0391612923310447_37.5231432423854017|127.0413942922874782_37.5234190138592112"
        },
        {
          "LINK_ID": "1220034702",
          "ROAD_NM": "도산대로",
          "START_ND_CD": "1220052600",
          "START_ND_NM": "CJ미디어",
          "START_ND_XY": "127.0446346541440903_37.5238908194591545",
          "END_ND_CD": "1220052400",
          "END_ND_NM": "동궁타운앞",
          "END_ND_XY": "127.0413838928056833_37.5234724352375437",
          "DIST": "291.0",
          "SPD": 35.0,
          "IDX": "원활",
          "XYLIST": "127.0413947210608256_37.5234190677690904|127.0446454812748271_37.5238374516974602"
        },
        {
          "LINK_ID": "1220034703",
          "ROAD_NM": "도산대로",
          "START_ND_CD": "1220053000",
          "START_ND_NM": "청담사거리",
          "START_ND_XY": "127.0473765747084940_37.5242378014164260",
          "END_ND_CD": "1220052600",
          "END_ND_NM": "CJ미디어",
          "END_ND_XY": "127.0446346541440903_37.5238908194591545",
          "DIST": "245.0",
          "SPD": 15.0,
          "IDX": "서행",
          "XYLIST": "127.0446453070480288_37.5238374292382488|127.0473872245760560_37.5241844109530760"
        },
        {
          "LINK_ID": "1220034801",
          "ROAD_NM": "도산대로",
          "START_ND_CD": "1220053000",
          "START_ND_NM": "청담사거리",
          "START_ND_XY": "127.0473765747084940_37.5242378014164260",
          "END_ND_CD": "1220053200",
          "END_ND_NM": "송담빌딩",
          "END_ND_XY": "127.0482446605530527_37.5243566454065913",
          "DIST": "78.0",
          "SPD": 16.0,
          "IDX": "서행",
          "XYLIST": "127.0482331616209706_37.5244099245679976|127.0473650751771402_37.5242910804948124"
        },
        {
          "LINK_ID": "1220034802",
          "ROAD_NM": "도산대로",
          "START_ND_CD": "1220053200",
          "START_ND_NM": "송담빌딩",
          "START_ND_XY": "127.0482446605530527_37.5243566454065913",
          "END_ND_CD": "1220053500",
          "END_ND_NM": "청담빌딩",
          "END_ND_XY": "127.0504418046321433_37.5246227250812581",
          "DIST": "196.0",
          "SPD": 21.5,
          "IDX": "서행",
          "XYLIST": "127.0504316026370333_37.5246761714863410|127.0482344558950842_37.5244100916258532"
        },
        {
          "LINK_ID": "1220034901",
          "ROAD_NM": "도산대로",
          "START_ND_CD": "1220053200",
          "START_ND_NM": "송담빌딩",
          "START_ND_XY": "127.0482446605530527_37.5243566454065913",
          "END_ND_CD": "1220053000",
          "END_ND_NM": "청담사거리",
          "END_ND_XY": "127.0473765747084940_37.5242378014164260",
          "DIST": "78.0",
          "SPD": 17.0,
          "IDX": "서행",
          "XYLIST": "127.0473880730928471_37.5241845232379347|127.0482561583381766_37.5243033671450803"
        },
        {
          "LINK_ID": "1220034902",
          "ROAD_NM": "도산대로",
          "START_ND_CD": "1220053500",
          "START_ND_NM": "청담빌딩",
          "START_ND_XY": "127.0504418046321433_37.5246227250812581",
          "END_ND_CD": "1220053200",
          "END_ND_NM": "송담빌딩",
          "END_ND_XY": "127.0482446605530527_37.5243566454065913",
          "DIST": "196.0",
          "SPD": 17.0,
          "IDX": "서행",
          "XYLIST": "127.0482548640658536_37.5243032000874521|127.0504520077446102_37.5245692795753101"
        },
        {
          "LINK_ID": "1220035401",
          "ROAD_NM": "선릉로",
          "START_ND_CD": "1220052200",
          "START_ND_NM": "학동사거리",
          "START_ND_XY": "127.0391508912950087_37.5231966635705092",
          "END_ND_CD": "1220052700",
          "END_ND_NM": "키네마극장",
          "END_ND_XY": "127.0393697362186316_37.5240507447578864",
          "DIST": "98.0",
          "SPD": 13.0,
          "IDX": "정체",
          "XYLIST": "127.0393041723874177_37.5240647339338693|127.0391660322892449_37.5236540272358496|127.0391045399377816_37.5234487055447730|127.0390831756950121_37.5232003593851076"
        },
        {
          "LINK_ID": "1220035402",
          "ROAD_NM": "선릉로",
          "START_ND_CD": "1220052700",
          "START_ND_NM": "키네마극장",
          "START_ND_XY": "127.0393697362186316_37.5240507447578864",
          "END_ND_CD": "1220053400",
          "END_ND_NM": "신한양빌딩",
          "END_ND_XY": "127.0395855584502556_37.5246514168335139",
          "DIST": "69.0",
          "SPD": 27.0,
          "IDX": "원활",
          "XYLIST": "127.0395203023055899_37.5246662908092716|127.0393044805535965_37.5240656177146619"
        },
        {
          "LINK_ID": "1220035404",
          "ROAD_NM": "선릉로",
          "START_ND_CD": "1220055400",
          "START_ND_NM": "한양타운앞",
          "START_ND_XY": "127.0399692779188712_37.5257669562929337",
          "END_ND_CD": "1220057300",
          "END_ND_NM": "한양아파트앞교차로",
          "END_ND_XY": "127.0407038224521017_37.5278137647784362",
          "DIST": "236.0",
          "SPD": 17.0,
          "IDX": "서행",
          "XYLIST": "127.0406385581095208_37.5278286213475027|127.0399040140817561_37.5257818124606572"
        },
        {
          "LINK_ID": "1220035501",
          "ROAD_NM": "선릉로",
          "START_ND_CD": "1220052700",
          "START_ND_NM": "키네마극장",
          "START_ND_XY": "127.0393697362186316_37.5240507447578864",
          "END_ND_CD": "1220052200",
          "END_ND_NM": "학동사거리",
          "END_ND_XY": "127.0391508912950087_37.5231966635705092",
          "DIST": "96.0",
          "SPD": 22.0,
          "IDX": "서행",
          "XYLIST": "127.0392186068882836_37.5231929677171081|127.0392392010293747_37.5234323545396080|127.0392976430606637_37.5236274895412407|127.0394353000253318_37.5240367555455165"
        },
        {
          "LINK_ID": "1220035502",
          "ROAD_NM": "선릉로",
          "START_ND_CD": "1220053400",
          "START_ND_NM": "신한양빌딩",
          "START_ND_XY": "127.0395855584502556_37.5246514168335139",
          "END_ND_CD": "1220052700",
          "END_ND_NM": "키네마극장",
          "END_ND_XY": "127.0393697362186316_37.5240507447578864",
          "DIST": "69.0",
          "SPD": 16.5,
          "IDX": "서행",
          "XYLIST": "127.0394349929889728_37.5240358717646814|127.0396508157007531_37.5246365437222806"
        },
        {
          "LINK_ID": "1220035504",
          "ROAD_NM": "선릉로",
          "START_ND_CD": "1220057300",
          "START_ND_NM": "한양아파트앞교차로",
          "START_ND_XY": "127.0407038224521017_37.5278137647784362",
          "END_ND_CD": "1220055400",
          "END_ND_NM": "한양타운앞",
          "END_ND_XY": "127.0399692779188712_37.5257669562929337",
          "DIST": "236.0",
          "SPD": 16.0,
          "IDX": "서행",
          "XYLIST": "127.0400345417300514_37.5257521000890932|127.0407690879000455_37.5277989081729260"
        },
        {
          "LINK_ID": "1220035801",
          "ROAD_NM": "압구정로",
          "START_ND_CD": "1220053000",
          "START_ND_NM": "청담사거리",
          "START_ND_XY": "127.0473765747084940_37.5242378014164260",
          "END_ND_CD": "1220054300",
          "END_ND_NM": "진빌딩",
          "END_ND_XY": "127.0469633959157676_37.5249919963234504",
          "DIST": "91.0",
          "SPD": 7.0,
          "IDX": "정체",
          "XYLIST": "127.0469011838456197_37.5249703762685414|127.0473143631464268_37.5242161824770264"
        },
        {
          "LINK_ID": "1220035802",
          "ROAD_NM": "압구정로",
          "START_ND_CD": "1220054300",
          "START_ND_NM": "진빌딩",
          "START_ND_XY": "127.0469633959157676_37.5249919963234504",
          "END_ND_CD": "1220056100",
          "END_ND_NM": "갤러리아주유소",
          "END_ND_XY": "127.0437559139934081_37.5270338519371265",
          "DIST": "382.0",
          "SPD": 23.0,
          "IDX": "서행",
          "XYLIST": "127.0437355249405158_37.5269822879409816|127.0453114402949382_37.5265870369638819|127.0454843189038030_37.5265227029401203|127.0457602712255323_37.5263963055946590|127.0459803638395186_37.5262716295533281|127.0461746176674325_37.5261167670214704|127.0463298767727736_37.5259242062253477|127.0469021319477463_37.5249687216519305"
        },
        {
          "LINK_ID": "1220035803",
          "ROAD_NM": "압구정로",
          "START_ND_CD": "1220056100",
          "START_ND_NM": "갤러리아주유소",
          "START_ND_XY": "127.0437559139934081_37.5270338519371265",
          "END_ND_CD": "1220056300",
          "END_ND_NM": "압구정로데오역3번출구",
          "END_ND_XY": "127.0423228544176197_37.5274014955076964",
          "DIST": "133.0",
          "SPD": 20.0,
          "IDX": "서행",
          "XYLIST": "127.0423020432017012_37.5273500386375574|127.0437351018957628_37.5269823953168569"
        },
        {
          "LINK_ID": "1220035804",
          "ROAD_NM": "압구정로",
          "START_ND_CD": "1220056300",
          "START_ND_NM": "압구정로데오역3번출구",
          "START_ND_XY": "127.0423228544176197_37.5274014955076964",
          "END_ND_CD": "1220057300",
          "END_ND_NM": "한양아파트앞교차로",
          "END_ND_XY": "127.0407038224521017_37.5278137647784362",
          "DIST": "150.0",
          "SPD": 32.0,
          "IDX": "원활",
          "XYLIST": "127.0406831513658972_37.5277622724390270|127.0423021823328327_37.5273500034486389"
        },
        {
          "LINK_ID": "1220035901",
          "ROAD_NM": "압구정로",
          "START_ND_CD": "1220054300",
          "START_ND_NM": "진빌딩",
          "START_ND_XY": "127.0469633959157676_37.5249919963234504",
          "END_ND_CD": "1220053000",
          "END_ND_NM": "청담사거리",
          "END_ND_XY": "127.0473765747084940_37.5242378014164260",
          "DIST": "91.0",
          "SPD": 23.0,
          "IDX": "서행",
          "XYLIST": "127.0474387863070120_37.5242594212239595|127.0470256080218121_37.5250136163455039"
        },
        {
          "LINK_ID": "1220035902",
          "ROAD_NM": "압구정로",
          "START_ND_CD": "1220056100",
          "START_ND_NM": "갤러리아주유소",
          "START_ND_XY": "127.0437559139934081_37.5270338519371265",
          "END_ND_CD": "1220054300",
          "END_ND_NM": "진빌딩",
          "END_ND_XY": "127.0469633959157676_37.5249919963234504",
          "DIST": "392.0",
          "SPD": 23.3,
          "IDX": "서행",
          "XYLIST": "127.0470246587905478_37.5250152709635429|127.0464487251597916_37.5259769006016342|127.0462809660115369_37.5261849636864042|127.0460683422365946_37.5263544712371200|127.0458336235477645_37.5264874333260394|127.0455470058465579_37.5266187156823534|127.0453607773583826_37.5266880176438349|127.0437763019430832_37.5270854159297258"
        },
        {
          "LINK_ID": "1220035903",
          "ROAD_NM": "압구정로",
          "START_ND_CD": "1220056300",
          "START_ND_NM": "압구정로데오역3번출구",
          "START_ND_XY": "127.0423228544176197_37.5274014955076964",
          "END_ND_CD": "1220056100",
          "END_ND_NM": "갤러리아주유소",
          "END_ND_XY": "127.0437559139934081_37.5270338519371265",
          "DIST": "133.0",
          "SPD": 41.0,
          "IDX": "원활",
          "XYLIST": "127.0437767261191340_37.5270853076522783|127.0423436656621448_37.5274529523736859"
        },
        {
          "LINK_ID": "1220035904",
          "ROAD_NM": "압구정로",
          "START_ND_CD": "1220057300",
          "START_ND_NM": "한양아파트앞교차로",
          "START_ND_XY": "127.0407038224521017_37.5278137647784362",
          "END_ND_CD": "1220056300",
          "END_ND_NM": "압구정로데오역3번출구",
          "END_ND_XY": "127.0423228544176197_37.5274014955076964",
          "DIST": "150.0",
          "SPD": 15.0,
          "IDX": "서행",
          "XYLIST": "127.0423435265308427_37.5274529875626470|127.0407244946980541_37.5278652571133904"
        },
        {
          "LINK_ID": "1220036205",
          "ROAD_NM": "압구정로",
          "START_ND_CD": "1220057900",
          "START_ND_NM": "압구정로데오역6번출구",
          "START_ND_XY": "127.0391535088479600_37.5282052498097229",
          "END_ND_CD": "1220058000",
          "END_ND_NM": "한양아파트36동",
          "END_ND_XY": "127.0383933220305721_37.5284200504224543",
          "DIST": "71.0",
          "SPD": 32.0,
          "IDX": "원활",
          "XYLIST": "127.0383706253105203_37.5283691025467689|127.0391308116757614_37.5281543011775298"
        },
        {
          "LINK_ID": "1220036206",
          "ROAD_NM": "압구정로",
          "START_ND_CD": "1220057300",
          "START_ND_NM": "한양아파트앞교차로",
          "START_ND_XY": "127.0407038224521017_37.5278137647784362",
          "END_ND_CD": "1220057900",
          "END_ND_NM": "압구정로데오역6번출구",
          "END_ND_XY": "127.0391535088479600_37.5282052498097229",
          "DIST": "144.0",
          "SPD": 14.0,
          "IDX": "정체",
          "XYLIST": "127.0391329936891651_37.5281537175064059|127.0406833063349836_37.5277622336425836"
        },
        {
          "LINK_ID": "1220036305",
          "ROAD_NM": "압구정로",
          "START_ND_CD": "1220058000",
          "START_ND_NM": "한양아파트36동",
          "START_ND_XY": "127.0383933220305721_37.5284200504224543",
          "END_ND_CD": "1220057900",
          "END_ND_NM": "압구정로데오역6번출구",
          "END_ND_XY": "127.0391535088479600_37.5282052498097229",
          "DIST": "71.0",
          "SPD": 31.0,
          "IDX": "원활",
          "XYLIST": "127.0391762060510530_37.5282561984370773|127.0384160187819447_37.5284709991943046"
        },
        {
          "LINK_ID": "1220036306",
          "ROAD_NM": "압구정로",
          "START_ND_CD": "1220057900",
          "START_ND_NM": "압구정로데오역6번출구",
          "START_ND_XY": "127.0391535088479600_37.5282052498097229",
          "END_ND_CD": "1220057300",
          "END_ND_NM": "한양아파트앞교차로",
          "END_ND_XY": "127.0407038224521017_37.5278137647784362",
          "DIST": "144.0",
          "SPD": 18.0,
          "IDX": "서행",
          "XYLIST": "127.0407243397292376_37.5278652968109085|127.0391740240345371_37.5282567812080075"
        },
        {
          "LINK_ID": "1220036400",
          "ROAD_NM": "선릉로",
          "START_ND_CD": "1220057300",
          "START_ND_NM": "한양아파트앞교차로",
          "START_ND_XY": "127.0407038224521017_37.5278137647784362",
          "END_ND_CD": "1220059500",
          "END_ND_NM": "한양아파트81동",
          "END_ND_XY": "127.0416392497226212_37.5305549297662537",
          "DIST": "315.0",
          "SPD": 12.0,
          "IDX": "정체",
          "XYLIST": "127.0415737440847863_37.5305691075757579|127.0406383201651295_37.5278279429750086"
        },
        {
          "LINK_ID": "1220036500",
          "ROAD_NM": "선릉로",
          "START_ND_CD": "1220059500",
          "START_ND_NM": "한양아파트81동",
          "START_ND_XY": "127.0416392497226212_37.5305549297662537",
          "END_ND_CD": "1220057300",
          "END_ND_NM": "한양아파트앞교차로",
          "END_ND_XY": "127.0407038224521017_37.5278137647784362",
          "DIST": "315.0",
          "SPD": 31.0,
          "IDX": "원활",
          "XYLIST": "127.0407693258460142_37.5277995874461539|127.0417047553351608_37.5305407510194087"
        },
        {
          "LINK_ID": "1220094000",
          "ROAD_NM": "선릉로148길",
          "START_ND_CD": "1220052600",
          "START_ND_NM": "CJ미디어",
          "START_ND_XY": "127.0446346541440903_37.5238908194591545",
          "END_ND_CD": "1220052000",
          "END_ND_NM": "금구빌딩",
          "END_ND_XY": "127.0415328474928032_37.5226839282467068",
          "DIST": "392.0",
          "SPD": 10.0,
          "IDX": "정체",
          "XYLIST": "127.0415436574270984_37.5226305580609463|127.0448670650164331_37.5230575023395261|127.0447017143677471_37.5238991761221996"
        },
        {
          "LINK_ID": "1220094100",
          "ROAD_NM": "선릉로148길",
          "START_ND_CD": "1220052000",
          "START_ND_NM": "금구빌딩",
          "START_ND_XY": "127.0415328474928032_37.5226839282467068",
          "END_ND_CD": "1220052600",
          "END_ND_NM": "CJ미디어",
          "END_ND_XY": "127.0446346541440903_37.5238908194591545",
          "DIST": "368.0",
          "SPD": 11.0,
          "IDX": "정체",
          "XYLIST": "127.0445675950660842_37.5238824618566014|127.0447120599987159_37.5231471090591455|127.0415220386743442_37.5227372984306200"
        },
        {
          "LINK_ID": "1220094400",
          "ROAD_NM": "도산대로58길",
          "START_ND_CD": "1220052400",
          "START_ND_NM": "동궁타운앞",
          "START_ND_XY": "127.0413838928056833_37.5234724352375437",
          "END_ND_CD": "1220052000",
          "END_ND_NM": "금구빌딩",
          "END_ND_XY": "127.0415328474928032_37.5226839282467068",
          "DIST": "88.0",
          "SPD": 9.0,
          "IDX": "정체",
          "XYLIST": "127.0415999660723401_37.5226919713015405|127.0414510120757683_37.5234804783755465"
        },
        {
          "LINK_ID": "1220094500",
          "ROAD_NM": "도산대로58길",
          "START_ND_CD": "1220052000",
          "START_ND_NM": "금구빌딩",
          "START_ND_XY": "127.0415328474928032_37.5226839282467068",
          "END_ND_CD": "1220052400",
          "END_ND_NM": "동궁타운앞",
          "END_ND_XY": "127.0413838928056833_37.5234724352375437",
          "DIST": "88.0",
          "SPD": 18.0,
          "IDX": "서행",
          "XYLIST": "127.0413167724186962_37.5234643920618041|127.0414657289275908_37.5226758851537312"
        },
        {
          "LINK_ID": "1220095300",
          "ROAD_NM": "선릉로152길",
          "START_ND_CD": "1220052400",
          "START_ND_NM": "동궁타운앞",
          "START_ND_XY": "127.0413838928056833_37.5234724352375437",
          "END_ND_CD": "1220052700",
          "END_ND_NM": "키네마극장",
          "END_ND_XY": "127.0393697362186316_37.5240507447578864",
          "DIST": "243.0",
          "SPD": 11.7,
          "IDX": "정체",
          "XYLIST": "127.0393798555148805_37.5239972885161208|127.0411143256185653_37.5242055606259584|127.0411635768105896_37.5242025260138377|127.0411861454816886_37.5241881336430723|127.0413167081312338_37.5234647434752588"
        },
        {
          "LINK_ID": "1220095400",
          "ROAD_NM": "선릉로152길",
          "START_ND_CD": "1220052700",
          "START_ND_NM": "키네마극장",
          "START_ND_XY": "127.0393697362186316_37.5240507447578864",
          "END_ND_CD": "1220052400",
          "END_ND_NM": "동궁타운앞",
          "END_ND_XY": "127.0413838928056833_37.5234724352375437",
          "DIST": "263.0",
          "SPD": 18.0,
          "IDX": "서행",
          "XYLIST": "127.0414510763631597_37.5234801278630101|127.0413128808020531_37.5242458193041557|127.0412157654857310_37.5243077538981922|127.0411093794579500_37.5243143088269946|127.0393596169079586_37.5241042009983374"
        },
        {
          "LINK_ID": "1220095900",
          "ROAD_NM": "도산대로81길",
          "START_ND_CD": "1220053200",
          "START_ND_NM": "송담빌딩",
          "START_ND_XY": "127.0482446605530527_37.5243566454065913",
          "END_ND_CD": "1220054700",
          "END_ND_NM": "횃불교회",
          "END_ND_XY": "127.0478494396997604_37.5250965326488739",
          "DIST": "89.0",
          "SPD": 5.0,
          "IDX": "정체",
          "XYLIST": "127.0477869809606091_37.5250753690680696|127.0481822023195519_37.5243354820317876"
        },
        {
          "LINK_ID": "1220096000",
          "ROAD_NM": "도산대로81길",
          "START_ND_CD": "1220054700",
          "START_ND_NM": "횃불교회",
          "START_ND_XY": "127.0478494396997604_37.5250965326488739",
          "END_ND_CD": "1220053200",
          "END_ND_NM": "송담빌딩",
          "END_ND_XY": "127.0482446605530527_37.5243566454065913",
          "DIST": "89.0",
          "SPD": 16.0,
          "IDX": "서행",
          "XYLIST": "127.0483071188218389_37.5243778087482482|127.0479118984741973_37.5251176961965243"
        },
        {
          "LINK_ID": "1220096600",
          "ROAD_NM": "압구정로79길",
          "START_ND_CD": "1220054700",
          "START_ND_NM": "횃불교회",
          "START_ND_XY": "127.0478494396997604_37.5250965326488739",
          "END_ND_CD": "1220054300",
          "END_ND_NM": "진빌딩",
          "END_ND_XY": "127.0469633959157676_37.5249919963234504",
          "DIST": "79.0",
          "SPD": 14.0,
          "IDX": "정체",
          "XYLIST": "127.0469733424788927_37.5249385196875949|127.0478593856441591_37.5250430559397614"
        },
        {
          "LINK_ID": "1220096700",
          "ROAD_NM": "압구정로79길",
          "START_ND_CD": "1220054300",
          "START_ND_NM": "진빌딩",
          "START_ND_XY": "127.0469633959157676_37.5249919963234504",
          "END_ND_CD": "1220054700",
          "END_ND_NM": "횃불교회",
          "END_ND_XY": "127.0478494396997604_37.5250965326488739",
          "DIST": "79.0",
          "SPD": 9.0,
          "IDX": "정체",
          "XYLIST": "127.0478394937412077_37.5251500093566435|127.0469534493384884_37.5250454729579985"
        },
        {
          "LINK_ID": "1220097400",
          "ROAD_NM": "압구정로79길",
          "START_ND_CD": "1220055900",
          "START_ND_NM": "영동대교남측삼거리",
          "START_ND_XY": "127.0545551252279921_37.5264476838905452",
          "END_ND_CD": "1220054700",
          "END_ND_NM": "횃불교회",
          "END_ND_XY": "127.0478494396997604_37.5250965326488739",
          "DIST": "623.0",
          "SPD": 14.0,
          "IDX": "정체",
          "XYLIST": "127.0478594738904263_37.5250430667160231|127.0508532342909831_37.5253994432076752|127.0526799391542028_37.5256323543877102|127.0531059195704984_37.5256903187941404|127.0534485940314937_37.5257943470844708|127.0545928132392532_37.5264027226948400"
        },
        {
          "LINK_ID": "1220097500",
          "ROAD_NM": "압구정로79길",
          "START_ND_CD": "1220054700",
          "START_ND_NM": "횃불교회",
          "START_ND_XY": "127.0478494396997604_37.5250965326488739",
          "END_ND_CD": "1220055900",
          "END_ND_NM": "영동대교남측삼거리",
          "END_ND_XY": "127.0545551252279921_37.5264476838905452",
          "DIST": "618.0",
          "SPD": 13.0,
          "IDX": "정체",
          "XYLIST": "127.0545174383034208_37.5264926459744146|127.0533859444738596_37.5258910367243601|127.0530699725998858_37.5257951142871136|127.0526577776354173_37.5257390258000711|127.0508324697551927_37.5255062929804595|127.0478394054948410_37.5251499985803747"
        },
        {
          "LINK_ID": "1220097800",
          "ROAD_NM": "압구정로60길",
          "START_ND_CD": "1220056300",
          "START_ND_NM": "압구정로데오역3번출구",
          "START_ND_XY": "127.0423228544176197_37.5274014955076964",
          "END_ND_CD": "1220055400",
          "END_ND_NM": "한양타운앞",
          "END_ND_XY": "127.0399692779188712_37.5257669562929337",
          "DIST": "389.0",
          "SPD": 9.0,
          "IDX": "정체",
          "XYLIST": "127.0399511835114055_37.5257148520557564|127.0415787633461946_37.5253563203214711|127.0416840223929427_37.5253935351535333|127.0423881962359047_37.5273868542196283"
        },
        {
          "LINK_ID": "1220097900",
          "ROAD_NM": "압구정로60길",
          "START_ND_CD": "1220055400",
          "START_ND_NM": "한양타운앞",
          "START_ND_XY": "127.0399692779188712_37.5257669562929337",
          "END_ND_CD": "1220056300",
          "END_ND_NM": "압구정로데오역3번출구",
          "END_ND_XY": "127.0423228544176197_37.5274014955076964",
          "DIST": "369.0",
          "SPD": 14.0,
          "IDX": "정체",
          "XYLIST": "127.0422575125742526_37.5274161376605946|127.0415706244871359_37.5254717370603998|127.0415681080258139_37.5254708477559760|127.0399873712197234_37.5258190596262082"
        },
        {
          "LINK_ID": "1220099600",
          "ROAD_NM": "도산대로81길",
          "START_ND_CD": "1220054700",
          "START_ND_NM": "횃불교회",
          "START_ND_XY": "127.0478494396997604_37.5250965326488739",
          "END_ND_CD": "1220057200",
          "END_ND_NM": "청담매스터빌",
          "END_ND_XY": "127.0440436744389245_37.5277298455036714",
          "DIST": "477.0",
          "SPD": 13.0,
          "IDX": "정체",
          "XYLIST": "127.0440226300654984_37.5276784484929991|127.0455677470908142_37.5272771508824405|127.0460080784356052_37.5271727054180317|127.0462880520407367_37.5270796693870636|127.0464775640202220_37.5269926698991867|127.0467202966966056_37.5268406210517114|127.0469047535877110_37.5266751843469422|127.0470362116366516_37.5265202471221500|127.0471411138227467_37.5263250347476216|127.0477866724968692_37.5250759557453151"
        },
        {
          "LINK_ID": "1220099700",
          "ROAD_NM": "도산대로81길",
          "START_ND_CD": "1220057200",
          "START_ND_NM": "청담매스터빌",
          "START_ND_XY": "127.0440436744389245_37.5277298455036714",
          "END_ND_CD": "1220054700",
          "END_ND_NM": "횃불교회",
          "END_ND_XY": "127.0478494396997604_37.5250965326488739",
          "DIST": "487.0",
          "SPD": 14.0,
          "IDX": "정체",
          "XYLIST": "127.0479122069371130_37.5251171095189591|127.0472662906897625_37.5263668840138749|127.0471559321316022_37.5265722529692027|127.0470122166248785_37.5267416364650757|127.0468137542171689_37.5269196343500084|127.0465538176338356_37.5270824598460280|127.0463483326163185_37.5271767926718951|127.0460537191989800_37.5272746936570698|127.0456081749980797_37.5273803756757260|127.0440647188407297_37.5277812416091479"
        },
        {
          "LINK_ID": "1220100000",
          "ROAD_NM": "압구정로61길",
          "START_ND_CD": "1220057200",
          "START_ND_NM": "청담매스터빌",
          "START_ND_XY": "127.0440436744389245_37.5277298455036714",
          "END_ND_CD": "1220056100",
          "END_ND_NM": "갤러리아주유소",
          "END_ND_XY": "127.0437559139934081_37.5270338519371265",
          "DIST": "81.0",
          "SPD": 14.0,
          "IDX": "정체",
          "XYLIST": "127.0438203861748150_37.5270169441582837|127.0441081482848631_37.5277129366679745"
        },
        {
          "LINK_ID": "1220100100",
          "ROAD_NM": "압구정로61길",
          "START_ND_CD": "1220056100",
          "START_ND_NM": "갤러리아주유소",
          "START_ND_XY": "127.0437559139934081_37.5270338519371265",
          "END_ND_CD": "1220057200",
          "END_ND_NM": "청담매스터빌",
          "END_ND_XY": "127.0440436744389245_37.5277298455036714",
          "DIST": "81.0",
          "SPD": 10.0,
          "IDX": "정체",
          "XYLIST": "127.0439792016946399_37.5277467534027238|127.0436914406515569_37.5270507596811740"
        },
        {
          "LINK_ID": "1220102200",
          "ROAD_NM": "압구정로61길",
          "START_ND_CD": "1220059200",
          "START_ND_NM": "청담동146",
          "START_ND_XY": "127.0447452162564161_37.5295973708736241",
          "END_ND_CD": "1220057200",
          "END_ND_NM": "청담매스터빌",
          "END_ND_XY": "127.0440436744389245_37.5277298455036714",
          "DIST": "216.0",
          "SPD": 19.0,
          "IDX": "서행",
          "XYLIST": "127.0441099297474494_37.5277180933370289|127.0441454282712925_37.5278450321291004|127.0447136572623634_37.5293809991963343|127.0448085904139077_37.5295780014419762"
        },
        {
          "LINK_ID": "1220102300",
          "ROAD_NM": "압구정로61길",
          "START_ND_CD": "1220057200",
          "START_ND_NM": "청담매스터빌",
          "START_ND_XY": "127.0440436744389245_37.5277298455036714",
          "END_ND_CD": "1220059200",
          "END_ND_NM": "청담동146",
          "END_ND_XY": "127.0447452162564161_37.5295973708736241",
          "DIST": "217.0",
          "SPD": 24.0,
          "IDX": "서행",
          "XYLIST": "127.0446818431979921_37.5296167411718073|127.0445849654173713_37.5294157030726865|127.0440139116746536_37.5278720932492433|127.0439774191095665_37.5277415976331312"
        }
      ]
    },
    "PRK_STTS": [
      {
        "PRK_NM": "아마노코리아 청담 주차장",
        "PRK_CD": "787355",
        "PRK_TYPE": "BS",
        "CPCTY": "11",
        "CUR_PRK_CNT": "",
        "CUR_PRK_TIME": "",
        "CUR_PRK_YN": "N",
        "PAY_YN": "Y",
        "RATES": "1500",
        "TIME_RATES": "10",
        "ADD_RATES": "1500",
        "ADD_TIME_RATES": "10",
        "ADDRESS": "강남구 청담동 99-11",
        "ROAD_ADDR": "",
        "LNG": "127.04608003",
        "LAT": "37.52533366"
      },
      {
        "PRK_NM": "버거킹 주차장(민영)",
        "PRK_CD": "2878621",
        "PRK_TYPE": "NP",
        "CPCTY": "15",
        "CUR_PRK_CNT": "",
        "CUR_PRK_TIME": "",
        "CUR_PRK_YN": "N",
        "PAY_YN": "Y",
        "RATES": "5000",
        "TIME_RATES": "30",
        "ADD_RATES": "1500",
        "ADD_TIME_RATES": "10",
        "ADDRESS": "강남구 청담동 85-5",
        "ROAD_ADDR": "",
        "LNG": "127.039814",
        "LAT": "37.524199"
      },
      {
        "PRK_NM": "킹콩빌딩 주차장",
        "PRK_CD": "2875448",
        "PRK_TYPE": "BS",
        "CPCTY": "63",
        "CUR_PRK_CNT": "",
        "CUR_PRK_TIME": "",
        "CUR_PRK_YN": "N",
        "PAY_YN": "Y",
        "RATES": "5000",
        "TIME_RATES": "120",
        "ADD_RATES": "1000",
        "ADD_TIME_RATES": "15",
        "ADDRESS": "강남구 청담동 86-0",
        "ROAD_ADDR": "",
        "LNG": "127.039643",
        "LAT": "37.523858"
      },
      {
        "PRK_NM": "아노블리81타워 주차장",
        "PRK_CD": "3187567",
        "PRK_TYPE": "BS",
        "CPCTY": "85",
        "CUR_PRK_CNT": "",
        "CUR_PRK_TIME": "",
        "CUR_PRK_YN": "N",
        "PAY_YN": "Y",
        "RATES": "6000",
        "TIME_RATES": "60",
        "ADD_RATES": "1000",
        "ADD_TIME_RATES": "10",
        "ADDRESS": "강남구 청담동 91-2",
        "ROAD_ADDR": "",
        "LNG": "127.04165",
        "LAT": "37.523853"
      },
      {
        "PRK_NM": "퍼스트라이트타워 주차장",
        "PRK_CD": "2928448",
        "PRK_TYPE": "BS",
        "CPCTY": "38",
        "CUR_PRK_CNT": "",
        "CUR_PRK_TIME": "",
        "CUR_PRK_YN": "N",
        "PAY_YN": "Y",
        "RATES": "4000",
        "TIME_RATES": "10",
        "ADD_RATES": "1000",
        "ADD_TIME_RATES": "10",
        "ADDRESS": "강남구 청담동 87-11",
        "ROAD_ADDR": "",
        "LNG": "127.041104",
        "LAT": "37.523802"
      },
      {
        "PRK_NM": "부귀영전빌딩 주차장",
        "PRK_CD": "2909782",
        "PRK_TYPE": "BS",
        "CPCTY": "30",
        "CUR_PRK_CNT": "",
        "CUR_PRK_TIME": "",
        "CUR_PRK_YN": "N",
        "PAY_YN": "Y",
        "RATES": "3000",
        "TIME_RATES": "30",
        "ADD_RATES": "1000",
        "ADD_TIME_RATES": "10",
        "ADDRESS": "강남구 청담동 91-5",
        "ROAD_ADDR": "",
        "LNG": "127.042388",
        "LAT": "37.52425"
      },
      {
        "PRK_NM": "더에디션주차장",
        "PRK_CD": "3189209",
        "PRK_TYPE": "BS",
        "CPCTY": "9",
        "CUR_PRK_CNT": "",
        "CUR_PRK_TIME": "",
        "CUR_PRK_YN": "N",
        "PAY_YN": "Y",
        "RATES": "3000",
        "TIME_RATES": "30",
        "ADD_RATES": "1000",
        "ADD_TIME_RATES": "10",
        "ADDRESS": "강남구 청담동 97-7",
        "ROAD_ADDR": "",
        "LNG": "127.046064",
        "LAT": "37.524408"
      },
      {
        "PRK_NM": "먼데이투선데이 주차장",
        "PRK_CD": "2913912",
        "PRK_TYPE": "BS",
        "CPCTY": "14",
        "CUR_PRK_CNT": "",
        "CUR_PRK_TIME": "",
        "CUR_PRK_YN": "N",
        "PAY_YN": "Y",
        "RATES": "3000",
        "TIME_RATES": "120",
        "ADD_RATES": "2000",
        "ADD_TIME_RATES": "30",
        "ADDRESS": "강남구 청담동 93-13",
        "ROAD_ADDR": "",
        "LNG": "127.044159",
        "LAT": "37.524807"
      },
      {
        "PRK_NM": "미라클빌딩 주차장",
        "PRK_CD": "2914995",
        "PRK_TYPE": "BS",
        "CPCTY": "52",
        "CUR_PRK_CNT": "",
        "CUR_PRK_TIME": "",
        "CUR_PRK_YN": "N",
        "PAY_YN": "Y",
        "RATES": "3000",
        "TIME_RATES": "30",
        "ADD_RATES": "1000",
        "ADD_TIME_RATES": "10",
        "ADDRESS": "강남구 청담동 91-3",
        "ROAD_ADDR": "",
        "LNG": "127.041948",
        "LAT": "37.524193"
      },
      {
        "PRK_NM": "청담동일모터스 주차장",
        "PRK_CD": "2924152",
        "PRK_TYPE": "BS",
        "CPCTY": "15",
        "CUR_PRK_CNT": "",
        "CUR_PRK_TIME": "",
        "CUR_PRK_YN": "N",
        "PAY_YN": "Y",
        "RATES": "1000",
        "TIME_RATES": "10",
        "ADD_RATES": "1000",
        "ADD_TIME_RATES": "10",
        "ADDRESS": "강남구 청담동 87-7",
        "ROAD_ADDR": "",
        "LNG": "127.040811",
        "LAT": "37.524043"
      },
      {
        "PRK_NM": "보메청담 주차장",
        "PRK_CD": "2907681",
        "PRK_TYPE": "BS",
        "CPCTY": "33",
        "CUR_PRK_CNT": "",
        "CUR_PRK_TIME": "",
        "CUR_PRK_YN": "N",
        "PAY_YN": "Y",
        "RATES": "3000",
        "TIME_RATES": "120",
        "ADD_RATES": "2000",
        "ADD_TIME_RATES": "10",
        "ADDRESS": "강남구 청담동 91-6",
        "ROAD_ADDR": "",
        "LNG": "127.042624",
        "LAT": "37.524252"
      },
      {
        "PRK_NM": "울프강스테이크하우스 주차장",
        "PRK_CD": "2911373",
        "PRK_TYPE": "BS",
        "CPCTY": "53",
        "CUR_PRK_CNT": "",
        "CUR_PRK_TIME": "",
        "CUR_PRK_YN": "N",
        "PAY_YN": "Y",
        "RATES": "3000",
        "TIME_RATES": "30",
        "ADD_RATES": "1000",
        "ADD_TIME_RATES": "10",
        "ADDRESS": "강남구 청담동 89-6",
        "ROAD_ADDR": "",
        "LNG": "127.041501",
        "LAT": "37.524496"
      },
      {
        "PRK_NM": "갤러리아백화점 명품관 EAST",
        "PRK_CD": "768488",
        "PRK_TYPE": "BS",
        "CPCTY": "197",
        "CUR_PRK_CNT": "",
        "CUR_PRK_TIME": "",
        "CUR_PRK_YN": "N",
        "PAY_YN": "Y",
        "RATES": "0",
        "TIME_RATES": "30",
        "ADD_RATES": "1000",
        "ADD_TIME_RATES": "10",
        "ADDRESS": "강남구 압구정동 515-0",
        "ROAD_ADDR": "",
        "LNG": "127.04159925",
        "LAT": "37.52808559"
      },
      {
        "PRK_NM": "갤러리아백화점 명품관 WEST",
        "PRK_CD": "1041175",
        "PRK_TYPE": "BS",
        "CPCTY": "177",
        "CUR_PRK_CNT": "",
        "CUR_PRK_TIME": "",
        "CUR_PRK_YN": "N",
        "PAY_YN": "Y",
        "RATES": "0",
        "TIME_RATES": "30",
        "ADD_RATES": "1000",
        "ADD_TIME_RATES": "10",
        "ADDRESS": "강남구 압구정동 494-0",
        "ROAD_ADDR": "",
        "LNG": "127.0400765",
        "LAT": "37.52857263"
      },
      {
        "PRK_NM": "W빌딩 민영주차장",
        "PRK_CD": "3163166",
        "PRK_TYPE": "BS",
        "CPCTY": "5",
        "CUR_PRK_CNT": "",
        "CUR_PRK_TIME": "",
        "CUR_PRK_YN": "N",
        "PAY_YN": "Y",
        "RATES": "6000",
        "TIME_RATES": "60",
        "ADD_RATES": "1000",
        "ADD_TIME_RATES": "10",
        "ADDRESS": "강남구 청담동 118-8",
        "ROAD_ADDR": "",
        "LNG": "127.046937",
        "LAT": "37.525673"
      },
      {
        "PRK_NM": "네이처포엠오피스텔 주차장",
        "PRK_CD": "3159939",
        "PRK_TYPE": "BS",
        "CPCTY": "113",
        "CUR_PRK_CNT": "",
        "CUR_PRK_TIME": "",
        "CUR_PRK_YN": "N",
        "PAY_YN": "Y",
        "RATES": "3000",
        "TIME_RATES": "30",
        "ADD_RATES": "1500",
        "ADD_TIME_RATES": "10",
        "ADDRESS": "강남구 청담동 118-17",
        "ROAD_ADDR": "",
        "LNG": "127.047261",
        "LAT": "37.525345"
      }
    ],
    "SUB_STTS": [
      {
        "SUB_STN_NM": "압구정로데오",
        "SUB_STN_LINE": "수인분당선",
        "SUB_STN_RADDR": "서울 강남구 압구정로 지하 402",
        "SUB_STN_JIBUN": "서울 강남구 압구정동 495",
        "SUB_STN_X": "127.0406027693898",
        "SUB_STN_Y": "37.5275184818021",
        "SUB_DETAIL": [
          {
            "SUB_NT_STN": "1075075211",
            "SUB_BF_STN": "1075075213",
            "SUB_ROUTE_NM": "왕십리행 - 서울숲방면",
            "SUB_LINE": "수인분당",
            "SUB_ORD": "01002왕십리0",
            "SUB_DIR": "상행",
            "SUB_TERMINAL": "왕십리",
            "SUB_ARVTIME": "0",
            "SUB_ARMG1": "[2]번째 전역 (선정릉)",
            "SUB_ARMG2": "선정릉",
            "SUB_ARVINFO": "운행중"
          },
          {
            "SUB_NT_STN": "1075075211",
            "SUB_BF_STN": "1075075213",
            "SUB_ROUTE_NM": "왕십리행 - 서울숲방면",
            "SUB_LINE": "수인분당",
            "SUB_ORD": "02008왕십리0",
            "SUB_DIR": "상행",
            "SUB_TERMINAL": "왕십리",
            "SUB_ARVTIME": "0",
            "SUB_ARMG1": "[8]번째 전역 (대모산입구)",
            "SUB_ARMG2": "대모산입구",
            "SUB_ARVINFO": "운행중"
          },
          {
            "SUB_NT_STN": "1075075213",
            "SUB_BF_STN": "1075075211",
            "SUB_ROUTE_NM": "죽전행 - 강남구청방면",
            "SUB_LINE": "수인분당",
            "SUB_ORD": "11000죽전0",
            "SUB_DIR": "하행",
            "SUB_TERMINAL": "죽전",
            "SUB_ARVTIME": "0",
            "SUB_ARMG1": "압구정로데오 진입",
            "SUB_ARMG2": "압구정로데오",
            "SUB_ARVINFO": "진입"
          },
          {
            "SUB_NT_STN": "1075075213",
            "SUB_BF_STN": "1075075211",
            "SUB_ROUTE_NM": "인천행 - 강남구청방면",
            "SUB_LINE": "수인분당",
            "SUB_ORD": "12002인천0",
            "SUB_DIR": "하행",
            "SUB_TERMINAL": "인천",
            "SUB_ARVTIME": "0",
            "SUB_ARMG1": "[2]번째 전역 (왕십리)",
            "SUB_ARMG2": "왕십리",
            "SUB_ARVINFO": "운행중"
          }
        ],
        "SUB_FACIINFO": []
      }
    ],
    "BUS_STN_STTS": [
      {
        "BUS_RESULT_MSG": "정상 호출되었습니다.",
        "BUS_STN_ID": "122000056",
        "BUS_ARS_ID": "23158",
        "BUS_STN_NM": "한양아파트.압구정로데오역",
        "BUS_STN_X": "127.0395789565",
        "BUS_STN_Y": "37.5282700029",
        "BUS_DETAIL": [
          {
            "RTE_STN_NM": "한양아파트.압구정로데오역",
            "RTE_NM": "6006",
            "RTE_ID": "100100506",
            "RTE_SECT": "프라마호텔~한양아파트.압구정로데오역",
            "RTE_CONGEST_1": "정보없음",
            "RTE_ARRV_TM_1": "출발대기",
            "RTE_ARRV_STN_1": null,
            "RTE_CONGEST_2": "정보없음",
            "RTE_ARRV_TM_2": "출발대기",
            "RTE_ARRV_STN_2": null
          },
          {
            "RTE_STN_NM": "한양아파트.압구정로데오역",
            "RTE_NM": "143",
            "RTE_ID": "100100022",
            "RTE_SECT": "청담초등학교~한양아파트.압구정로데오역",
            "RTE_CONGEST_1": "보통",
            "RTE_ARRV_TM_1": "3분14초후[1번째 전]",
            "RTE_ARRV_STN_1": "청담초등학교",
            "RTE_CONGEST_2": "여유",
            "RTE_ARRV_TM_2": "5분23초후[2번째 전]",
            "RTE_ARRV_STN_2": "청담동주민센터"
          },
          {
            "RTE_STN_NM": "한양아파트.압구정로데오역",
            "RTE_NM": "145",
            "RTE_ID": "100100024",
            "RTE_SECT": "일지아트홀.압구정동노인복지센터~한양아파트.압구정로데오역",
            "RTE_CONGEST_1": "여유",
            "RTE_ARRV_TM_1": "8분44초후[3번째 전]",
            "RTE_ARRV_STN_1": "언북중학교입구",
            "RTE_CONGEST_2": "여유",
            "RTE_ARRV_TM_2": "11분3초후[3번째 전]",
            "RTE_ARRV_STN_2": "언북중학교입구"
          },
          {
            "RTE_STN_NM": "한양아파트.압구정로데오역",
            "RTE_NM": "240",
            "RTE_ID": "100100407",
            "RTE_SECT": "청담초등학교~한양아파트.압구정로데오역",
            "RTE_CONGEST_1": "여유",
            "RTE_ARRV_TM_1": "5분1초후[2번째 전]",
            "RTE_ARRV_STN_1": "청담동주민센터",
            "RTE_CONGEST_2": "여유",
            "RTE_ARRV_TM_2": "23분42초후[13번째 전]",
            "RTE_ARRV_STN_2": "군자새마을금고앞"
          },
          {
            "RTE_STN_NM": "한양아파트.압구정로데오역",
            "RTE_NM": "301",
            "RTE_ID": "100100051",
            "RTE_SECT": "일지아트홀.압구정동노인복지센터~한양아파트.압구정로데오역",
            "RTE_CONGEST_1": "여유",
            "RTE_ARRV_TM_1": "곧 도착",
            "RTE_ARRV_STN_1": "한양아파트.압구정로데오역",
            "RTE_CONGEST_2": "여유",
            "RTE_ARRV_TM_2": "12분4초후[7번째 전]",
            "RTE_ARRV_STN_2": "청담역.경기고교"
          },
          {
            "RTE_STN_NM": "한양아파트.압구정로데오역",
            "RTE_NM": "345",
            "RTE_ID": "124000036",
            "RTE_SECT": "청담초등학교~한양아파트.압구정로데오역",
            "RTE_CONGEST_1": "여유",
            "RTE_ARRV_TM_1": "7분45초후[2번째 전]",
            "RTE_ARRV_STN_1": "청담동주민센터",
            "RTE_CONGEST_2": "여유",
            "RTE_ARRV_TM_2": "19분42초후[8번째 전]",
            "RTE_ARRV_STN_2": "잠실종합운동장"
          },
          {
            "RTE_STN_NM": "한양아파트.압구정로데오역",
            "RTE_NM": "440",
            "RTE_ID": "100100459",
            "RTE_SECT": "일지아트홀.압구정동노인복지센터~한양아파트.압구정로데오역",
            "RTE_CONGEST_1": "여유",
            "RTE_ARRV_TM_1": "8분55초후[3번째 전]",
            "RTE_ARRV_STN_1": "언북중학교입구",
            "RTE_CONGEST_2": "여유",
            "RTE_ARRV_TM_2": "13분13초후[4번째 전]",
            "RTE_ARRV_STN_2": "신사동고개"
          },
          {
            "RTE_STN_NM": "한양아파트.압구정로데오역",
            "RTE_NM": "472",
            "RTE_ID": "100100075",
            "RTE_SECT": "일지아트홀.압구정동노인복지센터~한양아파트.압구정로데오역",
            "RTE_CONGEST_1": "여유",
            "RTE_ARRV_TM_1": "곧 도착",
            "RTE_ARRV_STN_1": "한양아파트.압구정로데오역",
            "RTE_CONGEST_2": "여유",
            "RTE_ARRV_TM_2": "6분17초후[3번째 전]",
            "RTE_ARRV_STN_2": "강남구청역"
          },
          {
            "RTE_STN_NM": "한양아파트.압구정로데오역",
            "RTE_NM": "4312",
            "RTE_ID": "100100500",
            "RTE_SECT": "일지아트홀.압구정동노인복지센터~한양아파트.압구정로데오역",
            "RTE_CONGEST_1": "여유",
            "RTE_ARRV_TM_1": "3분2초후[1번째 전]",
            "RTE_ARRV_STN_1": "일지아트홀.압구정노인복지관",
            "RTE_CONGEST_2": "여유",
            "RTE_ARRV_TM_2": "12분8초후[7번째 전]",
            "RTE_ARRV_STN_2": "선릉역8번출구.선정릉"
          },
          {
            "RTE_STN_NM": "한양아파트.압구정로데오역",
            "RTE_NM": "4318",
            "RTE_ID": "100100237",
            "RTE_SECT": "청담초등학교~한양아파트.압구정로데오역",
            "RTE_CONGEST_1": "여유",
            "RTE_ARRV_TM_1": "곧 도착",
            "RTE_ARRV_STN_1": "한양아파트.압구정로데오역",
            "RTE_CONGEST_2": "여유",
            "RTE_ARRV_TM_2": "13분1초후[6번째 전]",
            "RTE_ARRV_STN_2": "삼성역7번출구"
          }
        ]
      },
      {
        "BUS_RESULT_MSG": "정상 호출되었습니다.",
        "BUS_STN_ID": "122000063",
        "BUS_ARS_ID": "23165",
        "BUS_STN_NM": "청담초등학교",
        "BUS_STN_X": "127.045122136",
        "BUS_STN_Y": "37.5268028293",
        "BUS_DETAIL": [
          {
            "RTE_STN_NM": "청담초등학교",
            "RTE_NM": "143",
            "RTE_ID": "100100022",
            "RTE_SECT": "프리마호텔~청담초등학교",
            "RTE_CONGEST_1": "보통",
            "RTE_ARRV_TM_1": "곧 도착",
            "RTE_ARRV_STN_1": "청담초등학교",
            "RTE_CONGEST_2": "여유",
            "RTE_ARRV_TM_2": "3분2초후[1번째 전]",
            "RTE_ARRV_STN_2": "청담동주민센터"
          },
          {
            "RTE_STN_NM": "청담초등학교",
            "RTE_NM": "240",
            "RTE_ID": "100100407",
            "RTE_SECT": "프리마호텔~청담초등학교",
            "RTE_CONGEST_1": "여유",
            "RTE_ARRV_TM_1": "2분40초후[1번째 전]",
            "RTE_ARRV_STN_1": "청담동주민센터",
            "RTE_CONGEST_2": "여유",
            "RTE_ARRV_TM_2": "21분52초후[12번째 전]",
            "RTE_ARRV_STN_2": "군자새마을금고앞"
          },
          {
            "RTE_STN_NM": "청담초등학교",
            "RTE_NM": "345",
            "RTE_ID": "124000036",
            "RTE_SECT": "프리마호텔~청담초등학교",
            "RTE_CONGEST_1": "여유",
            "RTE_ARRV_TM_1": "5분24초후[1번째 전]",
            "RTE_ARRV_STN_1": "청담동주민센터",
            "RTE_CONGEST_2": "여유",
            "RTE_ARRV_TM_2": "17분52초후[7번째 전]",
            "RTE_ARRV_STN_2": "잠실종합운동장"
          },
          {
            "RTE_STN_NM": "청담초등학교",
            "RTE_NM": "4318",
            "RTE_ID": "100100237",
            "RTE_SECT": "프리마호텔~청담초등학교",
            "RTE_CONGEST_1": "여유",
            "RTE_ARRV_TM_1": "10분40초후[5번째 전]",
            "RTE_ARRV_STN_1": "삼성역7번출구",
            "RTE_CONGEST_2": "여유",
            "RTE_ARRV_TM_2": "14분14초후[6번째 전]",
            "RTE_ARRV_STN_2": "삼성역"
          },
          {
            "RTE_STN_NM": "청담초등학교",
            "RTE_NM": "1006남양주",
            "RTE_ID": "222000192",
            "RTE_SECT": "정약용도서관~플루리움3단지",
            "RTE_CONGEST_1": "",
            "RTE_ARRV_TM_1": "20분27초후[12번째 전]",
            "RTE_ARRV_STN_1": "아천IC(미정차)",
            "RTE_CONGEST_2": "",
            "RTE_ARRV_TM_2": "43분1초후[21번째 전]",
            "RTE_ARRV_STN_2": "광나루역.극동아파트"
          }
        ]
      },
      {
        "BUS_RESULT_MSG": "정상 호출되었습니다.",
        "BUS_STN_ID": "122000077",
        "BUS_ARS_ID": "23180",
        "BUS_STN_NM": "농협앞",
        "BUS_STN_X": "127.0443867144",
        "BUS_STN_Y": "37.5240778005",
        "BUS_DETAIL": [
          {
            "RTE_STN_NM": "농협앞",
            "RTE_NM": "343",
            "RTE_ID": "107000002",
            "RTE_SECT": "청담천주교회~농협앞",
            "RTE_CONGEST_1": "여유",
            "RTE_ARRV_TM_1": "11분8초후[5번째 전]",
            "RTE_ARRV_STN_1": "삼성역7번출구",
            "RTE_CONGEST_2": "여유",
            "RTE_ARRV_TM_2": "22분29초후[11번째 전]",
            "RTE_ARRV_STN_2": "일원초등학교"
          },
          {
            "RTE_STN_NM": "농협앞",
            "RTE_NM": "4212",
            "RTE_ID": "100100234",
            "RTE_SECT": "프리마호텔~농협앞",
            "RTE_CONGEST_1": "여유",
            "RTE_ARRV_TM_1": "5분38초후[2번째 전]",
            "RTE_ARRV_STN_1": "영동대교북단",
            "RTE_CONGEST_2": "여유",
            "RTE_ARRV_TM_2": "11분58초후[4번째 전]",
            "RTE_ARRV_STN_2": "서울효사랑병원"
          }
        ]
      },
      {
        "BUS_RESULT_MSG": "정상 호출되었습니다.",
        "BUS_STN_ID": "122000079",
        "BUS_ARS_ID": "23182",
        "BUS_STN_NM": "청담초등학교앞",
        "BUS_STN_X": "127.045085725",
        "BUS_STN_Y": "37.5264613268",
        "BUS_DETAIL": [
          {
            "RTE_STN_NM": "청담초등학교앞",
            "RTE_NM": "143",
            "RTE_ID": "100100022",
            "RTE_SECT": "한양아파트.압구정로데오역~청담초등학교앞",
            "RTE_CONGEST_1": "여유",
            "RTE_ARRV_TM_1": "4분38초후[2번째 전]",
            "RTE_ARRV_STN_1": "압구정파출소",
            "RTE_CONGEST_2": "여유",
            "RTE_ARRV_TM_2": "12분7초후[5번째 전]",
            "RTE_ARRV_STN_2": "신사중학교"
          },
          {
            "RTE_STN_NM": "청담초등학교앞",
            "RTE_NM": "240",
            "RTE_ID": "100100407",
            "RTE_SECT": "한양아파트.압구정로데오역~청담초등학교앞",
            "RTE_CONGEST_1": "여유",
            "RTE_ARRV_TM_1": "2분32초후[1번째 전]",
            "RTE_ARRV_STN_1": "한양아파트.압구정로데오역",
            "RTE_CONGEST_2": "여유",
            "RTE_ARRV_TM_2": "17분45초후[7번째 전]",
            "RTE_ARRV_STN_2": "신사역3번출구"
          },
          {
            "RTE_STN_NM": "청담초등학교앞",
            "RTE_NM": "343",
            "RTE_ID": "107000002",
            "RTE_SECT": "한양아파트.압구정로데오역~청담초등학교앞",
            "RTE_CONGEST_1": "여유",
            "RTE_ARRV_TM_1": "2분31초후[1번째 전]",
            "RTE_ARRV_STN_1": "한양아파트.압구정로데오역",
            "RTE_CONGEST_2": "여유",
            "RTE_ARRV_TM_2": "11분30초후[5번째 전]",
            "RTE_ARRV_STN_2": "국민은행압구정종합금융센터"
          },
          {
            "RTE_STN_NM": "청담초등학교앞",
            "RTE_NM": "345",
            "RTE_ID": "124000036",
            "RTE_SECT": "한양아파트.압구정로데오역~청담초등학교앞",
            "RTE_CONGEST_1": "여유",
            "RTE_ARRV_TM_1": "7분30초후[3번째 전]",
            "RTE_ARRV_STN_1": "현대아파트",
            "RTE_CONGEST_2": "여유",
            "RTE_ARRV_TM_2": "16분25초후[7번째 전]",
            "RTE_ARRV_STN_2": "잠원한신아파트"
          },
          {
            "RTE_STN_NM": "청담초등학교앞",
            "RTE_NM": "4318",
            "RTE_ID": "100100237",
            "RTE_SECT": "한양아파트.압구정로데오역~청담초등학교앞",
            "RTE_CONGEST_1": "여유",
            "RTE_ARRV_TM_1": "5분후[2번째 전]",
            "RTE_ARRV_STN_1": "압구정파출소",
            "RTE_CONGEST_2": "여유",
            "RTE_ARRV_TM_2": "16분2초후[6번째 전]",
            "RTE_ARRV_STN_2": "래미안신반포리오센트아파트"
          },
          {
            "RTE_STN_NM": "청담초등학교앞",
            "RTE_NM": "9407성남",
            "RTE_ID": "204000024",
            "RTE_SECT": "일지아트홀.압구정동노인복지센터~청담초등학교앞",
            "RTE_CONGEST_1": "",
            "RTE_ARRV_TM_1": "3분40초후[1번째 전]",
            "RTE_ARRV_STN_1": "일지아트홀.압구정노인복지관",
            "RTE_CONGEST_2": "",
            "RTE_ARRV_TM_2": "24분18초후[11번째 전]",
            "RTE_ARRV_STN_2": "쌍용아파트"
          },
          {
            "RTE_STN_NM": "청담초등학교앞",
            "RTE_NM": "9507성남",
            "RTE_ID": "204000059",
            "RTE_SECT": "일지아트홀.압구정동노인복지센터~청담초등학교앞",
            "RTE_CONGEST_1": "",
            "RTE_ARRV_TM_1": "38분56초후[18번째 전]",
            "RTE_ARRV_STN_1": "모란(미정차)",
            "RTE_CONGEST_2": "",
            "RTE_ARRV_TM_2": "73분4초후[38번째 전]",
            "RTE_ARRV_STN_2": "힐스테이트판교엘포레6단지.판교"
          },
          {
            "RTE_STN_NM": "청담초등학교앞",
            "RTE_NM": "9607성남",
            "RTE_ID": "204000065",
            "RTE_SECT": "일지아트홀.압구정동노인복지센터~청담초등학교앞",
            "RTE_CONGEST_1": "",
            "RTE_ARRV_TM_1": "27분40초후[13번째 전]",
            "RTE_ARRV_STN_1": "일원초등학교",
            "RTE_CONGEST_2": "",
            "RTE_ARRV_TM_2": "70분7초후[40번째 전]",
            "RTE_ARRV_STN_2": "이마트"
          }
        ]
      },
      {
        "BUS_RESULT_MSG": "정상 호출되었습니다.",
        "BUS_STN_ID": "122000082",
        "BUS_ARS_ID": "23185",
        "BUS_STN_NM": "차병원차움",
        "BUS_STN_X": "127.04417",
        "BUS_STN_Y": "37.523668",
        "BUS_DETAIL": [
          {
            "RTE_STN_NM": "차병원차움",
            "RTE_NM": "4212",
            "RTE_ID": "100100234",
            "RTE_SECT": "영동119.안전센터~차병원차움",
            "RTE_CONGEST_1": "여유",
            "RTE_ARRV_TM_1": "5분18초후[3번째 전]",
            "RTE_ARRV_STN_1": "언북중학교입구",
            "RTE_CONGEST_2": "여유",
            "RTE_ARRV_TM_2": "12분12초후[6번째 전]",
            "RTE_ARRV_STN_2": "신사역3번출구"
          }
        ]
      },
      {
        "BUS_RESULT_MSG": "정상 호출되었습니다.",
        "BUS_STN_ID": "122000559",
        "BUS_ARS_ID": "23766",
        "BUS_STN_NM": "ST송은빌딩",
        "BUS_STN_X": "127.0440702137",
        "BUS_STN_Y": "37.5240522735",
        "BUS_DETAIL": [
          {
            "RTE_STN_NM": "ST송은빌딩",
            "RTE_NM": "9407성남",
            "RTE_ID": "204000024",
            "RTE_SECT": "프리마호텔~엠네트음악방송국",
            "RTE_CONGEST_1": "",
            "RTE_ARRV_TM_1": "19분11초후[9번째 전]",
            "RTE_ARRV_STN_1": "쌍용아파트",
            "RTE_CONGEST_2": "",
            "RTE_ARRV_TM_2": "32분33초후[16번째 전]",
            "RTE_ARRV_STN_2": "모란(미정차)"
          },
          {
            "RTE_STN_NM": "ST송은빌딩",
            "RTE_NM": "9507성남",
            "RTE_ID": "204000059",
            "RTE_SECT": "프리마호텔~엠네트음악방송국",
            "RTE_CONGEST_1": "",
            "RTE_ARRV_TM_1": "33분49초후[16번째 전]",
            "RTE_ARRV_STN_1": "모란(미정차)",
            "RTE_CONGEST_2": "",
            "RTE_ARRV_TM_2": "67분57초후[36번째 전]",
            "RTE_ARRV_STN_2": "힐스테이트판교엘포레6단지.판교"
          },
          {
            "RTE_STN_NM": "ST송은빌딩",
            "RTE_NM": "9607성남",
            "RTE_ID": "204000065",
            "RTE_SECT": "프리마호텔~엠네트음악방송국",
            "RTE_CONGEST_1": "",
            "RTE_ARRV_TM_1": "22분22초후[11번째 전]",
            "RTE_ARRV_STN_1": "일원초등학교",
            "RTE_CONGEST_2": "",
            "RTE_ARRV_TM_2": "64분49초후[38번째 전]",
            "RTE_ARRV_STN_2": "이마트"
          }
        ]
      },
      {
        "BUS_RESULT_MSG": "현재 오류가 발생중입니다. 나중에 다시 시도해주세요.",
        "BUS_STN_ID": "122000729",
        "BUS_ARS_ID": "23908",
        "BUS_STN_NM": "한류스타거리",
        "BUS_STN_X": "127.0433500025",
        "BUS_STN_Y": "37.5272518736",
        "BUS_DETAIL": []
      }
    ],
    "ACDNT_CNTRL_STTS": [],
    "SBIKE_STTS": [
      {
        "SBIKE_SPOT_NM": "2429.압구정로데오역 6번출구",
        "SBIKE_SPOT_ID": "ST-1895",
        "SBIKE_SHARED": "30",
        "SBIKE_PARKING_CNT": "3",
        "SBIKE_RACK_CNT": "10",
        "SBIKE_X": 127.04042816,
        "SBIKE_Y": 37.52745438
      },
      {
        "SBIKE_SPOT_NM": "2310. 청담동 맥도날드 옆(위치)",
        "SBIKE_SPOT_ID": "ST-794",
        "SBIKE_SHARED": "270",
        "SBIKE_PARKING_CNT": "27",
        "SBIKE_RACK_CNT": "10",
        "SBIKE_X": 127.04017639,
        "SBIKE_Y": 37.52361298
      }
    ],
    "WEATHER_STTS": [
      {
        "WEATHER_TIME": "2025-04-21 12:50",
        "TEMP": "23.1",
        "SENSIBLE_TEMP": "23.1",
        "MAX_TEMP": "26.0",
        "MIN_TEMP": "16.0",
        "HUMIDITY": "51",
        "WIND_DIRCT": "SE",
        "WIND_SPD": "1.7",
        "PRECIPITATION": "-",
        "PRECPT_TYPE": "없음",
        "PCP_MSG": "비 또는 눈 소식이 없어요.",
        "SUNRISE": "05:49",
        "SUNSET": "19:13",
        "UV_INDEX_LVL": "6",
        "UV_INDEX": "높음",
        "UV_MSG": "햇볕에 노출 시 1-2시간 이내에도 피부 화상을 입을 수 있어 위험해요.한낮에는 실내나 그늘에 머물러주세요.외출시 긴 소매 옷, 모자, 선글라스를 착용해주세요.자외선 차단제를 정기적으로 발라주세요.",
        "PM25_INDEX": "좋음",
        "PM25": "14",
        "PM10_INDEX": "보통",
        "PM10": "33",
        "AIR_IDX": "보통",
        "AIR_IDX_MVL": "61.0",
        "AIR_IDX_MAIN": "O3",
        "AIR_MSG": "호흡기가 예민하신 분들은 몸상태 유의하며 활동해주세요.",
        "FCST24HOURS": [
          {
            "FCST_DT": "202504211300",
            "TEMP": "24",
            "PRECIPITATION": "-",
            "PRECPT_TYPE": "없음",
            "RAIN_CHANCE": "0",
            "SKY_STTS": "흐림"
          },
          {
            "FCST_DT": "202504211400",
            "TEMP": "25",
            "PRECIPITATION": "-",
            "PRECPT_TYPE": "없음",
            "RAIN_CHANCE": "0",
            "SKY_STTS": "흐림"
          },
          {
            "FCST_DT": "202504211500",
            "TEMP": "25",
            "PRECIPITATION": "-",
            "PRECPT_TYPE": "없음",
            "RAIN_CHANCE": "0",
            "SKY_STTS": "흐림"
          },
          {
            "FCST_DT": "202504211600",
            "TEMP": "25",
            "PRECIPITATION": "-",
            "PRECPT_TYPE": "없음",
            "RAIN_CHANCE": "0",
            "SKY_STTS": "흐림"
          },
          {
            "FCST_DT": "202504211700",
            "TEMP": "24",
            "PRECIPITATION": "-",
            "PRECPT_TYPE": "없음",
            "RAIN_CHANCE": "0",
            "SKY_STTS": "구름많음"
          },
          {
            "FCST_DT": "202504211800",
            "TEMP": "23",
            "PRECIPITATION": "-",
            "PRECPT_TYPE": "없음",
            "RAIN_CHANCE": "0",
            "SKY_STTS": "흐림"
          },
          {
            "FCST_DT": "202504211900",
            "TEMP": "21",
            "PRECIPITATION": "-",
            "PRECPT_TYPE": "없음",
            "RAIN_CHANCE": "0",
            "SKY_STTS": "맑음"
          },
          {
            "FCST_DT": "202504212000",
            "TEMP": "21",
            "PRECIPITATION": "-",
            "PRECPT_TYPE": "없음",
            "RAIN_CHANCE": "0",
            "SKY_STTS": "맑음"
          },
          {
            "FCST_DT": "202504212100",
            "TEMP": "20",
            "PRECIPITATION": "-",
            "PRECPT_TYPE": "없음",
            "RAIN_CHANCE": "0",
            "SKY_STTS": "맑음"
          },
          {
            "FCST_DT": "202504212200",
            "TEMP": "20",
            "PRECIPITATION": "-",
            "PRECPT_TYPE": "없음",
            "RAIN_CHANCE": "20",
            "SKY_STTS": "구름많음"
          },
          {
            "FCST_DT": "202504212300",
            "TEMP": "20",
            "PRECIPITATION": "-",
            "PRECPT_TYPE": "없음",
            "RAIN_CHANCE": "20",
            "SKY_STTS": "구름많음"
          },
          {
            "FCST_DT": "202504220000",
            "TEMP": "20",
            "PRECIPITATION": "-",
            "PRECPT_TYPE": "없음",
            "RAIN_CHANCE": "20",
            "SKY_STTS": "구름많음"
          },
          {
            "FCST_DT": "202504220100",
            "TEMP": "20",
            "PRECIPITATION": "-",
            "PRECPT_TYPE": "없음",
            "RAIN_CHANCE": "30",
            "SKY_STTS": "흐림"
          },
          {
            "FCST_DT": "202504220200",
            "TEMP": "19",
            "PRECIPITATION": "-",
            "PRECPT_TYPE": "없음",
            "RAIN_CHANCE": "30",
            "SKY_STTS": "흐림"
          },
          {
            "FCST_DT": "202504220300",
            "TEMP": "19",
            "PRECIPITATION": "-",
            "PRECPT_TYPE": "없음",
            "RAIN_CHANCE": "30",
            "SKY_STTS": "흐림"
          },
          {
            "FCST_DT": "202504220400",
            "TEMP": "18",
            "PRECIPITATION": "-",
            "PRECPT_TYPE": "없음",
            "RAIN_CHANCE": "30",
            "SKY_STTS": "흐림"
          },
          {
            "FCST_DT": "202504220500",
            "TEMP": "18",
            "PRECIPITATION": "1 미만",
            "PRECPT_TYPE": "비",
            "RAIN_CHANCE": "60",
            "SKY_STTS": "흐림"
          },
          {
            "FCST_DT": "202504220600",
            "TEMP": "18",
            "PRECIPITATION": "1 미만",
            "PRECPT_TYPE": "비",
            "RAIN_CHANCE": "60",
            "SKY_STTS": "흐림"
          },
          {
            "FCST_DT": "202504220700",
            "TEMP": "17",
            "PRECIPITATION": "-",
            "PRECPT_TYPE": "없음",
            "RAIN_CHANCE": "30",
            "SKY_STTS": "흐림"
          },
          {
            "FCST_DT": "202504220800",
            "TEMP": "17",
            "PRECIPITATION": "1 미만",
            "PRECPT_TYPE": "비",
            "RAIN_CHANCE": "60",
            "SKY_STTS": "흐림"
          },
          {
            "FCST_DT": "202504220900",
            "TEMP": "17",
            "PRECIPITATION": "4.0",
            "PRECPT_TYPE": "비",
            "RAIN_CHANCE": "61",
            "SKY_STTS": "흐림"
          },
          {
            "FCST_DT": "202504221000",
            "TEMP": "16",
            "PRECIPITATION": "5.0",
            "PRECPT_TYPE": "비",
            "RAIN_CHANCE": "66",
            "SKY_STTS": "흐림"
          },
          {
            "FCST_DT": "202504221100",
            "TEMP": "17",
            "PRECIPITATION": "5.0",
            "PRECPT_TYPE": "비",
            "RAIN_CHANCE": "64",
            "SKY_STTS": "흐림"
          },
          {
            "FCST_DT": "202504221200",
            "TEMP": "17",
            "PRECIPITATION": "6.0",
            "PRECPT_TYPE": "비",
            "RAIN_CHANCE": "68",
            "SKY_STTS": "흐림"
          }
        ],
        "NEWS_LIST": []
      }
    ],
    "CHARGER_STTS": [
      {
        "STAT_NM": "기아 압구정사옥",
        "STAT_ID": "CV004291",
        "STAT_ADDR": "서울특별시 강남구 압구정로 417",
        "STAT_X": "127.04289399",
        "STAT_Y": "37.527551000",
        "STAT_USETIME": "24시간 이용가능",
        "STAT_PARKPAY": "N",
        "STAT_LIMITYN": "Y",
        "STAT_LIMITDETAIL": "직원 외 이용불가",
        "STAT_KINDDETAIL": "사업장(사옥)",
        "CHARGER_DETAILS": [
          {
            "CHARGER_ID": "01",
            "CHARGER_TYPE": "DC콤보",
            "CHARGER_STAT": "사용가능",
            "STATUPDDT": "2025-04-19 15:15",
            "LASTTSDT": "2025-04-18 19:15",
            "LASTTEDT": "2025-04-18 20:15",
            "NOWTSDT": null,
            "OUTPUT": "100",
            "METHOD": "동시"
          },
          {
            "CHARGER_ID": "02",
            "CHARGER_TYPE": "DC콤보",
            "CHARGER_STAT": "사용가능",
            "STATUPDDT": "2025-04-19 15:15",
            "LASTTSDT": "2025-04-15 17:17",
            "LASTTEDT": "2025-04-15 18:00",
            "NOWTSDT": null,
            "OUTPUT": "100",
            "METHOD": "동시"
          }
        ]
      },
      {
        "STAT_NM": "기아 압구정지점",
        "STAT_ID": "ST116816",
        "STAT_ADDR": "서울특별시 강남구 압구정로 417",
        "STAT_X": "127.04288685",
        "STAT_Y": "37.52755859",
        "STAT_USETIME": "24시간 이용가능",
        "STAT_PARKPAY": "N",
        "STAT_LIMITYN": "N",
        "STAT_LIMITDETAIL": "",
        "STAT_KINDDETAIL": "사업장(사옥)",
        "CHARGER_DETAILS": [
          {
            "CHARGER_ID": "01",
            "CHARGER_TYPE": "AC완속",
            "CHARGER_STAT": "사용가능",
            "STATUPDDT": "2025-04-17 11:57",
            "LASTTSDT": "2025-04-16 14:47",
            "LASTTEDT": "2025-04-17 11:57",
            "NOWTSDT": null,
            "OUTPUT": "7",
            "METHOD": "단독"
          },
          {
            "CHARGER_ID": "02",
            "CHARGER_TYPE": "AC완속",
            "CHARGER_STAT": "사용가능",
            "STATUPDDT": "2025-04-16 09:06",
            "LASTTSDT": "2025-04-15 18:57",
            "LASTTEDT": "2025-04-16 09:06",
            "NOWTSDT": null,
            "OUTPUT": "7",
            "METHOD": "단독"
          },
          {
            "CHARGER_ID": "03",
            "CHARGER_TYPE": "AC완속",
            "CHARGER_STAT": "충전중",
            "STATUPDDT": "2025-04-21 12:36",
            "LASTTSDT": "2025-04-21 12:36",
            "LASTTEDT": "2025-04-21 08:42",
            "NOWTSDT": "2025-04-18 14:43",
            "OUTPUT": "7",
            "METHOD": "단독"
          },
          {
            "CHARGER_ID": "04",
            "CHARGER_TYPE": "AC완속",
            "CHARGER_STAT": "사용가능",
            "STATUPDDT": "2025-04-18 11:41",
            "LASTTSDT": "2025-04-17 17:11",
            "LASTTEDT": "2025-04-18 11:41",
            "NOWTSDT": null,
            "OUTPUT": "7",
            "METHOD": "단독"
          }
        ]
      },
      {
        "STAT_NM": "부귀영전",
        "STAT_ID": "LU000872",
        "STAT_ADDR": "서울특별시 강남구 선릉로152길 34",
        "STAT_X": "127.042399",
        "STAT_Y": "37.524252",
        "STAT_USETIME": "평일 09:00~18:00",
        "STAT_PARKPAY": "Y",
        "STAT_LIMITYN": "Y",
        "STAT_LIMITDETAIL": "시설 상황에 따라 이용이 제한될 수 있음.",
        "STAT_KINDDETAIL": "기타",
        "CHARGER_DETAILS": [
          {
            "CHARGER_ID": "01",
            "CHARGER_TYPE": "AC완속",
            "CHARGER_STAT": "사용가능",
            "STATUPDDT": "2025-04-01 12:13",
            "LASTTSDT": "2025-01-30 12:48",
            "LASTTEDT": "2025-01-30 20:02",
            "NOWTSDT": null,
            "OUTPUT": "7",
            "METHOD": "단독"
          }
        ]
      },
      {
        "STAT_NM": "서울 강남 갤러리아백화점 명품관 EAST",
        "STAT_ID": "HW001012",
        "STAT_ADDR": "서울특별시 강남구 압구정로 407",
        "STAT_X": "127.0418579",
        "STAT_Y": "37.5279285",
        "STAT_USETIME": "10:30 ~ 20:00",
        "STAT_PARKPAY": "N",
        "STAT_LIMITYN": "N",
        "STAT_LIMITDETAIL": "백화점 영업시간에만 운영",
        "STAT_KINDDETAIL": "백화점",
        "CHARGER_DETAILS": [
          {
            "CHARGER_ID": "01",
            "CHARGER_TYPE": "DC콤보",
            "CHARGER_STAT": "사용가능",
            "STATUPDDT": "2025-04-19 14:36",
            "LASTTSDT": "2025-04-19 14:10",
            "LASTTEDT": "2025-04-19 14:35",
            "NOWTSDT": null,
            "OUTPUT": "100",
            "METHOD": "단독"
          },
          {
            "CHARGER_ID": "02",
            "CHARGER_TYPE": "AC완속",
            "CHARGER_STAT": "사용가능",
            "STATUPDDT": "2025-04-19 18:24",
            "LASTTSDT": "2025-04-06 15:51",
            "LASTTEDT": "2025-04-06 16:17",
            "NOWTSDT": null,
            "OUTPUT": "7",
            "METHOD": "단독"
          },
          {
            "CHARGER_ID": "03",
            "CHARGER_TYPE": "AC완속",
            "CHARGER_STAT": "사용가능",
            "STATUPDDT": "2025-04-19 19:43",
            "LASTTSDT": "2025-04-13 18:31",
            "LASTTEDT": "2025-04-13 20:11",
            "NOWTSDT": null,
            "OUTPUT": "7",
            "METHOD": "단독"
          },
          {
            "CHARGER_ID": "04",
            "CHARGER_TYPE": "DC콤보",
            "CHARGER_STAT": "사용가능",
            "STATUPDDT": "2025-04-20 05:56",
            "LASTTSDT": "2025-04-07 10:39",
            "LASTTEDT": "2025-04-07 10:54",
            "NOWTSDT": null,
            "OUTPUT": "100",
            "METHOD": "동시"
          }
        ]
      },
      {
        "STAT_NM": "서울 강남 갤러리아백화점 명품관 WEST",
        "STAT_ID": "HW001013",
        "STAT_ADDR": "서울특별시 강남구 압구정로 343",
        "STAT_X": "127.040104",
        "STAT_Y": "37.5284458",
        "STAT_USETIME": "10:30 ~ 20:00",
        "STAT_PARKPAY": "N",
        "STAT_LIMITYN": "N",
        "STAT_LIMITDETAIL": "백화점 영업시간에만 운영",
        "STAT_KINDDETAIL": "백화점",
        "CHARGER_DETAILS": [
          {
            "CHARGER_ID": "01",
            "CHARGER_TYPE": "DC콤보",
            "CHARGER_STAT": "사용가능",
            "STATUPDDT": "2025-04-20 21:37",
            "LASTTSDT": "2025-04-19 15:45",
            "LASTTEDT": "2025-04-19 16:22",
            "NOWTSDT": null,
            "OUTPUT": "100",
            "METHOD": "단독"
          },
          {
            "CHARGER_ID": "02",
            "CHARGER_TYPE": "AC완속",
            "CHARGER_STAT": "사용가능",
            "STATUPDDT": "2025-04-21 04:03",
            "LASTTSDT": "2025-04-20 23:19",
            "LASTTEDT": "2025-04-21 04:02",
            "NOWTSDT": null,
            "OUTPUT": "7",
            "METHOD": "단독"
          },
          {
            "CHARGER_ID": "03",
            "CHARGER_TYPE": "AC완속",
            "CHARGER_STAT": "사용가능",
            "STATUPDDT": "2025-04-21 02:34",
            "LASTTSDT": "2025-04-20 23:42",
            "LASTTEDT": "2025-04-21 02:33",
            "NOWTSDT": null,
            "OUTPUT": "7",
            "METHOD": "단독"
          },
          {
            "CHARGER_ID": "04",
            "CHARGER_TYPE": "DC콤보",
            "CHARGER_STAT": "사용가능",
            "STATUPDDT": "2025-04-20 15:34",
            "LASTTSDT": "2025-04-19 18:50",
            "LASTTEDT": "2025-04-19 19:38",
            "NOWTSDT": null,
            "OUTPUT": "100",
            "METHOD": "동시"
          }
        ]
      },
      {
        "STAT_NM": "서울강남 대우로얄카운티2",
        "STAT_ID": "EV014559",
        "STAT_ADDR": "서울특별시 강남구 도산대로81길 26",
        "STAT_X": "127.0475645",
        "STAT_Y": "37.5260482",
        "STAT_USETIME": "24시간 이용가능",
        "STAT_PARKPAY": "N",
        "STAT_LIMITYN": "Y",
        "STAT_LIMITDETAIL": "외부인 사용불가",
        "STAT_KINDDETAIL": "빌라",
        "CHARGER_DETAILS": [
          {
            "CHARGER_ID": "01",
            "CHARGER_TYPE": "AC완속",
            "CHARGER_STAT": "상태미확인",
            "STATUPDDT": "2025-04-20 21:13",
            "LASTTSDT": "2025-04-16 18:58",
            "LASTTEDT": "2025-04-16 22:39",
            "NOWTSDT": null,
            "OUTPUT": "7",
            "METHOD": "단독"
          },
          {
            "CHARGER_ID": "02",
            "CHARGER_TYPE": "AC완속",
            "CHARGER_STAT": "상태미확인",
            "STATUPDDT": "2025-04-20 21:18",
            "LASTTSDT": "2025-04-19 08:39",
            "LASTTEDT": "2025-04-19 18:31",
            "NOWTSDT": null,
            "OUTPUT": "7",
            "METHOD": "단독"
          }
        ]
      },
      {
        "STAT_NM": "청담 네이처포엠",
        "STAT_ID": "NT100161",
        "STAT_ADDR": "서울특별시 강남구 압구정로 461",
        "STAT_X": "127.0472183",
        "STAT_Y": "37.5252175",
        "STAT_USETIME": "24시간 이용가능",
        "STAT_PARKPAY": "N",
        "STAT_LIMITYN": "N",
        "STAT_LIMITDETAIL": "",
        "STAT_KINDDETAIL": "기타",
        "CHARGER_DETAILS": [
          {
            "CHARGER_ID": "01",
            "CHARGER_TYPE": "AC완속",
            "CHARGER_STAT": "사용가능",
            "STATUPDDT": "2025-04-19 15:42",
            "LASTTSDT": "2025-04-19 13:51",
            "LASTTEDT": "2025-04-19 15:42",
            "NOWTSDT": null,
            "OUTPUT": "7",
            "METHOD": "단독"
          },
          {
            "CHARGER_ID": "02",
            "CHARGER_TYPE": "AC완속",
            "CHARGER_STAT": "사용가능",
            "STATUPDDT": "2025-04-12 12:02",
            "LASTTSDT": "2025-04-12 05:33",
            "LASTTEDT": "2025-04-12 12:02",
            "NOWTSDT": null,
            "OUTPUT": "7",
            "METHOD": "단독"
          }
        ]
      },
      {
        "STAT_NM": "청담 아노블리81타워",
        "STAT_ID": "NT100088",
        "STAT_ADDR": "서울특별시 강남구 도산대로 419",
        "STAT_X": "127.041628",
        "STAT_Y": "37.52386862",
        "STAT_USETIME": "24시간 이용가능",
        "STAT_PARKPAY": "N",
        "STAT_LIMITYN": "N",
        "STAT_LIMITDETAIL": "",
        "STAT_KINDDETAIL": "기타",
        "CHARGER_DETAILS": [
          {
            "CHARGER_ID": "01",
            "CHARGER_TYPE": "AC완속",
            "CHARGER_STAT": "사용가능",
            "STATUPDDT": "2025-04-19 17:45",
            "LASTTSDT": "2025-04-19 13:03",
            "LASTTEDT": "2025-04-19 17:45",
            "NOWTSDT": null,
            "OUTPUT": "7",
            "METHOD": "단독"
          },
          {
            "CHARGER_ID": "02",
            "CHARGER_TYPE": "AC완속",
            "CHARGER_STAT": "사용가능",
            "STATUPDDT": "2025-04-21 06:00",
            "LASTTSDT": "2025-04-20 23:06",
            "LASTTEDT": "2025-04-21 06:00",
            "NOWTSDT": null,
            "OUTPUT": "7",
            "METHOD": "단독"
          }
        ]
      }
    ],
    "EVENT_STTS": [
      {
        "EVENT_NM": "[한솥아트스페이스] 제인 마시 Jane Massey， With You",
        "EVENT_PERIOD": "2025-04-04~2025-05-10",
        "EVENT_PLACE": "한솥아트스페이스(서울시 강남구 압구정로 459 B1F)",
        "EVENT_X": 127.047030515103,
        "EVENT_Y": 37.5254941585008,
        "PAY_YN": "N",
        "THUMBNAIL": "https://culture.seoul.go.kr/cmmn/file/getImage.do?atchFileId=1b21f6d910434039a3404f8cfa666c2a&thumb=Y",
        "URL": "https://culture.seoul.go.kr/culture/culture/cultureEvent/view.do?cultcode=153123&menuNo=200009",
        "EVENT_ETC_DETAIL": "없음"
      }
    ],
    "LIVE_CMRCL_STTS": {
      "AREA_CMRCL_LVL": "보통",
      "AREA_SH_PAYMENT_CNT": "64",
      "AREA_SH_PAYMENT_AMT_MIN": 1100000,
      "AREA_SH_PAYMENT_AMT_MAX": 1200000,
      "CMRCL_RSB": [
        {
          "RSB_LRG_CTGR": "음식·음료",
          "RSB_MID_CTGR": "한식",
          "RSB_PAYMENT_LVL": "바쁜",
          "RSB_SH_PAYMENT_CNT": 17,
          "RSB_SH_PAYMENT_AMT_MIN": 250000,
          "RSB_SH_PAYMENT_AMT_MAX": 300000,
          "RSB_MCT_CNT": 55,
          "RSB_MCT_TIME": "202503"
        },
        {
          "RSB_LRG_CTGR": "음식·음료",
          "RSB_MID_CTGR": "일식/중식/양식",
          "RSB_PAYMENT_LVL": "한산한",
          "RSB_SH_PAYMENT_CNT": 4,
          "RSB_SH_PAYMENT_AMT_MIN": 80000,
          "RSB_SH_PAYMENT_AMT_MAX": 90000,
          "RSB_MCT_CNT": 80,
          "RSB_MCT_TIME": "202503"
        },
        {
          "RSB_LRG_CTGR": "음식·음료",
          "RSB_MID_CTGR": "제과/커피/패스트푸드",
          "RSB_PAYMENT_LVL": "분주한",
          "RSB_SH_PAYMENT_CNT": 16,
          "RSB_SH_PAYMENT_AMT_MIN": 150000,
          "RSB_SH_PAYMENT_AMT_MAX": 200000,
          "RSB_MCT_CNT": 17,
          "RSB_MCT_TIME": "202503"
        },
        {
          "RSB_LRG_CTGR": "음식·음료",
          "RSB_MID_CTGR": "기타요식",
          "RSB_PAYMENT_LVL": "보통",
          "RSB_SH_PAYMENT_CNT": 13,
          "RSB_SH_PAYMENT_AMT_MIN": 150000,
          "RSB_SH_PAYMENT_AMT_MAX": 200000,
          "RSB_MCT_CNT": 84,
          "RSB_MCT_TIME": "202503"
        },
        {
          "RSB_LRG_CTGR": "유통",
          "RSB_MID_CTGR": "편의점",
          "RSB_PAYMENT_LVL": "바쁜",
          "RSB_SH_PAYMENT_CNT": 10,
          "RSB_SH_PAYMENT_AMT_MIN": 60000,
          "RSB_SH_PAYMENT_AMT_MAX": 70000,
          "RSB_MCT_CNT": 15,
          "RSB_MCT_TIME": "202503"
        },
        {
          "RSB_LRG_CTGR": "의료",
          "RSB_MID_CTGR": "병원",
          "RSB_PAYMENT_LVL": "한산한",
          "RSB_SH_PAYMENT_CNT": 4,
          "RSB_SH_PAYMENT_AMT_MIN": 400000,
          "RSB_SH_PAYMENT_AMT_MAX": 450000,
          "RSB_MCT_CNT": 132,
          "RSB_MCT_TIME": "202503"
        }
      ],
      "CMRCL_MALE_RATE": 40.1,
      "CMRCL_FEMALE_RATE": 59.9,
      "CMRCL_10_RATE": 0.0,
      "CMRCL_20_RATE": 28.0,
      "CMRCL_30_RATE": 17.1,
      "CMRCL_40_RATE": 17.8,
      "CMRCL_50_RATE": 4.0,
      "CMRCL_60_RATE": 33.2,
      "CMRCL_PERSONAL_RATE": 86.4,
      "CMRCL_CORPORATION_RATE": 13.6,
      "CMRCL_TIME": "20250421 1250"
    }
  }
}